Workbook
Name SegmentaciónDeDatos_Mes_Año: #N/A

Sheet Ordenes
A1: Mes | B1: Fecha_Conta | C1: BELNR_ID | D1: ItemCode | E1: Descripción | F1: Sec | G1: Fecha Inicio | H1: Cantidad Base | I1: Horas | J1: Maquina | K1: Planificado | L1: Proceso | M1: Horas Programadas | N1: Línea | O1: Subcomponente | P1: Estado | Q1: Avance_SAP | R1: Fecha_Gantt_Desde
A2: =+MONTH(Ordenes_Mes[[#This Row],[Fecha_Conta]]) -> 4 | B2: =+VLOOKUP(C2,OP!$A$1:$P$27848,12,FALSE) -> 46113 | C2: 3955 | D2: 2140150001 | E2: Archivador Plastificado Negro, Lomo Ancho, t/Oficio Layconsa Office | F2: =+_xlfn.XLOOKUP(D2,BD_Spec!$A$1:$A$2336,BD_Spec!$L$1:$L$2336) -> 1 | G2: 46113 | H2: =+VLOOKUP(D2,Tiempos!$A$1:$N$7440,3,FALSE) -> 3500 | I2: =+VLOOKUP(D2,Tiempos!$A$1:$N$7440,5,FALSE) -> 12 | J2: =+VLOOKUP(D2,Tiempos!$A$1:$N$7440,7,FALSE) -> AMAN02 | K2: =IF(VLOOKUP(C2,OP!$A$1:$P$27848,4,FALSE)="Cerrado",VLOOKUP(C2,OP!$A$1:$P$27848,10,FALSE),VLOOKUP(C2,OP!$A$1:$P$27848,9,FALSE)) -> 32441 | L2: =IF( IFERROR(VLOOKUP(D2,BD_Spec!$A$1:$D$2300,4,FALSE),"")="Producto Terminado", "TERMINADO", IFERROR(_xlfn.XLOOKUP(Ordenes_Mes[[#This Row],[Maquina]],Tiempos!$G$1:$G$766,Tiempos!$O$1:$O$766),"") ) -> TERMINADO | M2: =IF(OR(Ordenes_Mes[[#This Row],[Proceso]]="Plástico_lima",Ordenes_Mes[[#This Row],[Proceso]]="soplado"),24,12) -> 12 | N2: =+VLOOKUP(D2,BD_Spec!$A$1:$K$2336,7,FALSE) -> Manuales | O2: =+VLOOKUP(D2,BD_Spec!$A$1:$K$2336,8,FALSE) -> Archivador | P2: =+VLOOKUP(C2,OP!$A$1:$P$27848,4,FALSE) -> CERRADO | Q2: =+VLOOKUP(C2,OP!$A$1:$P$27848,10,FALSE) -> 32441 | R2: =+Ordenes_Mes[[#This Row],[Fecha Inicio]] -> 46113
A3: =+MONTH(Ordenes_Mes[[#This Row],[Fecha_Conta]]) -> 4 | B3: =+VLOOKUP(C3,OP!$A$1:$P$27848,12,FALSE) -> 46129 | C3: 4028 | D3: 2140250020 | E3: Papelógrafo Rayado Rllx3 57x83cm 56gr. 25mm | F3: 1 | G3: 46132 | H3: =+VLOOKUP(D3,Tiempos!$A$1:$N$7440,3,FALSE) -> 800 | I3: 12 | J3: =+VLOOKUP(D3,Tiempos!$A$1:$N$7440,7,FALSE) -> AMAN02 | K3: =IF(VLOOKUP(C3,OP!$A$1:$P$27848,4,FALSE)="Cerrado",VLOOKUP(C3,OP!$A$1:$P$27848,10,FALSE),VLOOKUP(C3,OP!$A$1:$P$27848,9,FALSE)) -> 5668 | L3: =IF( IFERROR(VLOOKUP(D3,BD_Spec!$A$1:$D$2300,4,FALSE),"")="Producto Terminado", "TERMINADO", IFERROR(_xlfn.XLOOKUP(Ordenes_Mes[[#This Row],[Maquina]],Tiempos!$G$1:$G$766,Tiempos!$O$1:$O$766),"") ) -> TERMINADO | M3: =IF(OR(Ordenes_Mes[[#This Row],[Proceso]]="Plástico_lima",Ordenes_Mes[[#This Row],[Proceso]]="soplado"),24,12) -> 12 | N3: =+VLOOKUP(D3,BD_Spec!$A$1:$K$2336,7,FALSE) -> Manuales | O3: =+VLOOKUP(D3,BD_Spec!$A$1:$K$2336,8,FALSE) -> Papelería | P3: =+VLOOKUP(C3,OP!$A$1:$P$27848,4,FALSE) -> CERRADO | Q3: =+VLOOKUP(C3,OP!$A$1:$P$27848,10,FALSE) -> 5668 | R3: =+Ordenes_Mes[[#This Row],[Fecha Inicio]] -> 46132
A4: =+MONTH(Ordenes_Mes[[#This Row],[Fecha_Conta]]) -> 4 | B4: =+VLOOKUP(C4,OP!$A$1:$P$27848,12,FALSE) -> 46125 | C4: 4003 | D4: 2310230105 | E4: Frasco Etiquetado Para Témpera 30 cc ARTI P.S. | F4: 1 | G4: 46127 | H4: =+VLOOKUP(D4,Tiempos!$A$1:$N$7440,3,FALSE) -> 25000 | I4: =+VLOOKUP(D4,Tiempos!$A$1:$N$7440,5,FALSE) -> 12 | J4: =+VLOOKUP(D4,Tiempos!$A$1:$N$7440,7,FALSE) -> AMAN02 | K4: =IF(VLOOKUP(C4,OP!$A$1:$P$27848,4,FALSE)="Cerrado",VLOOKUP(C4,OP!$A$1:$P$27848,10,FALSE),VLOOKUP(C4,OP!$A$1:$P$27848,9,FALSE)) -> 223775 | L4: =IF( IFERROR(VLOOKUP(D4,BD_Spec!$A$1:$D$2300,4,FALSE),"")="Producto Terminado", "TERMINADO", IFERROR(_xlfn.XLOOKUP(Ordenes_Mes[[#This Row],[Maquina]],Tiempos!$G$1:$G$766,Tiempos!$O$1:$O$766),"") ) -> ENSAMBLE_LIMA | M4: =IF(OR(Ordenes_Mes[[#This Row],[Proceso]]="Plástico_lima",Ordenes_Mes[[#This Row],[Proceso]]="soplado"),24,12) -> 12 | N4: =+VLOOKUP(D4,BD_Spec!$A$1:$K$2336,7,FALSE) -> Línea_30cc | O4: =+VLOOKUP(D4,BD_Spec!$A$1:$K$2336,8,FALSE) -> Frasco | P4: =+VLOOKUP(C4,OP!$A$1:$P$27848,4,FALSE) -> CERRADO | Q4: =+VLOOKUP(C4,OP!$A$1:$P$27848,10,FALSE) -> 223775 | R4: =+Ordenes_Mes[[#This Row],[Fecha Inicio]] -> 46127
A5: =+MONTH(Ordenes_Mes[[#This Row],[Fecha_Conta]]) -> 4 | B5: =+VLOOKUP(C5,OP!$A$1:$P$27848,12,FALSE) -> 46133 | C5: 4034 | D5: 2140370001 | E5: Papel Crepé Rojo Pqtx1 Layconsa | F5: 2 | G5: 46135 | H5: =+VLOOKUP(D5,Tiempos!$A$1:$N$7440,3,FALSE) -> 800 | I5: 12 | J5: =+VLOOKUP(D5,Tiempos!$A$1:$N$7440,7,FALSE) -> AMAN02 | K5: =IF(VLOOKUP(C5,OP!$A$1:$P$27848,4,FALSE)="Cerrado",VLOOKUP(C5,OP!$A$1:$P$27848,10,FALSE),VLOOKUP(C5,OP!$A$1:$P$27848,9,FALSE)) -> 2895 | L5: =IF( IFERROR(VLOOKUP(D5,BD_Spec!$A$1:$D$2300,4,FALSE),"")="Producto Terminado", "TERMINADO", IFERROR(_xlfn.XLOOKUP(Ordenes_Mes[[#This Row],[Maquina]],Tiempos!$G$1:$G$766,Tiempos!$O$1:$O$766),"") ) -> TERMINADO | M5: =IF(OR(Ordenes_Mes[[#This Row],[Proceso]]="Plástico_lima",Ordenes_Mes[[#This Row],[Proceso]]="soplado"),24,12) -> 12 | N5: =+VLOOKUP(D5,BD_Spec!$A$1:$K$2336,7,FALSE) -> Manuales | O5: =+VLOOKUP(D5,BD_Spec!$A$1:$K$2336,8,FALSE) -> Papelería | P5: =+VLOOKUP(C5,OP!$A$1:$P$27848,4,FALSE) -> CERRADO | Q5: =+VLOOKUP(C5,OP!$A$1:$P$27848,10,FALSE) -> 2895 | R5: =+Ordenes_Mes[[#This Row],[Fecha Inicio]] -> 46135
A6: =+MONTH(Ordenes_Mes[[#This Row],[Fecha_Conta]]) -> 4 | B6: =+VLOOKUP(C6,OP!$A$1:$P$27848,12,FALSE) -> 46135 | C6: 4041 | D6: 2140150001 | E6: Archivador Plastificado Negro, Lomo Ancho, t/Oficio Layconsa Office | F6: 2 | G6: 46136 | H6: =+VLOOKUP(D6,Tiempos!$A$1:$N$7440,3,FALSE) -> 3500 | I6: =+VLOOKUP(D6,Tiempos!$A$1:$N$7440,5,FALSE) -> 12 | J6: =+VLOOKUP(D6,Tiempos!$A$1:$N$7440,7,FALSE) -> AMAN02 | K6: =IF(VLOOKUP(C6,OP!$A$1:$P$27848,4,FALSE)="Cerrado",VLOOKUP(C6,OP!$A$1:$P$27848,10,FALSE),VLOOKUP(C6,OP!$A$1:$P$27848,9,FALSE)) -> 4944 | L6: =IF( IFERROR(VLOOKUP(D6,BD_Spec!$A$1:$D$2300,4,FALSE),"")="Producto Terminado", "TERMINADO", IFERROR(_xlfn.XLOOKUP(Ordenes_Mes[[#This Row],[Maquina]],Tiempos!$G$1:$G$766,Tiempos!$O$1:$O$766),"") ) -> TERMINADO | M6: =IF(OR(Ordenes_Mes[[#This Row],[Proceso]]="Plástico_lima",Ordenes_Mes[[#This Row],[Proceso]]="soplado"),24,12) -> 12 | N6: =+VLOOKUP(D6,BD_Spec!$A$1:$K$2336,7,FALSE) -> Manuales | O6: =+VLOOKUP(D6,BD_Spec!$A$1:$K$2336,8,FALSE) -> Archivador | P6: =+VLOOKUP(C6,OP!$A$1:$P$27848,4,FALSE) -> CERRADO | Q6: =+VLOOKUP(C6,OP!$A$1:$P$27848,10,FALSE) -> 4944 | R6: =+Ordenes_Mes[[#This Row],[Fecha Inicio]] -> 46136
A7: =+MONTH(Ordenes_Mes[[#This Row],[Fecha_Conta]]) -> 4 | B7: =+VLOOKUP(C7,OP!$A$1:$P$27848,12,FALSE) -> 46133 | C7: 4035 | D7: 2140370002 | E7: Papel Crepé Blanco Pqtx1 Layconsa | F7: 3 | G7: 46135 | H7: =+VLOOKUP(D7,Tiempos!$A$1:$N$7440,3,FALSE) -> 800 | I7: 12 | J7: =+VLOOKUP(D7,Tiempos!$A$1:$N$7440,7,FALSE) -> AMAN02 | K7: =IF(VLOOKUP(C7,OP!$A$1:$P$27848,4,FALSE)="Cerrado",VLOOKUP(C7,OP!$A$1:$P$27848,10,FALSE),VLOOKUP(C7,OP!$A$1:$P$27848,9,FALSE)) -> 1901 | L7: =IF( IFERROR(VLOOKUP(D7,BD_Spec!$A$1:$D$2300,4,FALSE),"")="Producto Terminado", "TERMINADO", IFERROR(_xlfn.XLOOKUP(Ordenes_Mes[[#This Row],[Maquina]],Tiempos!$G$1:$G$766,Tiempos!$O$1:$O$766),"") ) -> TERMINADO | M7: =IF(OR(Ordenes_Mes[[#This Row],[Proceso]]="Plástico_lima",Ordenes_Mes[[#This Row],[Proceso]]="soplado"),24,12) -> 12 | N7: =+VLOOKUP(D7,BD_Spec!$A$1:$K$2336,7,FALSE) -> Manuales | O7: =+VLOOKUP(D7,BD_Spec!$A$1:$K$2336,8,FALSE) -> Papelería | P7: =+VLOOKUP(C7,OP!$A$1:$P$27848,4,FALSE) -> CERRADO | Q7: =+VLOOKUP(C7,OP!$A$1:$P$27848,10,FALSE) -> 1901 | R7: =+Ordenes_Mes[[#This Row],[Fecha Inicio]] -> 46135
A8: =+MONTH(Ordenes_Mes[[#This Row],[Fecha_Conta]]) -> 4 | B8: =+VLOOKUP(C8,OP!$A$1:$P$27848,12,FALSE) -> 46133 | C8: 4036 | D8: 2140370011 | E8: Papel Crepé Verde Claro Pqtx1 Layconsa | F8: 4 | G8: 46134 | H8: =+VLOOKUP(D8,Tiempos!$A$1:$N$7440,3,FALSE) -> 800 | I8: 12 | J8: =+VLOOKUP(D8,Tiempos!$A$1:$N$7440,7,FALSE) -> AMAN02 | K8: =IF(VLOOKUP(C8,OP!$A$1:$P$27848,4,FALSE)="Cerrado",VLOOKUP(C8,OP!$A$1:$P$27848,10,FALSE),VLOOKUP(C8,OP!$A$1:$P$27848,9,FALSE)) -> 3051 | L8: =IF( IFERROR(VLOOKUP(D8,BD_Spec!$A$1:$D$2300,4,FALSE),"")="Producto Terminado", "TERMINADO", IFERROR(_xlfn.XLOOKUP(Ordenes_Mes[[#This Row],[Maquina]],Tiempos!$G$1:$G$766,Tiempos!$O$1:$O$766),"") ) -> TERMINADO | M8: =IF(OR(Ordenes_Mes[[#This Row],[Proceso]]="Plástico_lima",Ordenes_Mes[[#This Row],[Proceso]]="soplado"),24,12) -> 12 | N8: =+VLOOKUP(D8,BD_Spec!$A$1:$K$2336,7,FALSE) -> Manuales | O8: =+VLOOKUP(D8,BD_Spec!$A$1:$K$2336,8,FALSE) -> Papelería | P8: =+VLOOKUP(C8,OP!$A$1:$P$27848,4,FALSE) -> CERRADO | Q8: =+VLOOKUP(C8,OP!$A$1:$P$27848,10,FALSE) -> 3051 | R8: =+Ordenes_Mes[[#This Row],[Fecha Inicio]] -> 46134
A9: =+MONTH(Ordenes_Mes[[#This Row],[Fecha_Conta]]) -> 4 | B9: =+VLOOKUP(C9,OP!$A$1:$P$27848,12,FALSE) -> 46125 | C9: 4006 | D9: 2310320328 | E9: Carga Para Bolígrafo 036 PFTR Azul N | F9: 1 | G9: 46127 | H9: =+VLOOKUP(D9,Tiempos!$A$1:$N$7440,3,FALSE) -> 35000 | I9: =+VLOOKUP(D9,Tiempos!$A$1:$N$7440,5,FALSE) -> 12 | J9: =+VLOOKUP(D9,Tiempos!$A$1:$N$7440,7,FALSE) -> CAR02 | K9: =IF(VLOOKUP(C9,OP!$A$1:$P$27848,4,FALSE)="Cerrado",VLOOKUP(C9,OP!$A$1:$P$27848,10,FALSE),VLOOKUP(C9,OP!$A$1:$P$27848,9,FALSE)) -> 220032 | L9: =IF( IFERROR(VLOOKUP(D9,BD_Spec!$A$1:$D$2300,4,FALSE),"")="Producto Terminado", "TERMINADO", IFERROR(_xlfn.XLOOKUP(Ordenes_Mes[[#This Row],[Maquina]],Tiempos!$G$1:$G$766,Tiempos!$O$1:$O$766),"") ) -> ENSAMBLE_LIMA | M9: =IF(OR(Ordenes_Mes[[#This Row],[Proceso]]="Plástico_lima",Ordenes_Mes[[#This Row],[Proceso]]="soplado"),24,12) -> 12 | N9: =+VLOOKUP(D9,BD_Spec!$A$1:$K$2336,7,FALSE) -> Línea_036 | O9: =+VLOOKUP(D9,BD_Spec!$A$1:$K$2336,8,FALSE) -> Colores | P9: =+VLOOKUP(C9,OP!$A$1:$P$27848,4,FALSE) -> CERRADO | Q9: =+VLOOKUP(C9,OP!$A$1:$P$27848,10,FALSE) -> 220032 | R9: =+Ordenes_Mes[[#This Row],[Fecha Inicio]] -> 46127
A10: =+MONTH(Ordenes_Mes[[#This Row],[Fecha_Conta]]) -> 4 | B10: =+VLOOKUP(C10,OP!$A$1:$P$27848,12,FALSE) -> 46113 | C10: 4007 | D10: 2310320329 | E10: Carga Para Bolígrafo 036 PFTR Rojo N | F10: 2 | G10: 46132 | H10: =+VLOOKUP(D10,Tiempos!$A$1:$N$7440,3,FALSE) -> 35000 | I10: =+VLOOKUP(D10,Tiempos!$A$1:$N$7440,5,FALSE) -> 12 | J10: =+VLOOKUP(D10,Tiempos!$A$1:$N$7440,7,FALSE) -> CAR02 | K10: =IF(VLOOKUP(C10,OP!$A$1:$P$27848,4,FALSE)="Cerrado",VLOOKUP(C10,OP!$A$1:$P$27848,10,FALSE),VLOOKUP(C10,OP!$A$1:$P$27848,9,FALSE)) -> 61920 | L10: =IF( IFERROR(VLOOKUP(D10,BD_Spec!$A$1:$D$2300,4,FALSE),"")="Producto Terminado", "TERMINADO", IFERROR(_xlfn.XLOOKUP(Ordenes_Mes[[#This Row],[Maquina]],Tiempos!$G$1:$G$766,Tiempos!$O$1:$O$766),"") ) -> ENSAMBLE_LIMA | M10: =IF(OR(Ordenes_Mes[[#This Row],[Proceso]]="Plástico_lima",Ordenes_Mes[[#This Row],[Proceso]]="soplado"),24,12) -> 12 | N10: =+VLOOKUP(D10,BD_Spec!$A$1:$K$2336,7,FALSE) -> Línea_036 | O10: =+VLOOKUP(D10,BD_Spec!$A$1:$K$2336,8,FALSE) -> Colores | P10: =+VLOOKUP(C10,OP!$A$1:$P$27848,4,FALSE) -> CERRADO | Q10: =+VLOOKUP(C10,OP!$A$1:$P$27848,10,FALSE) -> 61920 | R10: =+Ordenes_Mes[[#This Row],[Fecha Inicio]] -> 46132
A11: =+MONTH(Ordenes_Mes[[#This Row],[Fecha_Conta]]) -> 4 | B11: =+VLOOKUP(C11,OP!$A$1:$P$27848,12,FALSE) -> 46132 | C11: 3989 | D11: 2110030170 | E11: Témperas Set x 7 x 30cc ARTI | F11: 1 | G11: 46132 | H11: =+VLOOKUP(D11,Tiempos!$A$1:$N$7440,3,FALSE) -> 6000 | I11: =+VLOOKUP(D11,Tiempos!$A$1:$N$7440,5,FALSE) -> 12 | J11: =+VLOOKUP(D11,Tiempos!$A$1:$N$7440,7,FALSE) -> DOSI_TEMP01 | K11: =IF(VLOOKUP(C11,OP!$A$1:$P$27848,4,FALSE)="Cerrado",VLOOKUP(C11,OP!$A$1:$P$27848,10,FALSE),VLOOKUP(C11,OP!$A$1:$P$27848,9,FALSE)) -> 25920 | L11: =IF( IFERROR(VLOOKUP(D11,BD_Spec!$A$1:$D$2300,4,FALSE),"")="Producto Terminado", "TERMINADO", IFERROR(_xlfn.XLOOKUP(Ordenes_Mes[[#This Row],[Maquina]],Tiempos!$G$1:$G$766,Tiempos!$O$1:$O$766),"") ) -> TERMINADO | M11: =IF(OR(Ordenes_Mes[[#This Row],[Proceso]]="Plástico_lima",Ordenes_Mes[[#This Row],[Proceso]]="soplado"),24,12) -> 12 | N11: =+VLOOKUP(D11,BD_Spec!$A$1:$K$2336,7,FALSE) -> Línea_30cc | O11: =+VLOOKUP(D11,BD_Spec!$A$1:$K$2336,8,FALSE) -> Témpera | P11: =+VLOOKUP(C11,OP!$A$1:$P$27848,4,FALSE) -> CERRADO | Q11: =+VLOOKUP(C11,OP!$A$1:$P$27848,10,FALSE) -> 25920 | R11: =+Ordenes_Mes[[#This Row],[Fecha Inicio]] -> 46132
A12: =+MONTH(Ordenes_Mes[[#This Row],[Fecha_Conta]]) -> 4 | B12: =+VLOOKUP(C12,OP!$A$1:$P$27848,12,FALSE) -> 46121 | C12: 3983 | D12: 2110040047 | E12: Crayón triangular cj. cartón Layconsa Puppy Jumbo x 12 | F12: 1 | G12: 46121 | H12: =+VLOOKUP(D12,Tiempos!$A$1:$N$7440,3,FALSE) -> 4000 | I12: 12 | J12: =+VLOOKUP(D12,Tiempos!$A$1:$N$7440,7,FALSE) -> ENCJ03 | K12: =IF(VLOOKUP(C12,OP!$A$1:$P$27848,4,FALSE)="Cerrado",VLOOKUP(C12,OP!$A$1:$P$27848,10,FALSE),VLOOKUP(C12,OP!$A$1:$P$27848,9,FALSE)) -> 3680 | L12: =IF( IFERROR(VLOOKUP(D12,BD_Spec!$A$1:$D$2300,4,FALSE),"")="Producto Terminado", "TERMINADO", IFERROR(_xlfn.XLOOKUP(Ordenes_Mes[[#This Row],[Maquina]],Tiempos!$G$1:$G$766,Tiempos!$O$1:$O$766),"") ) -> TERMINADO | M12: =IF(OR(Ordenes_Mes[[#This Row],[Proceso]]="Plástico_lima",Ordenes_Mes[[#This Row],[Proceso]]="soplado"),24,12) -> 12 | N12: =+VLOOKUP(D12,BD_Spec!$A$1:$K$2336,7,FALSE) -> Línea_Crayón | O12: =+VLOOKUP(D12,BD_Spec!$A$1:$K$2336,8,FALSE) -> Crayones | P12: =+VLOOKUP(C12,OP!$A$1:$P$27848,4,FALSE) -> CERRADO | Q12: =+VLOOKUP(C12,OP!$A$1:$P$27848,10,FALSE) -> 3680 | R12: =+Ordenes_Mes[[#This Row],[Fecha Inicio]] -> 46121
A13: =+MONTH(Ordenes_Mes[[#This Row],[Fecha_Conta]]) -> 4 | B13: =+VLOOKUP(C13,OP!$A$1:$P$27848,12,FALSE) -> 46119 | C13: 3980 | D13: 2310210138 | E13: Plumones LYC School 45 Granel Piel NP P.S. | F13: 1 | G13: 46119 | H13: =+VLOOKUP(D13,Tiempos!$A$1:$N$7440,3,FALSE) -> 50000 | I13: =+VLOOKUP(D13,Tiempos!$A$1:$N$7440,5,FALSE) -> 12 | J13: =+VLOOKUP(D13,Tiempos!$A$1:$N$7440,7,FALSE) -> ENS02 | K13: =IF(VLOOKUP(C13,OP!$A$1:$P$27848,4,FALSE)="Cerrado",VLOOKUP(C13,OP!$A$1:$P$27848,10,FALSE),VLOOKUP(C13,OP!$A$1:$P$27848,9,FALSE)) -> 11450 | L13: =IF( IFERROR(VLOOKUP(D13,BD_Spec!$A$1:$D$2300,4,FALSE),"")="Producto Terminado", "TERMINADO", IFERROR(_xlfn.XLOOKUP(Ordenes_Mes[[#This Row],[Maquina]],Tiempos!$G$1:$G$766,Tiempos!$O$1:$O$766),"") ) -> ENSAMBLE_LIMA | M13: =IF(OR(Ordenes_Mes[[#This Row],[Proceso]]="Plástico_lima",Ordenes_Mes[[#This Row],[Proceso]]="soplado"),24,12) -> 12 | N13: =+VLOOKUP(D13,BD_Spec!$A$1:$K$2336,7,FALSE) -> Línea_045 | O13: =+VLOOKUP(D13,BD_Spec!$A$1:$K$2336,8,FALSE) -> Ensamble_12 | P13: =+VLOOKUP(C13,OP!$A$1:$P$27848,4,FALSE) -> CERRADO | Q13: =+VLOOKUP(C13,OP!$A$1:$P$27848,10,FALSE) -> 11450 | R13: =+Ordenes_Mes[[#This Row],[Fecha Inicio]] -> 46119
A14: =+MONTH(Ordenes_Mes[[#This Row],[Fecha_Conta]]) -> 4 | B14: =+VLOOKUP(C14,OP!$A$1:$P$27848,12,FALSE) -> 46135 | C14: 4042 | D14: 2310210133 | E14: Plumones LYC School 45 Granel Anaranjado NP P.S. | F14: 2 | G14: 46136 | H14: =+VLOOKUP(D14,Tiempos!$A$1:$N$7440,3,FALSE) -> 50000 | I14: =+VLOOKUP(D14,Tiempos!$A$1:$N$7440,5,FALSE) -> 12 | J14: =+VLOOKUP(D14,Tiempos!$A$1:$N$7440,7,FALSE) -> ENS02 | K14: =IF(VLOOKUP(C14,OP!$A$1:$P$27848,4,FALSE)="Cerrado",VLOOKUP(C14,OP!$A$1:$P$27848,10,FALSE),VLOOKUP(C14,OP!$A$1:$P$27848,9,FALSE)) -> 50000 | L14: =IF( IFERROR(VLOOKUP(D14,BD_Spec!$A$1:$D$2300,4,FALSE),"")="Producto Terminado", "TERMINADO", IFERROR(_xlfn.XLOOKUP(Ordenes_Mes[[#This Row],[Maquina]],Tiempos!$G$1:$G$766,Tiempos!$O$1:$O$766),"") ) -> ENSAMBLE_LIMA | M14: =IF(OR(Ordenes_Mes[[#This Row],[Proceso]]="Plástico_lima",Ordenes_Mes[[#This Row],[Proceso]]="soplado"),24,12) -> 12 | N14: =+VLOOKUP(D14,BD_Spec!$A$1:$K$2336,7,FALSE) -> Línea_045 | O14: =+VLOOKUP(D14,BD_Spec!$A$1:$K$2336,8,FALSE) -> Ensamble_12 | P14: =+VLOOKUP(C14,OP!$A$1:$P$27848,4,FALSE) -> CERRADO | Q14: =+VLOOKUP(C14,OP!$A$1:$P$27848,10,FALSE) -> 50000 | R14: =+Ordenes_Mes[[#This Row],[Fecha Inicio]] -> 46136
A15: =+MONTH(Ordenes_Mes[[#This Row],[Fecha_Conta]]) -> 4 | B15: =+VLOOKUP(C15,OP!$A$1:$P$27848,12,FALSE) -> 46113 | C15: 3940 | D15: 2110080227 | E15: Bolígrafo Layconsa crystal L-036 Azul | F15: =+_xlfn.XLOOKUP(D15,BD_Spec!$A$1:$A$2336,BD_Spec!$L$1:$L$2336) -> 1 | G15: 46113 | H15: =+VLOOKUP(D15,Tiempos!$A$1:$N$7440,3,FALSE) -> 35000 | I15: =+VLOOKUP(D15,Tiempos!$A$1:$N$7440,5,FALSE) -> 12 | J15: =+VLOOKUP(D15,Tiempos!$A$1:$N$7440,7,FALSE) -> ENS03 | K15: =IF(VLOOKUP(C15,OP!$A$1:$P$27848,4,FALSE)="Cerrado",VLOOKUP(C15,OP!$A$1:$P$27848,10,FALSE),VLOOKUP(C15,OP!$A$1:$P$27848,9,FALSE)) -> 35000 | L15: =IF( IFERROR(VLOOKUP(D15,BD_Spec!$A$1:$D$2300,4,FALSE),"")="Producto Terminado", "TERMINADO", IFERROR(_xlfn.XLOOKUP(Ordenes_Mes[[#This Row],[Maquina]],Tiempos!$G$1:$G$766,Tiempos!$O$1:$O$766),"") ) -> TERMINADO | M15: =IF(OR(Ordenes_Mes[[#This Row],[Proceso]]="Plástico_lima",Ordenes_Mes[[#This Row],[Proceso]]="soplado"),24,12) -> 12 | N15: =+VLOOKUP(D15,BD_Spec!$A$1:$K$2336,7,FALSE) -> Línea_036 | O15: =+VLOOKUP(D15,BD_Spec!$A$1:$K$2336,8,FALSE) -> N/A | P15: =+VLOOKUP(C15,OP!$A$1:$P$27848,4,FALSE) -> CERRADO | Q15: =+VLOOKUP(C15,OP!$A$1:$P$27848,10,FALSE) -> 35000 | R15: =+Ordenes_Mes[[#This Row],[Fecha Inicio]] -> 46113
A16: =+MONTH(Ordenes_Mes[[#This Row],[Fecha_Conta]]) -> 4 | B16: =+VLOOKUP(C16,OP!$A$1:$P$27848,12,FALSE) -> 46139 | C16: 4097 | D16: 2110080228 | E16: Bolígrafo Layconsa crystal L-036 Negro | F16: 1 | G16: 46139 | H16: =+VLOOKUP(D16,Tiempos!$A$1:$N$7440,3,FALSE) -> 35000 | I16: =+VLOOKUP(D16,Tiempos!$A$1:$N$7440,5,FALSE) -> 12 | J16: =+VLOOKUP(D16,Tiempos!$A$1:$N$7440,7,FALSE) -> ENS03 | K16: =IF(VLOOKUP(C16,OP!$A$1:$P$27848,4,FALSE)="Cerrado",VLOOKUP(C16,OP!$A$1:$P$27848,10,FALSE),VLOOKUP(C16,OP!$A$1:$P$27848,9,FALSE)) -> 50000 | L16: =IF( IFERROR(VLOOKUP(D16,BD_Spec!$A$1:$D$2300,4,FALSE),"")="Producto Terminado", "TERMINADO", IFERROR(_xlfn.XLOOKUP(Ordenes_Mes[[#This Row],[Maquina]],Tiempos!$G$1:$G$766,Tiempos!$O$1:$O$766),"") ) -> TERMINADO | M16: =IF(OR(Ordenes_Mes[[#This Row],[Proceso]]="Plástico_lima",Ordenes_Mes[[#This Row],[Proceso]]="soplado"),24,12) -> 12 | N16: =+VLOOKUP(D16,BD_Spec!$A$1:$K$2336,7,FALSE) -> Línea_036 | O16: =+VLOOKUP(D16,BD_Spec!$A$1:$K$2336,8,FALSE) -> N/A | P16: =+VLOOKUP(C16,OP!$A$1:$P$27848,4,FALSE) -> CERRADO | Q16: =+VLOOKUP(C16,OP!$A$1:$P$27848,10,FALSE) -> 50000 | R16: =+Ordenes_Mes[[#This Row],[Fecha Inicio]] -> 46139
A17: =+MONTH(Ordenes_Mes[[#This Row],[Fecha_Conta]]) -> 4 | B17: =+VLOOKUP(C17,OP!$A$1:$P$27848,12,FALSE) -> 46125 | C17: 4009 | D17: 2310340006 | E17: Punta Carga 036F + Adaptador | F17: 1 | G17: 46127 | H17: =+VLOOKUP(D17,Tiempos!$A$1:$N$7440,3,FALSE) -> 30000 | I17: =+VLOOKUP(D17,Tiempos!$A$1:$N$7440,5,FALSE) -> 12 | J17: =+VLOOKUP(D17,Tiempos!$A$1:$N$7440,7,FALSE) -> ENS05 | K17: =IF(VLOOKUP(C17,OP!$A$1:$P$27848,4,FALSE)="Cerrado",VLOOKUP(C17,OP!$A$1:$P$27848,10,FALSE),VLOOKUP(C17,OP!$A$1:$P$27848,9,FALSE)) -> 500550 | L17: =IF( IFERROR(VLOOKUP(D17,BD_Spec!$A$1:$D$2300,4,FALSE),"")="Producto Terminado", "TERMINADO", IFERROR(_xlfn.XLOOKUP(Ordenes_Mes[[#This Row],[Maquina]],Tiempos!$G$1:$G$766,Tiempos!$O$1:$O$766),"") ) -> ENSAMBLE_LIMA | M17: =IF(OR(Ordenes_Mes[[#This Row],[Proceso]]="Plástico_lima",Ordenes_Mes[[#This Row],[Proceso]]="soplado"),24,12) -> 12 | N17: =+VLOOKUP(D17,BD_Spec!$A$1:$K$2336,7,FALSE) -> Línea_036 | O17: =+VLOOKUP(D17,BD_Spec!$A$1:$K$2336,8,FALSE) -> Colores | P17: =+VLOOKUP(C17,OP!$A$1:$P$27848,4,FALSE) -> CERRADO | Q17: =+VLOOKUP(C17,OP!$A$1:$P$27848,10,FALSE) -> 500550 | R17: =+Ordenes_Mes[[#This Row],[Fecha Inicio]] -> 46127
A18: =+MONTH(Ordenes_Mes[[#This Row],[Fecha_Conta]]) -> 4 | B18: =+VLOOKUP(C18,OP!$A$1:$P$27848,12,FALSE) -> 46121 | C18: 3986 | D18: 2310360001 | E18: Tubito Para Bolígrafo 036 | F18: 1 | G18: 46120 | H18: =+VLOOKUP(D18,Tiempos!$A$1:$N$7440,3,FALSE) -> 50000 | I18: =+VLOOKUP(D18,Tiempos!$A$1:$N$7440,5,FALSE) -> 12 | J18: =+VLOOKUP(D18,Tiempos!$A$1:$N$7440,7,FALSE) -> EXT01 | K18: 830000 | L18: =IF( IFERROR(VLOOKUP(D18,BD_Spec!$A$1:$D$2300,4,FALSE),"")="Producto Terminado", "TERMINADO", IFERROR(_xlfn.XLOOKUP(Ordenes_Mes[[#This Row],[Maquina]],Tiempos!$G$1:$G$766,Tiempos!$O$1:$O$766),"") ) -> ENSAMBLE_LIMA | M18: =IF(OR(Ordenes_Mes[[#This Row],[Proceso]]="Plástico_lima",Ordenes_Mes[[#This Row],[Proceso]]="soplado"),24,12) -> 12 | N18: =+VLOOKUP(D18,BD_Spec!$A$1:$K$2336,7,FALSE) -> Línea_036 | O18: =+VLOOKUP(D18,BD_Spec!$A$1:$K$2336,8,FALSE) -> Tubo | P18: =+VLOOKUP(C18,OP!$A$1:$P$27848,4,FALSE) -> CERRADO | Q18: =+VLOOKUP(C18,OP!$A$1:$P$27848,10,FALSE) -> 754833 | R18: =+Ordenes_Mes[[#This Row],[Fecha Inicio]] -> 46120
A19: =+MONTH(Ordenes_Mes[[#This Row],[Fecha_Conta]]) -> 4 | B19: =+VLOOKUP(C19,OP!$A$1:$P$27848,12,FALSE) -> 46118 | C19: 3925 | D19: 2310040362 | E19: Formado Crayón Triangular Jumbo LYC Amarillo | F19: =+_xlfn.XLOOKUP(D19,BD_Spec!$A$1:$A$2336,BD_Spec!$L$1:$L$2336) -> 1 | G19: 46118 | H19: =+VLOOKUP(D19,Tiempos!$A$1:$N$7440,3,FALSE) -> 25000 | I19: =+VLOOKUP(D19,Tiempos!$A$1:$N$7440,5,FALSE) -> 12 | J19: =+VLOOKUP(D19,Tiempos!$A$1:$N$7440,7,FALSE) -> FORM01 | K19: =IF(VLOOKUP(C19,OP!$A$1:$P$27848,4,FALSE)="Cerrado",VLOOKUP(C19,OP!$A$1:$P$27848,10,FALSE),VLOOKUP(C19,OP!$A$1:$P$27848,9,FALSE)) -> 6401 | L19: =IF( IFERROR(VLOOKUP(D19,BD_Spec!$A$1:$D$2300,4,FALSE),"")="Producto Terminado", "TERMINADO", IFERROR(_xlfn.XLOOKUP(Ordenes_Mes[[#This Row],[Maquina]],Tiempos!$G$1:$G$766,Tiempos!$O$1:$O$766),"") ) -> MASAS_TINTAS_LIMA | M19: =IF(OR(Ordenes_Mes[[#This Row],[Proceso]]="Plástico_lima",Ordenes_Mes[[#This Row],[Proceso]]="soplado"),24,12) -> 12 | N19: =+VLOOKUP(D19,BD_Spec!$A$1:$K$2336,7,FALSE) -> Línea_Crayón | O19: =+VLOOKUP(D19,BD_Spec!$A$1:$K$2336,8,FALSE) -> Crayón_Triángular | P19: =+VLOOKUP(C19,OP!$A$1:$P$27848,4,FALSE) -> CERRADO | Q19: =+VLOOKUP(C19,OP!$A$1:$P$27848,10,FALSE) -> 6401 | R19: =+Ordenes_Mes[[#This Row],[Fecha Inicio]] -> 46118
A20: =+MONTH(Ordenes_Mes[[#This Row],[Fecha_Conta]]) -> 4 | B20: =+VLOOKUP(C20,OP!$A$1:$P$27848,12,FALSE) -> 46118 | C20: 3926 | D20: 2310040364 | E20: Formado Crayón Triangular Jumbo LYC Anaranjado | F20: =+_xlfn.XLOOKUP(D20,BD_Spec!$A$1:$A$2336,BD_Spec!$L$1:$L$2336) -> 2 | G20: 46118 | H20: =+VLOOKUP(D20,Tiempos!$A$1:$N$7440,3,FALSE) -> 25000 | I20: =+VLOOKUP(D20,Tiempos!$A$1:$N$7440,5,FALSE) -> 12 | J20: =+VLOOKUP(D20,Tiempos!$A$1:$N$7440,7,FALSE) -> FORM01 | K20: =IF(VLOOKUP(C20,OP!$A$1:$P$27848,4,FALSE)="Cerrado",VLOOKUP(C20,OP!$A$1:$P$27848,10,FALSE),VLOOKUP(C20,OP!$A$1:$P$27848,9,FALSE)) -> 5972 | L20: =IF( IFERROR(VLOOKUP(D20,BD_Spec!$A$1:$D$2300,4,FALSE),"")="Producto Terminado", "TERMINADO", IFERROR(_xlfn.XLOOKUP(Ordenes_Mes[[#This Row],[Maquina]],Tiempos!$G$1:$G$766,Tiempos!$O$1:$O$766),"") ) -> MASAS_TINTAS_LIMA | M20: =IF(OR(Ordenes_Mes[[#This Row],[Proceso]]="Plástico_lima",Ordenes_Mes[[#This Row],[Proceso]]="soplado"),24,12) -> 12 | N20: =+VLOOKUP(D20,BD_Spec!$A$1:$K$2336,7,FALSE) -> Línea_Crayón | O20: =+VLOOKUP(D20,BD_Spec!$A$1:$K$2336,8,FALSE) -> Crayón_Triángular | P20: =+VLOOKUP(C20,OP!$A$1:$P$27848,4,FALSE) -> CERRADO | Q20: =+VLOOKUP(C20,OP!$A$1:$P$27848,10,FALSE) -> 5972 | R20: =+Ordenes_Mes[[#This Row],[Fecha Inicio]] -> 46118
A21: =+MONTH(Ordenes_Mes[[#This Row],[Fecha_Conta]]) -> 4 | B21: =+VLOOKUP(C21,OP!$A$1:$P$27848,12,FALSE) -> 46118 | C21: 3933 | D21: 2310040371 | E21: Formado Crayón Triangular Jumbo LYC Rosado | F21: =+_xlfn.XLOOKUP(D21,BD_Spec!$A$1:$A$2336,BD_Spec!$L$1:$L$2336) -> 3 | G21: 46118 | H21: =+VLOOKUP(D21,Tiempos!$A$1:$N$7440,3,FALSE) -> 25000 | I21: =+VLOOKUP(D21,Tiempos!$A$1:$N$7440,5,FALSE) -> 12 | J21: =+VLOOKUP(D21,Tiempos!$A$1:$N$7440,7,FALSE) -> FORM01 | K21: =IF(VLOOKUP(C21,OP!$A$1:$P$27848,4,FALSE)="Cerrado",VLOOKUP(C21,OP!$A$1:$P$27848,10,FALSE),VLOOKUP(C21,OP!$A$1:$P$27848,9,FALSE)) -> 6066 | L21: =IF( IFERROR(VLOOKUP(D21,BD_Spec!$A$1:$D$2300,4,FALSE),"")="Producto Terminado", "TERMINADO", IFERROR(_xlfn.XLOOKUP(Ordenes_Mes[[#This Row],[Maquina]],Tiempos!$G$1:$G$766,Tiempos!$O$1:$O$766),"") ) -> MASAS_TINTAS_LIMA | M21: =IF(OR(Ordenes_Mes[[#This Row],[Proceso]]="Plástico_lima",Ordenes_Mes[[#This Row],[Proceso]]="soplado"),24,12) -> 12 | N21: =+VLOOKUP(D21,BD_Spec!$A$1:$K$2336,7,FALSE) -> Línea_Crayón | O21: =+VLOOKUP(D21,BD_Spec!$A$1:$K$2336,8,FALSE) -> Crayón_Triángular | P21: =+VLOOKUP(C21,OP!$A$1:$P$27848,4,FALSE) -> CERRADO | Q21: =+VLOOKUP(C21,OP!$A$1:$P$27848,10,FALSE) -> 6066 | R21: =+Ordenes_Mes[[#This Row],[Fecha Inicio]] -> 46118
A22: =+MONTH(Ordenes_Mes[[#This Row],[Fecha_Conta]]) -> 4 | B22: =+VLOOKUP(C22,OP!$A$1:$P$27848,12,FALSE) -> 46118 | C22: 3924 | D22: 2310040361 | E22: Formado Crayón Triangular Jumbo LYC Rojo | F22: =+_xlfn.XLOOKUP(D22,BD_Spec!$A$1:$A$2336,BD_Spec!$L$1:$L$2336) -> 4 | G22: 46118 | H22: =+VLOOKUP(D22,Tiempos!$A$1:$N$7440,3,FALSE) -> 25000 | I22: =+VLOOKUP(D22,Tiempos!$A$1:$N$7440,5,FALSE) -> 12 | J22: =+VLOOKUP(D22,Tiempos!$A$1:$N$7440,7,FALSE) -> FORM01 | K22: =IF(VLOOKUP(C22,OP!$A$1:$P$27848,4,FALSE)="Cerrado",VLOOKUP(C22,OP!$A$1:$P$27848,10,FALSE),VLOOKUP(C22,OP!$A$1:$P$27848,9,FALSE)) -> 5988 | L22: =IF( IFERROR(VLOOKUP(D22,BD_Spec!$A$1:$D$2300,4,FALSE),"")="Producto Terminado", "TERMINADO", IFERROR(_xlfn.XLOOKUP(Ordenes_Mes[[#This Row],[Maquina]],Tiempos!$G$1:$G$766,Tiempos!$O$1:$O$766),"") ) -> MASAS_TINTAS_LIMA | M22: =IF(OR(Ordenes_Mes[[#This Row],[Proceso]]="Plástico_lima",Ordenes_Mes[[#This Row],[Proceso]]="soplado"),24,12) -> 12 | N22: =+VLOOKUP(D22,BD_Spec!$A$1:$K$2336,7,FALSE) -> Línea_Crayón | O22: =+VLOOKUP(D22,BD_Spec!$A$1:$K$2336,8,FALSE) -> Crayón_Triángular | P22: =+VLOOKUP(C22,OP!$A$1:$P$27848,4,FALSE) -> CERRADO | Q22: =+VLOOKUP(C22,OP!$A$1:$P$27848,10,FALSE) -> 5988 | R22: =+Ordenes_Mes[[#This Row],[Fecha Inicio]] -> 46118
A23: =+MONTH(Ordenes_Mes[[#This Row],[Fecha_Conta]]) -> 4 | B23: =+VLOOKUP(C23,OP!$A$1:$P$27848,12,FALSE) -> 46118 | C23: 3927 | D23: 2310040365 | E23: Formado Crayón Triangular Jumbo LYC Verde Claro | F23: =+_xlfn.XLOOKUP(D23,BD_Spec!$A$1:$A$2336,BD_Spec!$L$1:$L$2336) -> 5 | G23: 46118 | H23: =+VLOOKUP(D23,Tiempos!$A$1:$N$7440,3,FALSE) -> 25000 | I23: =+VLOOKUP(D23,Tiempos!$A$1:$N$7440,5,FALSE) -> 12 | J23: =+VLOOKUP(D23,Tiempos!$A$1:$N$7440,7,FALSE) -> FORM01 | K23: =IF(VLOOKUP(C23,OP!$A$1:$P$27848,4,FALSE)="Cerrado",VLOOKUP(C23,OP!$A$1:$P$27848,10,FALSE),VLOOKUP(C23,OP!$A$1:$P$27848,9,FALSE)) -> 5838 | L23: =IF( IFERROR(VLOOKUP(D23,BD_Spec!$A$1:$D$2300,4,FALSE),"")="Producto Terminado", "TERMINADO", IFERROR(_xlfn.XLOOKUP(Ordenes_Mes[[#This Row],[Maquina]],Tiempos!$G$1:$G$766,Tiempos!$O$1:$O$766),"") ) -> MASAS_TINTAS_LIMA | M23: =IF(OR(Ordenes_Mes[[#This Row],[Proceso]]="Plástico_lima",Ordenes_Mes[[#This Row],[Proceso]]="soplado"),24,12) -> 12 | N23: =+VLOOKUP(D23,BD_Spec!$A$1:$K$2336,7,FALSE) -> Línea_Crayón | O23: =+VLOOKUP(D23,BD_Spec!$A$1:$K$2336,8,FALSE) -> Crayón_Triángular | P23: =+VLOOKUP(C23,OP!$A$1:$P$27848,4,FALSE) -> CERRADO | Q23: =+VLOOKUP(C23,OP!$A$1:$P$27848,10,FALSE) -> 5838 | R23: =+Ordenes_Mes[[#This Row],[Fecha Inicio]] -> 46118
A24: =+MONTH(Ordenes_Mes[[#This Row],[Fecha_Conta]]) -> 4 | B24: =+VLOOKUP(C24,OP!$A$1:$P$27848,12,FALSE) -> 46118 | C24: 3928 | D24: 2310040366 | E24: Formado Crayón Triangular Jumbo LYC Verde Oscuro | F24: =+_xlfn.XLOOKUP(D24,BD_Spec!$A$1:$A$2336,BD_Spec!$L$1:$L$2336) -> 6 | G24: 46118 | H24: =+VLOOKUP(D24,Tiempos!$A$1:$N$7440,3,FALSE) -> 25000 | I24: =+VLOOKUP(D24,Tiempos!$A$1:$N$7440,5,FALSE) -> 12 | J24: =+VLOOKUP(D24,Tiempos!$A$1:$N$7440,7,FALSE) -> FORM01 | K24: =IF(VLOOKUP(C24,OP!$A$1:$P$27848,4,FALSE)="Cerrado",VLOOKUP(C24,OP!$A$1:$P$27848,10,FALSE),VLOOKUP(C24,OP!$A$1:$P$27848,9,FALSE)) -> 6451 | L24: =IF( IFERROR(VLOOKUP(D24,BD_Spec!$A$1:$D$2300,4,FALSE),"")="Producto Terminado", "TERMINADO", IFERROR(_xlfn.XLOOKUP(Ordenes_Mes[[#This Row],[Maquina]],Tiempos!$G$1:$G$766,Tiempos!$O$1:$O$766),"") ) -> MASAS_TINTAS_LIMA | M24: =IF(OR(Ordenes_Mes[[#This Row],[Proceso]]="Plástico_lima",Ordenes_Mes[[#This Row],[Proceso]]="soplado"),24,12) -> 12 | N24: =+VLOOKUP(D24,BD_Spec!$A$1:$K$2336,7,FALSE) -> Línea_Crayón | O24: =+VLOOKUP(D24,BD_Spec!$A$1:$K$2336,8,FALSE) -> Crayón_Triángular | P24: =+VLOOKUP(C24,OP!$A$1:$P$27848,4,FALSE) -> CERRADO | Q24: =+VLOOKUP(C24,OP!$A$1:$P$27848,10,FALSE) -> 6451 | R24: =+Ordenes_Mes[[#This Row],[Fecha Inicio]] -> 46118
A25: =+MONTH(Ordenes_Mes[[#This Row],[Fecha_Conta]]) -> 4 | B25: =+VLOOKUP(C25,OP!$A$1:$P$27848,12,FALSE) -> 46118 | C25: 3930 | D25: 2310040368 | E25: Formado Crayón Triangular Jumbo LYC Azul | F25: =+_xlfn.XLOOKUP(D25,BD_Spec!$A$1:$A$2336,BD_Spec!$L$1:$L$2336) -> 7 | G25: 46118 | H25: =+VLOOKUP(D25,Tiempos!$A$1:$N$7440,3,FALSE) -> 25000 | I25: =+VLOOKUP(D25,Tiempos!$A$1:$N$7440,5,FALSE) -> 12 | J25: =+VLOOKUP(D25,Tiempos!$A$1:$N$7440,7,FALSE) -> FORM01 | K25: =IF(VLOOKUP(C25,OP!$A$1:$P$27848,4,FALSE)="Cerrado",VLOOKUP(C25,OP!$A$1:$P$27848,10,FALSE),VLOOKUP(C25,OP!$A$1:$P$27848,9,FALSE)) -> 6026 | L25: =IF( IFERROR(VLOOKUP(D25,BD_Spec!$A$1:$D$2300,4,FALSE),"")="Producto Terminado", "TERMINADO", IFERROR(_xlfn.XLOOKUP(Ordenes_Mes[[#This Row],[Maquina]],Tiempos!$G$1:$G$766,Tiempos!$O$1:$O$766),"") ) -> MASAS_TINTAS_LIMA | M25: =IF(OR(Ordenes_Mes[[#This Row],[Proceso]]="Plástico_lima",Ordenes_Mes[[#This Row],[Proceso]]="soplado"),24,12) -> 12 | N25: =+VLOOKUP(D25,BD_Spec!$A$1:$K$2336,7,FALSE) -> Línea_Crayón | O25: =+VLOOKUP(D25,BD_Spec!$A$1:$K$2336,8,FALSE) -> Crayón_Triángular | P25: =+VLOOKUP(C25,OP!$A$1:$P$27848,4,FALSE) -> CERRADO | Q25: =+VLOOKUP(C25,OP!$A$1:$P$27848,10,FALSE) -> 6026 | R25: =+Ordenes_Mes[[#This Row],[Fecha Inicio]] -> 46118
A26: =+MONTH(Ordenes_Mes[[#This Row],[Fecha_Conta]]) -> 4 | B26: =+VLOOKUP(C26,OP!$A$1:$P$27848,12,FALSE) -> 46118 | C26: 3929 | D26: 2310040367 | E26: Formado Crayón Triangular Jumbo LYC Celeste | F26: =+_xlfn.XLOOKUP(D26,BD_Spec!$A$1:$A$2336,BD_Spec!$L$1:$L$2336) -> 8 | G26: 46118 | H26: =+VLOOKUP(D26,Tiempos!$A$1:$N$7440,3,FALSE) -> 25000 | I26: =+VLOOKUP(D26,Tiempos!$A$1:$N$7440,5,FALSE) -> 12 | J26: =+VLOOKUP(D26,Tiempos!$A$1:$N$7440,7,FALSE) -> FORM01 | K26: =IF(VLOOKUP(C26,OP!$A$1:$P$27848,4,FALSE)="Cerrado",VLOOKUP(C26,OP!$A$1:$P$27848,10,FALSE),VLOOKUP(C26,OP!$A$1:$P$27848,9,FALSE)) -> 5941 | L26: =IF( IFERROR(VLOOKUP(D26,BD_Spec!$A$1:$D$2300,4,FALSE),"")="Producto Terminado", "TERMINADO", IFERROR(_xlfn.XLOOKUP(Ordenes_Mes[[#This Row],[Maquina]],Tiempos!$G$1:$G$766,Tiempos!$O$1:$O$766),"") ) -> MASAS_TINTAS_LIMA | M26: =IF(OR(Ordenes_Mes[[#This Row],[Proceso]]="Plástico_lima",Ordenes_Mes[[#This Row],[Proceso]]="soplado"),24,12) -> 12 | N26: =+VLOOKUP(D26,BD_Spec!$A$1:$K$2336,7,FALSE) -> Línea_Crayón | O26: =+VLOOKUP(D26,BD_Spec!$A$1:$K$2336,8,FALSE) -> Crayón_Triángular | P26: =+VLOOKUP(C26,OP!$A$1:$P$27848,4,FALSE) -> CERRADO | Q26: =+VLOOKUP(C26,OP!$A$1:$P$27848,10,FALSE) -> 5941 | R26: =+Ordenes_Mes[[#This Row],[Fecha Inicio]] -> 46118
A27: =+MONTH(Ordenes_Mes[[#This Row],[Fecha_Conta]]) -> 4 | B27: =+VLOOKUP(C27,OP!$A$1:$P$27848,12,FALSE) -> 46118 | C27: 3935 | D27: 2310040571 | E27: Formado Crayón Triangular Jumbo LYC Blanco | F27: =+_xlfn.XLOOKUP(D27,BD_Spec!$A$1:$A$2336,BD_Spec!$L$1:$L$2336) -> 9 | G27: 46118 | H27: =+VLOOKUP(D27,Tiempos!$A$1:$N$7440,3,FALSE) -> 25000 | I27: =+VLOOKUP(D27,Tiempos!$A$1:$N$7440,5,FALSE) -> 12 | J27: =+VLOOKUP(D27,Tiempos!$A$1:$N$7440,7,FALSE) -> FORM01 | K27: =IF(VLOOKUP(C27,OP!$A$1:$P$27848,4,FALSE)="Cerrado",VLOOKUP(C27,OP!$A$1:$P$27848,10,FALSE),VLOOKUP(C27,OP!$A$1:$P$27848,9,FALSE)) -> 5811 | L27: =IF( IFERROR(VLOOKUP(D27,BD_Spec!$A$1:$D$2300,4,FALSE),"")="Producto Terminado", "TERMINADO", IFERROR(_xlfn.XLOOKUP(Ordenes_Mes[[#This Row],[Maquina]],Tiempos!$G$1:$G$766,Tiempos!$O$1:$O$766),"") ) -> MASAS_TINTAS_LIMA | M27: =IF(OR(Ordenes_Mes[[#This Row],[Proceso]]="Plástico_lima",Ordenes_Mes[[#This Row],[Proceso]]="soplado"),24,12) -> 12 | N27: =+VLOOKUP(D27,BD_Spec!$A$1:$K$2336,7,FALSE) -> Línea_Crayón | O27: =+VLOOKUP(D27,BD_Spec!$A$1:$K$2336,8,FALSE) -> Crayón_Triángular | P27: =+VLOOKUP(C27,OP!$A$1:$P$27848,4,FALSE) -> CERRADO | Q27: =+VLOOKUP(C27,OP!$A$1:$P$27848,10,FALSE) -> 5811 | R27: =+Ordenes_Mes[[#This Row],[Fecha Inicio]] -> 46118
A28: =+MONTH(Ordenes_Mes[[#This Row],[Fecha_Conta]]) -> 4 | B28: =+VLOOKUP(C28,OP!$A$1:$P$27848,12,FALSE) -> 46118 | C28: 3931 | D28: 2310040369 | E28: Formado Crayón Triangular Jumbo LYC Violeta | F28: =+_xlfn.XLOOKUP(D28,BD_Spec!$A$1:$A$2336,BD_Spec!$L$1:$L$2336) -> 10 | G28: 46118 | H28: =+VLOOKUP(D28,Tiempos!$A$1:$N$7440,3,FALSE) -> 25000 | I28: =+VLOOKUP(D28,Tiempos!$A$1:$N$7440,5,FALSE) -> 12 | J28: =+VLOOKUP(D28,Tiempos!$A$1:$N$7440,7,FALSE) -> FORM01 | K28: =IF(VLOOKUP(C28,OP!$A$1:$P$27848,4,FALSE)="Cerrado",VLOOKUP(C28,OP!$A$1:$P$27848,10,FALSE),VLOOKUP(C28,OP!$A$1:$P$27848,9,FALSE)) -> 5923 | L28: =IF( IFERROR(VLOOKUP(D28,BD_Spec!$A$1:$D$2300,4,FALSE),"")="Producto Terminado", "TERMINADO", IFERROR(_xlfn.XLOOKUP(Ordenes_Mes[[#This Row],[Maquina]],Tiempos!$G$1:$G$766,Tiempos!$O$1:$O$766),"") ) -> MASAS_TINTAS_LIMA | M28: =IF(OR(Ordenes_Mes[[#This Row],[Proceso]]="Plástico_lima",Ordenes_Mes[[#This Row],[Proceso]]="soplado"),24,12) -> 12 | N28: =+VLOOKUP(D28,BD_Spec!$A$1:$K$2336,7,FALSE) -> Línea_Crayón | O28: =+VLOOKUP(D28,BD_Spec!$A$1:$K$2336,8,FALSE) -> Crayón_Triángular | P28: =+VLOOKUP(C28,OP!$A$1:$P$27848,4,FALSE) -> CERRADO | Q28: =+VLOOKUP(C28,OP!$A$1:$P$27848,10,FALSE) -> 5923 | R28: =+Ordenes_Mes[[#This Row],[Fecha Inicio]] -> 46118
A29: =+MONTH(Ordenes_Mes[[#This Row],[Fecha_Conta]]) -> 4 | B29: =+VLOOKUP(C29,OP!$A$1:$P$27848,12,FALSE) -> 46118 | C29: 3934 | D29: 2310040372 | E29: Formado Crayón Triangular Jumbo LYC Marrón | F29: =+_xlfn.XLOOKUP(D29,BD_Spec!$A$1:$A$2336,BD_Spec!$L$1:$L$2336) -> 11 | G29: 46118 | H29: =+VLOOKUP(D29,Tiempos!$A$1:$N$7440,3,FALSE) -> 25000 | I29: =+VLOOKUP(D29,Tiempos!$A$1:$N$7440,5,FALSE) -> 12 | J29: =+VLOOKUP(D29,Tiempos!$A$1:$N$7440,7,FALSE) -> FORM01 | K29: =IF(VLOOKUP(C29,OP!$A$1:$P$27848,4,FALSE)="Cerrado",VLOOKUP(C29,OP!$A$1:$P$27848,10,FALSE),VLOOKUP(C29,OP!$A$1:$P$27848,9,FALSE)) -> 6447 | L29: =IF( IFERROR(VLOOKUP(D29,BD_Spec!$A$1:$D$2300,4,FALSE),"")="Producto Terminado", "TERMINADO", IFERROR(_xlfn.XLOOKUP(Ordenes_Mes[[#This Row],[Maquina]],Tiempos!$G$1:$G$766,Tiempos!$O$1:$O$766),"") ) -> MASAS_TINTAS_LIMA | M29: =IF(OR(Ordenes_Mes[[#This Row],[Proceso]]="Plástico_lima",Ordenes_Mes[[#This Row],[Proceso]]="soplado"),24,12) -> 12 | N29: =+VLOOKUP(D29,BD_Spec!$A$1:$K$2336,7,FALSE) -> Línea_Crayón | O29: =+VLOOKUP(D29,BD_Spec!$A$1:$K$2336,8,FALSE) -> Crayón_Triángular | P29: =+VLOOKUP(C29,OP!$A$1:$P$27848,4,FALSE) -> CERRADO | Q29: =+VLOOKUP(C29,OP!$A$1:$P$27848,10,FALSE) -> 6447 | R29: =+Ordenes_Mes[[#This Row],[Fecha Inicio]] -> 46118
A30: =+MONTH(Ordenes_Mes[[#This Row],[Fecha_Conta]]) -> 4 | B30: =+VLOOKUP(C30,OP!$A$1:$P$27848,12,FALSE) -> 46118 | C30: 3932 | D30: 2310040370 | E30: Formado Crayón Triangular Jumbo LYC Negro | F30: =+_xlfn.XLOOKUP(D30,BD_Spec!$A$1:$A$2336,BD_Spec!$L$1:$L$2336) -> 12 | G30: 46118 | H30: =+VLOOKUP(D30,Tiempos!$A$1:$N$7440,3,FALSE) -> 25000 | I30: =+VLOOKUP(D30,Tiempos!$A$1:$N$7440,5,FALSE) -> 12 | J30: =+VLOOKUP(D30,Tiempos!$A$1:$N$7440,7,FALSE) -> FORM01 | K30: =IF(VLOOKUP(C30,OP!$A$1:$P$27848,4,FALSE)="Cerrado",VLOOKUP(C30,OP!$A$1:$P$27848,10,FALSE),VLOOKUP(C30,OP!$A$1:$P$27848,9,FALSE)) -> 6424 | L30: =IF( IFERROR(VLOOKUP(D30,BD_Spec!$A$1:$D$2300,4,FALSE),"")="Producto Terminado", "TERMINADO", IFERROR(_xlfn.XLOOKUP(Ordenes_Mes[[#This Row],[Maquina]],Tiempos!$G$1:$G$766,Tiempos!$O$1:$O$766),"") ) -> MASAS_TINTAS_LIMA | M30: =IF(OR(Ordenes_Mes[[#This Row],[Proceso]]="Plástico_lima",Ordenes_Mes[[#This Row],[Proceso]]="soplado"),24,12) -> 12 | N30: =+VLOOKUP(D30,BD_Spec!$A$1:$K$2336,7,FALSE) -> Línea_Crayón | O30: =+VLOOKUP(D30,BD_Spec!$A$1:$K$2336,8,FALSE) -> Crayón_Triángular | P30: =+VLOOKUP(C30,OP!$A$1:$P$27848,4,FALSE) -> CERRADO | Q30: =+VLOOKUP(C30,OP!$A$1:$P$27848,10,FALSE) -> 6424 | R30: =+Ordenes_Mes[[#This Row],[Fecha Inicio]] -> 46118
A31: =+MONTH(Ordenes_Mes[[#This Row],[Fecha_Conta]]) -> 4 | B31: =+VLOOKUP(C31,OP!$A$1:$P$27848,12,FALSE) -> 46125 | C31: 4004 | D31: 2310030073 | E31: Masa Para Témperas Celeste LYC P.S. | F31: 1 | G31: 46127 | H31: =+VLOOKUP(D31,Tiempos!$A$1:$N$7440,3,FALSE) -> 2700 | I31: =+VLOOKUP(D31,Tiempos!$A$1:$N$7440,5,FALSE) -> 12 | J31: =+VLOOKUP(D31,Tiempos!$A$1:$N$7440,7,FALSE) -> HUBBES02 | K31: =IF(VLOOKUP(C31,OP!$A$1:$P$27848,4,FALSE)="Cerrado",VLOOKUP(C31,OP!$A$1:$P$27848,10,FALSE),VLOOKUP(C31,OP!$A$1:$P$27848,9,FALSE)) -> 600 | L31: =IF( IFERROR(VLOOKUP(D31,BD_Spec!$A$1:$D$2300,4,FALSE),"")="Producto Terminado", "TERMINADO", IFERROR(_xlfn.XLOOKUP(Ordenes_Mes[[#This Row],[Maquina]],Tiempos!$G$1:$G$766,Tiempos!$O$1:$O$766),"") ) -> MASAS_TINTAS_LIMA | M31: =IF(OR(Ordenes_Mes[[#This Row],[Proceso]]="Plástico_lima",Ordenes_Mes[[#This Row],[Proceso]]="soplado"),24,12) -> 12 | N31: =+VLOOKUP(D31,BD_Spec!$A$1:$K$2336,7,FALSE) -> Línea_30cc | O31: =+VLOOKUP(D31,BD_Spec!$A$1:$K$2336,8,FALSE) -> Colores | P31: =+VLOOKUP(C31,OP!$A$1:$P$27848,4,FALSE) -> CERRADO | Q31: =+VLOOKUP(C31,OP!$A$1:$P$27848,10,FALSE) -> 600 | R31: =+Ordenes_Mes[[#This Row],[Fecha Inicio]] -> 46127
A32: =+MONTH(Ordenes_Mes[[#This Row],[Fecha_Conta]]) -> 4 | B32: =+VLOOKUP(C32,OP!$A$1:$P$27848,12,FALSE) -> 46125 | C32: 4005 | D32: 2310030132 | E32: Masa Para Témperas Morado LYC P.S. | F32: 2 | G32: 46127 | H32: =+VLOOKUP(D32,Tiempos!$A$1:$N$7440,3,FALSE) -> 2700 | I32: =+VLOOKUP(D32,Tiempos!$A$1:$N$7440,5,FALSE) -> 12 | J32: =+VLOOKUP(D32,Tiempos!$A$1:$N$7440,7,FALSE) -> HUBBES02 | K32: =IF(VLOOKUP(C32,OP!$A$1:$P$27848,4,FALSE)="Cerrado",VLOOKUP(C32,OP!$A$1:$P$27848,10,FALSE),VLOOKUP(C32,OP!$A$1:$P$27848,9,FALSE)) -> 600 | L32: =IF( IFERROR(VLOOKUP(D32,BD_Spec!$A$1:$D$2300,4,FALSE),"")="Producto Terminado", "TERMINADO", IFERROR(_xlfn.XLOOKUP(Ordenes_Mes[[#This Row],[Maquina]],Tiempos!$G$1:$G$766,Tiempos!$O$1:$O$766),"") ) -> MASAS_TINTAS_LIMA | M32: =IF(OR(Ordenes_Mes[[#This Row],[Proceso]]="Plástico_lima",Ordenes_Mes[[#This Row],[Proceso]]="soplado"),24,12) -> 12 | N32: =+VLOOKUP(D32,BD_Spec!$A$1:$K$2336,7,FALSE) -> Línea_30cc | O32: =+VLOOKUP(D32,BD_Spec!$A$1:$K$2336,8,FALSE) -> Colores | P32: =+VLOOKUP(C32,OP!$A$1:$P$27848,4,FALSE) -> CERRADO | Q32: =+VLOOKUP(C32,OP!$A$1:$P$27848,10,FALSE) -> 600 | R32: =+Ordenes_Mes[[#This Row],[Fecha Inicio]] -> 46127
A33: =+MONTH(Ordenes_Mes[[#This Row],[Fecha_Conta]]) -> 4 | B33: =+VLOOKUP(C33,OP!$A$1:$P$27848,12,FALSE) -> 46126 | C33: 4013 | D33: 2310030021 | E33: Masa Para Témperas Marrón LYC P.S. | F33: 3 | G33: 46127 | H33: =+VLOOKUP(D33,Tiempos!$A$1:$N$7440,3,FALSE) -> 2700 | I33: =+VLOOKUP(D33,Tiempos!$A$1:$N$7440,5,FALSE) -> 12 | J33: =+VLOOKUP(D33,Tiempos!$A$1:$N$7440,7,FALSE) -> HUBBES02 | K33: =IF(VLOOKUP(C33,OP!$A$1:$P$27848,4,FALSE)="Cerrado",VLOOKUP(C33,OP!$A$1:$P$27848,10,FALSE),VLOOKUP(C33,OP!$A$1:$P$27848,9,FALSE)) -> 600 | L33: =IF( IFERROR(VLOOKUP(D33,BD_Spec!$A$1:$D$2300,4,FALSE),"")="Producto Terminado", "TERMINADO", IFERROR(_xlfn.XLOOKUP(Ordenes_Mes[[#This Row],[Maquina]],Tiempos!$G$1:$G$766,Tiempos!$O$1:$O$766),"") ) -> MASAS_TINTAS_LIMA | M33: =IF(OR(Ordenes_Mes[[#This Row],[Proceso]]="Plástico_lima",Ordenes_Mes[[#This Row],[Proceso]]="soplado"),24,12) -> 12 | N33: =+VLOOKUP(D33,BD_Spec!$A$1:$K$2336,7,FALSE) -> Línea_30cc | O33: =+VLOOKUP(D33,BD_Spec!$A$1:$K$2336,8,FALSE) -> Colores | P33: =+VLOOKUP(C33,OP!$A$1:$P$27848,4,FALSE) -> CERRADO | Q33: =+VLOOKUP(C33,OP!$A$1:$P$27848,10,FALSE) -> 600 | R33: =+Ordenes_Mes[[#This Row],[Fecha Inicio]] -> 46127
A34: =+MONTH(Ordenes_Mes[[#This Row],[Fecha_Conta]]) -> 4 | B34: =+VLOOKUP(C34,OP!$A$1:$P$27848,12,FALSE) -> 46118 | C34: 3923 | D34: 2140210005 | E34: Peine Patrullero Rojo Sin Cola 16A Lucas (NOPUCID) | F34: =+_xlfn.XLOOKUP(D34,BD_Spec!$A$1:$A$2336,BD_Spec!$L$1:$L$2336) -> 1 | G34: 46118 | H34: =+VLOOKUP(D34,Tiempos!$A$1:$N$7440,3,FALSE) -> 7000 | I34: =+VLOOKUP(D34,Tiempos!$A$1:$N$7440,5,FALSE) -> 12 | J34: =+VLOOKUP(D34,Tiempos!$A$1:$N$7440,7,FALSE) -> IMP03 | K34: =IF(VLOOKUP(C34,OP!$A$1:$P$27848,4,FALSE)="Cerrado",VLOOKUP(C34,OP!$A$1:$P$27848,10,FALSE),VLOOKUP(C34,OP!$A$1:$P$27848,9,FALSE)) -> 101232 | L34: =IF( IFERROR(VLOOKUP(D34,BD_Spec!$A$1:$D$2300,4,FALSE),"")="Producto Terminado", "TERMINADO", IFERROR(_xlfn.XLOOKUP(Ordenes_Mes[[#This Row],[Maquina]],Tiempos!$G$1:$G$766,Tiempos!$O$1:$O$766),"") ) -> TERMINADO | M34: =IF(OR(Ordenes_Mes[[#This Row],[Proceso]]="Plástico_lima",Ordenes_Mes[[#This Row],[Proceso]]="soplado"),24,12) -> 12 | N34: =+VLOOKUP(D34,BD_Spec!$A$1:$K$2336,7,FALSE) -> Línea_Peine | O34: =+VLOOKUP(D34,BD_Spec!$A$1:$K$2336,8,FALSE) -> Peine | P34: =+VLOOKUP(C34,OP!$A$1:$P$27848,4,FALSE) -> CERRADO | Q34: =+VLOOKUP(C34,OP!$A$1:$P$27848,10,FALSE) -> 101232 | R34: =+Ordenes_Mes[[#This Row],[Fecha Inicio]] -> 46118
A35: =+MONTH(Ordenes_Mes[[#This Row],[Fecha_Conta]]) -> 4 | B35: =+VLOOKUP(C35,OP!$A$1:$P$27848,12,FALSE) -> 46118 | C35: 3916 | D35: 2310230097 | E35: Frasco Para Témperas 30 cc NP P.S. | F35: =+_xlfn.XLOOKUP(D35,BD_Spec!$A$1:$A$2336,BD_Spec!$L$1:$L$2336) -> 1 | G35: 46113 | H35: =+VLOOKUP(D35,Tiempos!$A$1:$N$7440,3,FALSE) -> 44204.651 | I35: =+VLOOKUP(D35,Tiempos!$A$1:$N$7440,5,FALSE) -> 24 | J35: =+VLOOKUP(D35,Tiempos!$A$1:$N$7440,7,FALSE) -> INY02 | K35: =IF(VLOOKUP(C35,OP!$A$1:$P$27848,4,FALSE)="Cerrado",VLOOKUP(C35,OP!$A$1:$P$27848,10,FALSE),VLOOKUP(C35,OP!$A$1:$P$27848,9,FALSE)) -> 654000 | L35: =IF( IFERROR(VLOOKUP(D35,BD_Spec!$A$1:$D$2300,4,FALSE),"")="Producto Terminado", "TERMINADO", IFERROR(_xlfn.XLOOKUP(Ordenes_Mes[[#This Row],[Maquina]],Tiempos!$G$1:$G$766,Tiempos!$O$1:$O$766),"") ) -> PLÁSTICO_LIMA | M35: =IF(OR(Ordenes_Mes[[#This Row],[Proceso]]="Plástico_lima",Ordenes_Mes[[#This Row],[Proceso]]="soplado"),24,12) -> 24 | N35: =+VLOOKUP(D35,BD_Spec!$A$1:$K$2336,7,FALSE) -> Línea_30cc | O35: =+VLOOKUP(D35,BD_Spec!$A$1:$K$2336,8,FALSE) -> Frasco PLK | P35: =+VLOOKUP(C35,OP!$A$1:$P$27848,4,FALSE) -> CERRADO | Q35: =+VLOOKUP(C35,OP!$A$1:$P$27848,10,FALSE) -> 654000 | R35: =+Ordenes_Mes[[#This Row],[Fecha Inicio]] -> 46113
A36: =+MONTH(Ordenes_Mes[[#This Row],[Fecha_Conta]]) -> 4 | B36: =+VLOOKUP(C36,OP!$A$1:$P$27848,12,FALSE) -> 46118 | C36: 3870 | D36: 2310090450 | E36: Barril Para Plumón 045 - NP Piel | F36: =+_xlfn.XLOOKUP(D36,BD_Spec!$A$1:$A$2336,BD_Spec!$L$1:$L$2336) -> 1 | G36: 46118 | H36: =+VLOOKUP(D36,Tiempos!$A$1:$N$7440,3,FALSE) -> 98742.857 | I36: =+VLOOKUP(D36,Tiempos!$A$1:$N$7440,5,FALSE) -> 24 | J36: =+VLOOKUP(D36,Tiempos!$A$1:$N$7440,7,FALSE) -> INY05 | K36: =IF(VLOOKUP(C36,OP!$A$1:$P$27848,4,FALSE)="Cerrado",VLOOKUP(C36,OP!$A$1:$P$27848,10,FALSE),VLOOKUP(C36,OP!$A$1:$P$27848,9,FALSE)) -> 236000 | L36: =IF( IFERROR(VLOOKUP(D36,BD_Spec!$A$1:$D$2300,4,FALSE),"")="Producto Terminado", "TERMINADO", IFERROR(_xlfn.XLOOKUP(Ordenes_Mes[[#This Row],[Maquina]],Tiempos!$G$1:$G$766,Tiempos!$O$1:$O$766),"") ) -> PLÁSTICO_LIMA | M36: =IF(OR(Ordenes_Mes[[#This Row],[Proceso]]="Plástico_lima",Ordenes_Mes[[#This Row],[Proceso]]="soplado"),24,12) -> 24 | N36: =+VLOOKUP(D36,BD_Spec!$A$1:$K$2336,7,FALSE) -> Línea_045 | O36: =+VLOOKUP(D36,BD_Spec!$A$1:$K$2336,8,FALSE) -> Barril | P36: =+VLOOKUP(C36,OP!$A$1:$P$27848,4,FALSE) -> CERRADO | Q36: =+VLOOKUP(C36,OP!$A$1:$P$27848,10,FALSE) -> 236000 | R36: =+Ordenes_Mes[[#This Row],[Fecha Inicio]] -> 46118
A37: =+MONTH(Ordenes_Mes[[#This Row],[Fecha_Conta]]) -> 4 | B37: =+VLOOKUP(C37,OP!$A$1:$P$27848,12,FALSE) -> 46118 | C37: 3864 | D37: 2310090443 | E37: Barril Para Plumón 045 - NP Amarillo | F37: =+_xlfn.XLOOKUP(D37,BD_Spec!$A$1:$A$2336,BD_Spec!$L$1:$L$2336) -> 2 | G37: 46118 | H37: =+VLOOKUP(D37,Tiempos!$A$1:$N$7440,3,FALSE) -> 98742.857 | I37: =+VLOOKUP(D37,Tiempos!$A$1:$N$7440,5,FALSE) -> 24 | J37: =+VLOOKUP(D37,Tiempos!$A$1:$N$7440,7,FALSE) -> INY05 | K37: =IF(VLOOKUP(C37,OP!$A$1:$P$27848,4,FALSE)="Cerrado",VLOOKUP(C37,OP!$A$1:$P$27848,10,FALSE),VLOOKUP(C37,OP!$A$1:$P$27848,9,FALSE)) -> 207800 | L37: =IF( IFERROR(VLOOKUP(D37,BD_Spec!$A$1:$D$2300,4,FALSE),"")="Producto Terminado", "TERMINADO", IFERROR(_xlfn.XLOOKUP(Ordenes_Mes[[#This Row],[Maquina]],Tiempos!$G$1:$G$766,Tiempos!$O$1:$O$766),"") ) -> PLÁSTICO_LIMA | M37: =IF(OR(Ordenes_Mes[[#This Row],[Proceso]]="Plástico_lima",Ordenes_Mes[[#This Row],[Proceso]]="soplado"),24,12) -> 24 | N37: =+VLOOKUP(D37,BD_Spec!$A$1:$K$2336,7,FALSE) -> Línea_045 | O37: =+VLOOKUP(D37,BD_Spec!$A$1:$K$2336,8,FALSE) -> Barril | P37: =+VLOOKUP(C37,OP!$A$1:$P$27848,4,FALSE) -> CERRADO | Q37: =+VLOOKUP(C37,OP!$A$1:$P$27848,10,FALSE) -> 207800 | R37: =+Ordenes_Mes[[#This Row],[Fecha Inicio]] -> 46118
A38: =+MONTH(Ordenes_Mes[[#This Row],[Fecha_Conta]]) -> 4 | B38: =+VLOOKUP(C38,OP!$A$1:$P$27848,12,FALSE) -> 46118 | C38: 3869 | D38: 2310090447 | E38: Barril Para Plumón 045 - NP Anaranjado | F38: =+_xlfn.XLOOKUP(D38,BD_Spec!$A$1:$A$2336,BD_Spec!$L$1:$L$2336) -> 3 | G38: 46118 | H38: =+VLOOKUP(D38,Tiempos!$A$1:$N$7440,3,FALSE) -> 98742.857 | I38: =+VLOOKUP(D38,Tiempos!$A$1:$N$7440,5,FALSE) -> 24 | J38: =+VLOOKUP(D38,Tiempos!$A$1:$N$7440,7,FALSE) -> INY05 | K38: =IF(VLOOKUP(C38,OP!$A$1:$P$27848,4,FALSE)="Cerrado",VLOOKUP(C38,OP!$A$1:$P$27848,10,FALSE),VLOOKUP(C38,OP!$A$1:$P$27848,9,FALSE)) -> 244800 | L38: =IF( IFERROR(VLOOKUP(D38,BD_Spec!$A$1:$D$2300,4,FALSE),"")="Producto Terminado", "TERMINADO", IFERROR(_xlfn.XLOOKUP(Ordenes_Mes[[#This Row],[Maquina]],Tiempos!$G$1:$G$766,Tiempos!$O$1:$O$766),"") ) -> PLÁSTICO_LIMA | M38: =IF(OR(Ordenes_Mes[[#This Row],[Proceso]]="Plástico_lima",Ordenes_Mes[[#This Row],[Proceso]]="soplado"),24,12) -> 24 | N38: =+VLOOKUP(D38,BD_Spec!$A$1:$K$2336,7,FALSE) -> Línea_045 | O38: =+VLOOKUP(D38,BD_Spec!$A$1:$K$2336,8,FALSE) -> Barril | P38: =+VLOOKUP(C38,OP!$A$1:$P$27848,4,FALSE) -> CERRADO | Q38: =+VLOOKUP(C38,OP!$A$1:$P$27848,10,FALSE) -> 244800 | R38: =+Ordenes_Mes[[#This Row],[Fecha Inicio]] -> 46118
A39: =+MONTH(Ordenes_Mes[[#This Row],[Fecha_Conta]]) -> 4 | B39: =+VLOOKUP(C39,OP!$A$1:$P$27848,12,FALSE) -> 46118 | C39: 3867 | D39: 2310090446 | E39: Barril Para Plumón 045 - NP Rosado | F39: =+_xlfn.XLOOKUP(D39,BD_Spec!$A$1:$A$2336,BD_Spec!$L$1:$L$2336) -> 4 | G39: 46118 | H39: =+VLOOKUP(D39,Tiempos!$A$1:$N$7440,3,FALSE) -> 98742.857 | I39: =+VLOOKUP(D39,Tiempos!$A$1:$N$7440,5,FALSE) -> 24 | J39: =+VLOOKUP(D39,Tiempos!$A$1:$N$7440,7,FALSE) -> INY05 | K39: =IF(VLOOKUP(C39,OP!$A$1:$P$27848,4,FALSE)="Cerrado",VLOOKUP(C39,OP!$A$1:$P$27848,10,FALSE),VLOOKUP(C39,OP!$A$1:$P$27848,9,FALSE)) -> 246170 | L39: =IF( IFERROR(VLOOKUP(D39,BD_Spec!$A$1:$D$2300,4,FALSE),"")="Producto Terminado", "TERMINADO", IFERROR(_xlfn.XLOOKUP(Ordenes_Mes[[#This Row],[Maquina]],Tiempos!$G$1:$G$766,Tiempos!$O$1:$O$766),"") ) -> PLÁSTICO_LIMA | M39: =IF(OR(Ordenes_Mes[[#This Row],[Proceso]]="Plástico_lima",Ordenes_Mes[[#This Row],[Proceso]]="soplado"),24,12) -> 24 | N39: =+VLOOKUP(D39,BD_Spec!$A$1:$K$2336,7,FALSE) -> Línea_045 | O39: =+VLOOKUP(D39,BD_Spec!$A$1:$K$2336,8,FALSE) -> Barril | P39: =+VLOOKUP(C39,OP!$A$1:$P$27848,4,FALSE) -> CERRADO | Q39: =+VLOOKUP(C39,OP!$A$1:$P$27848,10,FALSE) -> 246170 | R39: =+Ordenes_Mes[[#This Row],[Fecha Inicio]] -> 46118
A40: =+MONTH(Ordenes_Mes[[#This Row],[Fecha_Conta]]) -> 4 | B40: =+VLOOKUP(C40,OP!$A$1:$P$27848,12,FALSE) -> 46118 | C40: 3861 | D40: 2310090440 | E40: Barril Para Plumón 045 - NP Rojo | F40: =+_xlfn.XLOOKUP(D40,BD_Spec!$A$1:$A$2336,BD_Spec!$L$1:$L$2336) -> 5 | G40: 46118 | H40: =+VLOOKUP(D40,Tiempos!$A$1:$N$7440,3,FALSE) -> 98742.857 | I40: =+VLOOKUP(D40,Tiempos!$A$1:$N$7440,5,FALSE) -> 24 | J40: =+VLOOKUP(D40,Tiempos!$A$1:$N$7440,7,FALSE) -> INY05 | K40: =IF(VLOOKUP(C40,OP!$A$1:$P$27848,4,FALSE)="Cerrado",VLOOKUP(C40,OP!$A$1:$P$27848,10,FALSE),VLOOKUP(C40,OP!$A$1:$P$27848,9,FALSE)) -> 240750 | L40: =IF( IFERROR(VLOOKUP(D40,BD_Spec!$A$1:$D$2300,4,FALSE),"")="Producto Terminado", "TERMINADO", IFERROR(_xlfn.XLOOKUP(Ordenes_Mes[[#This Row],[Maquina]],Tiempos!$G$1:$G$766,Tiempos!$O$1:$O$766),"") ) -> PLÁSTICO_LIMA | M40: =IF(OR(Ordenes_Mes[[#This Row],[Proceso]]="Plástico_lima",Ordenes_Mes[[#This Row],[Proceso]]="soplado"),24,12) -> 24 | N40: =+VLOOKUP(D40,BD_Spec!$A$1:$K$2336,7,FALSE) -> Línea_045 | O40: =+VLOOKUP(D40,BD_Spec!$A$1:$K$2336,8,FALSE) -> Barril | P40: =+VLOOKUP(C40,OP!$A$1:$P$27848,4,FALSE) -> CERRADO | Q40: =+VLOOKUP(C40,OP!$A$1:$P$27848,10,FALSE) -> 240750 | R40: =+Ordenes_Mes[[#This Row],[Fecha Inicio]] -> 46118
A41: =+MONTH(Ordenes_Mes[[#This Row],[Fecha_Conta]]) -> 4 | B41: =+VLOOKUP(C41,OP!$A$1:$P$27848,12,FALSE) -> 46118 | C41: 3868 | D41: 2310090448 | E41: Barril Para Plumón 045 - NP Celeste | F41: =+_xlfn.XLOOKUP(D41,BD_Spec!$A$1:$A$2336,BD_Spec!$L$1:$L$2336) -> 6 | G41: 46118 | H41: =+VLOOKUP(D41,Tiempos!$A$1:$N$7440,3,FALSE) -> 98742.857 | I41: =+VLOOKUP(D41,Tiempos!$A$1:$N$7440,5,FALSE) -> 24 | J41: =+VLOOKUP(D41,Tiempos!$A$1:$N$7440,7,FALSE) -> INY05 | K41: =IF(VLOOKUP(C41,OP!$A$1:$P$27848,4,FALSE)="Cerrado",VLOOKUP(C41,OP!$A$1:$P$27848,10,FALSE),VLOOKUP(C41,OP!$A$1:$P$27848,9,FALSE)) -> 81600 | L41: =IF( IFERROR(VLOOKUP(D41,BD_Spec!$A$1:$D$2300,4,FALSE),"")="Producto Terminado", "TERMINADO", IFERROR(_xlfn.XLOOKUP(Ordenes_Mes[[#This Row],[Maquina]],Tiempos!$G$1:$G$766,Tiempos!$O$1:$O$766),"") ) -> PLÁSTICO_LIMA | M41: =IF(OR(Ordenes_Mes[[#This Row],[Proceso]]="Plástico_lima",Ordenes_Mes[[#This Row],[Proceso]]="soplado"),24,12) -> 24 | N41: =+VLOOKUP(D41,BD_Spec!$A$1:$K$2336,7,FALSE) -> Línea_045 | O41: =+VLOOKUP(D41,BD_Spec!$A$1:$K$2336,8,FALSE) -> Barril | P41: =+VLOOKUP(C41,OP!$A$1:$P$27848,4,FALSE) -> CERRADO | Q41: =+VLOOKUP(C41,OP!$A$1:$P$27848,10,FALSE) -> 81600 | R41: =+Ordenes_Mes[[#This Row],[Fecha Inicio]] -> 46118
A42: =+MONTH(Ordenes_Mes[[#This Row],[Fecha_Conta]]) -> 4 | B42: =+VLOOKUP(C42,OP!$A$1:$P$27848,12,FALSE) -> 46118 | C42: 3950 | D42: 2310160270 | E42: Tapa Para Témpera 30cc Sin Logo Color Blanco P.S. | F42: 1 | G42: 46118 | H42: =+VLOOKUP(D42,Tiempos!$A$1:$N$7440,3,FALSE) -> 63123.288 | I42: =+VLOOKUP(D42,Tiempos!$A$1:$N$7440,5,FALSE) -> 24 | J42: =+VLOOKUP(D42,Tiempos!$A$1:$N$7440,7,FALSE) -> INY06 | K42: =IF(VLOOKUP(C42,OP!$A$1:$P$27848,4,FALSE)="Cerrado",VLOOKUP(C42,OP!$A$1:$P$27848,10,FALSE),VLOOKUP(C42,OP!$A$1:$P$27848,9,FALSE)) -> 150000 | L42: =IF( IFERROR(VLOOKUP(D42,BD_Spec!$A$1:$D$2300,4,FALSE),"")="Producto Terminado", "TERMINADO", IFERROR(_xlfn.XLOOKUP(Ordenes_Mes[[#This Row],[Maquina]],Tiempos!$G$1:$G$766,Tiempos!$O$1:$O$766),"") ) -> PLÁSTICO_LIMA | M42: =IF(OR(Ordenes_Mes[[#This Row],[Proceso]]="Plástico_lima",Ordenes_Mes[[#This Row],[Proceso]]="soplado"),24,12) -> 24 | N42: =+VLOOKUP(D42,BD_Spec!$A$1:$K$2336,7,FALSE) -> Línea_30cc | O42: =+VLOOKUP(D42,BD_Spec!$A$1:$K$2336,8,FALSE) -> Tapa PLK | P42: =+VLOOKUP(C42,OP!$A$1:$P$27848,4,FALSE) -> CERRADO | Q42: =+VLOOKUP(C42,OP!$A$1:$P$27848,10,FALSE) -> 150000 | R42: =+Ordenes_Mes[[#This Row],[Fecha Inicio]] -> 46118
A43: =+MONTH(Ordenes_Mes[[#This Row],[Fecha_Conta]]) -> 4 | B43: =+VLOOKUP(C43,OP!$A$1:$P$27848,12,FALSE) -> 46118 | C43: 3915 | D43: 2310160558 | E43: Tapa 30 cc P.S. | F43: =+_xlfn.XLOOKUP(D43,BD_Spec!$A$1:$A$2336,BD_Spec!$L$1:$L$2336) -> 1 | G43: 46132 | H43: =+VLOOKUP(D43,Tiempos!$A$1:$N$7440,3,FALSE) -> 38400 | I43: =+VLOOKUP(D43,Tiempos!$A$1:$N$7440,5,FALSE) -> 24 | J43: =+VLOOKUP(D43,Tiempos!$A$1:$N$7440,7,FALSE) -> INY08 | K43: =IF(VLOOKUP(C43,OP!$A$1:$P$27848,4,FALSE)="Cerrado",VLOOKUP(C43,OP!$A$1:$P$27848,10,FALSE),VLOOKUP(C43,OP!$A$1:$P$27848,9,FALSE)) -> 240000 | L43: =IF( IFERROR(VLOOKUP(D43,BD_Spec!$A$1:$D$2300,4,FALSE),"")="Producto Terminado", "TERMINADO", IFERROR(_xlfn.XLOOKUP(Ordenes_Mes[[#This Row],[Maquina]],Tiempos!$G$1:$G$766,Tiempos!$O$1:$O$766),"") ) -> PLÁSTICO_LIMA | M43: =IF(OR(Ordenes_Mes[[#This Row],[Proceso]]="Plástico_lima",Ordenes_Mes[[#This Row],[Proceso]]="soplado"),24,12) -> 24 | N43: =+VLOOKUP(D43,BD_Spec!$A$1:$K$2336,7,FALSE) -> Línea_30cc | O43: =+VLOOKUP(D43,BD_Spec!$A$1:$K$2336,8,FALSE) -> Tapa PLK | P43: =+VLOOKUP(C43,OP!$A$1:$P$27848,4,FALSE) -> CERRADO | Q43: =+VLOOKUP(C43,OP!$A$1:$P$27848,10,FALSE) -> 240000 | R43: =+Ordenes_Mes[[#This Row],[Fecha Inicio]] -> 46132
A44: =+MONTH(Ordenes_Mes[[#This Row],[Fecha_Conta]]) -> 4 | B44: =+VLOOKUP(C44,OP!$A$1:$P$27848,12,FALSE) -> 46118 | C44: 3881 | D44: 2310160479 | E44: Tapa Para Plumón 045 - NP Piel | F44: =+_xlfn.XLOOKUP(D44,BD_Spec!$A$1:$A$2336,BD_Spec!$L$1:$L$2336) -> 1 | G44: 46118 | H44: =+VLOOKUP(D44,Tiempos!$A$1:$N$7440,3,FALSE) -> 86400 | I44: =+VLOOKUP(D44,Tiempos!$A$1:$N$7440,5,FALSE) -> 24 | J44: =+VLOOKUP(D44,Tiempos!$A$1:$N$7440,7,FALSE) -> INY09 | K44: =IF(VLOOKUP(C44,OP!$A$1:$P$27848,4,FALSE)="Cerrado",VLOOKUP(C44,OP!$A$1:$P$27848,10,FALSE),VLOOKUP(C44,OP!$A$1:$P$27848,9,FALSE)) -> 241000 | L44: =IF( IFERROR(VLOOKUP(D44,BD_Spec!$A$1:$D$2300,4,FALSE),"")="Producto Terminado", "TERMINADO", IFERROR(_xlfn.XLOOKUP(Ordenes_Mes[[#This Row],[Maquina]],Tiempos!$G$1:$G$766,Tiempos!$O$1:$O$766),"") ) -> PLÁSTICO_LIMA | M44: =IF(OR(Ordenes_Mes[[#This Row],[Proceso]]="Plástico_lima",Ordenes_Mes[[#This Row],[Proceso]]="soplado"),24,12) -> 24 | N44: =+VLOOKUP(D44,BD_Spec!$A$1:$K$2336,7,FALSE) -> Línea_045 | O44: =+VLOOKUP(D44,BD_Spec!$A$1:$K$2336,8,FALSE) -> Tapa | P44: =+VLOOKUP(C44,OP!$A$1:$P$27848,4,FALSE) -> CERRADO | Q44: =+VLOOKUP(C44,OP!$A$1:$P$27848,10,FALSE) -> 241000 | R44: =+Ordenes_Mes[[#This Row],[Fecha Inicio]] -> 46118
A45: =+MONTH(Ordenes_Mes[[#This Row],[Fecha_Conta]]) -> 4 | B45: =+VLOOKUP(C45,OP!$A$1:$P$27848,12,FALSE) -> 46118 | C45: 3904 | D45: 2310160472 | E45: Tapa Para Plumón 045 - NP Amarillo | F45: =+_xlfn.XLOOKUP(D45,BD_Spec!$A$1:$A$2336,BD_Spec!$L$1:$L$2336) -> 2 | G45: 46118 | H45: =+VLOOKUP(D45,Tiempos!$A$1:$N$7440,3,FALSE) -> 86400 | I45: =+VLOOKUP(D45,Tiempos!$A$1:$N$7440,5,FALSE) -> 24 | J45: =+VLOOKUP(D45,Tiempos!$A$1:$N$7440,7,FALSE) -> INY09 | K45: =IF(VLOOKUP(C45,OP!$A$1:$P$27848,4,FALSE)="Cerrado",VLOOKUP(C45,OP!$A$1:$P$27848,10,FALSE),VLOOKUP(C45,OP!$A$1:$P$27848,9,FALSE)) -> 245300 | L45: =IF( IFERROR(VLOOKUP(D45,BD_Spec!$A$1:$D$2300,4,FALSE),"")="Producto Terminado", "TERMINADO", IFERROR(_xlfn.XLOOKUP(Ordenes_Mes[[#This Row],[Maquina]],Tiempos!$G$1:$G$766,Tiempos!$O$1:$O$766),"") ) -> PLÁSTICO_LIMA | M45: =IF(OR(Ordenes_Mes[[#This Row],[Proceso]]="Plástico_lima",Ordenes_Mes[[#This Row],[Proceso]]="soplado"),24,12) -> 24 | N45: =+VLOOKUP(D45,BD_Spec!$A$1:$K$2336,7,FALSE) -> Línea_045 | O45: =+VLOOKUP(D45,BD_Spec!$A$1:$K$2336,8,FALSE) -> Tapa | P45: =+VLOOKUP(C45,OP!$A$1:$P$27848,4,FALSE) -> CERRADO | Q45: =+VLOOKUP(C45,OP!$A$1:$P$27848,10,FALSE) -> 245300 | R45: =+Ordenes_Mes[[#This Row],[Fecha Inicio]] -> 46118
A46: =+MONTH(Ordenes_Mes[[#This Row],[Fecha_Conta]]) -> 4 | B46: =+VLOOKUP(C46,OP!$A$1:$P$27848,12,FALSE) -> 46118 | C46: 3879 | D46: 2310160476 | E46: Tapa Para Plumón 045 - NP Anaranjado | F46: =+_xlfn.XLOOKUP(D46,BD_Spec!$A$1:$A$2336,BD_Spec!$L$1:$L$2336) -> 3 | G46: 46118 | H46: =+VLOOKUP(D46,Tiempos!$A$1:$N$7440,3,FALSE) -> 86400 | I46: =+VLOOKUP(D46,Tiempos!$A$1:$N$7440,5,FALSE) -> 24 | J46: =+VLOOKUP(D46,Tiempos!$A$1:$N$7440,7,FALSE) -> INY09 | K46: =IF(VLOOKUP(C46,OP!$A$1:$P$27848,4,FALSE)="Cerrado",VLOOKUP(C46,OP!$A$1:$P$27848,10,FALSE),VLOOKUP(C46,OP!$A$1:$P$27848,9,FALSE)) -> 248900 | L46: =IF( IFERROR(VLOOKUP(D46,BD_Spec!$A$1:$D$2300,4,FALSE),"")="Producto Terminado", "TERMINADO", IFERROR(_xlfn.XLOOKUP(Ordenes_Mes[[#This Row],[Maquina]],Tiempos!$G$1:$G$766,Tiempos!$O$1:$O$766),"") ) -> PLÁSTICO_LIMA | M46: =IF(OR(Ordenes_Mes[[#This Row],[Proceso]]="Plástico_lima",Ordenes_Mes[[#This Row],[Proceso]]="soplado"),24,12) -> 24 | N46: =+VLOOKUP(D46,BD_Spec!$A$1:$K$2336,7,FALSE) -> Línea_045 | O46: =+VLOOKUP(D46,BD_Spec!$A$1:$K$2336,8,FALSE) -> Tapa | P46: =+VLOOKUP(C46,OP!$A$1:$P$27848,4,FALSE) -> CERRADO | Q46: =+VLOOKUP(C46,OP!$A$1:$P$27848,10,FALSE) -> 248900 | R46: =+Ordenes_Mes[[#This Row],[Fecha Inicio]] -> 46118
A47: =+MONTH(Ordenes_Mes[[#This Row],[Fecha_Conta]]) -> 4 | B47: =+VLOOKUP(C47,OP!$A$1:$P$27848,12,FALSE) -> 46118 | C47: 3878 | D47: 2310160475 | E47: Tapa Para Plumón 045 - NP Rosado | F47: =+_xlfn.XLOOKUP(D47,BD_Spec!$A$1:$A$2336,BD_Spec!$L$1:$L$2336) -> 4 | G47: 46118 | H47: =+VLOOKUP(D47,Tiempos!$A$1:$N$7440,3,FALSE) -> 86400 | I47: =+VLOOKUP(D47,Tiempos!$A$1:$N$7440,5,FALSE) -> 24 | J47: =+VLOOKUP(D47,Tiempos!$A$1:$N$7440,7,FALSE) -> INY09 | K47: =IF(VLOOKUP(C47,OP!$A$1:$P$27848,4,FALSE)="Cerrado",VLOOKUP(C47,OP!$A$1:$P$27848,10,FALSE),VLOOKUP(C47,OP!$A$1:$P$27848,9,FALSE)) -> 246400 | L47: =IF( IFERROR(VLOOKUP(D47,BD_Spec!$A$1:$D$2300,4,FALSE),"")="Producto Terminado", "TERMINADO", IFERROR(_xlfn.XLOOKUP(Ordenes_Mes[[#This Row],[Maquina]],Tiempos!$G$1:$G$766,Tiempos!$O$1:$O$766),"") ) -> PLÁSTICO_LIMA | M47: =IF(OR(Ordenes_Mes[[#This Row],[Proceso]]="Plástico_lima",Ordenes_Mes[[#This Row],[Proceso]]="soplado"),24,12) -> 24 | N47: =+VLOOKUP(D47,BD_Spec!$A$1:$K$2336,7,FALSE) -> Línea_045 | O47: =+VLOOKUP(D47,BD_Spec!$A$1:$K$2336,8,FALSE) -> Tapa | P47: =+VLOOKUP(C47,OP!$A$1:$P$27848,4,FALSE) -> CERRADO | Q47: =+VLOOKUP(C47,OP!$A$1:$P$27848,10,FALSE) -> 246400 | R47: =+Ordenes_Mes[[#This Row],[Fecha Inicio]] -> 46118
A48: =+MONTH(Ordenes_Mes[[#This Row],[Fecha_Conta]]) -> 4 | B48: =+VLOOKUP(C48,OP!$A$1:$P$27848,12,FALSE) -> 46118 | C48: 3873 | D48: 2310160469 | E48: Tapa Para Plumón 045 - NP Rojo | F48: =+_xlfn.XLOOKUP(D48,BD_Spec!$A$1:$A$2336,BD_Spec!$L$1:$L$2336) -> 5 | G48: 46118 | H48: =+VLOOKUP(D48,Tiempos!$A$1:$N$7440,3,FALSE) -> 86400 | I48: =+VLOOKUP(D48,Tiempos!$A$1:$N$7440,5,FALSE) -> 24 | J48: =+VLOOKUP(D48,Tiempos!$A$1:$N$7440,7,FALSE) -> INY09 | K48: =IF(VLOOKUP(C48,OP!$A$1:$P$27848,4,FALSE)="Cerrado",VLOOKUP(C48,OP!$A$1:$P$27848,10,FALSE),VLOOKUP(C48,OP!$A$1:$P$27848,9,FALSE)) -> 235200 | L48: =IF( IFERROR(VLOOKUP(D48,BD_Spec!$A$1:$D$2300,4,FALSE),"")="Producto Terminado", "TERMINADO", IFERROR(_xlfn.XLOOKUP(Ordenes_Mes[[#This Row],[Maquina]],Tiempos!$G$1:$G$766,Tiempos!$O$1:$O$766),"") ) -> PLÁSTICO_LIMA | M48: =IF(OR(Ordenes_Mes[[#This Row],[Proceso]]="Plástico_lima",Ordenes_Mes[[#This Row],[Proceso]]="soplado"),24,12) -> 24 | N48: =+VLOOKUP(D48,BD_Spec!$A$1:$K$2336,7,FALSE) -> Línea_045 | O48: =+VLOOKUP(D48,BD_Spec!$A$1:$K$2336,8,FALSE) -> Tapa | P48: =+VLOOKUP(C48,OP!$A$1:$P$27848,4,FALSE) -> CERRADO | Q48: =+VLOOKUP(C48,OP!$A$1:$P$27848,10,FALSE) -> 235200 | R48: =+Ordenes_Mes[[#This Row],[Fecha Inicio]] -> 46118
A49: =+MONTH(Ordenes_Mes[[#This Row],[Fecha_Conta]]) -> 4 | B49: =+VLOOKUP(C49,OP!$A$1:$P$27848,12,FALSE) -> 46118 | C49: 3920 | D49: 2310160457 | E49: Tapa Base Dosificador P/Témpera Rojo P.S. | F49: =+_xlfn.XLOOKUP(D49,BD_Spec!$A$1:$A$2336,BD_Spec!$L$1:$L$2336) -> 1 | G49: 46118 | H49: =+VLOOKUP(D49,Tiempos!$A$1:$N$7440,3,FALSE) -> 23563.636 | I49: =+VLOOKUP(D49,Tiempos!$A$1:$N$7440,5,FALSE) -> 24 | J49: =+VLOOKUP(D49,Tiempos!$A$1:$N$7440,7,FALSE) -> INY10 | K49: =IF(VLOOKUP(C49,OP!$A$1:$P$27848,4,FALSE)="Cerrado",VLOOKUP(C49,OP!$A$1:$P$27848,10,FALSE),VLOOKUP(C49,OP!$A$1:$P$27848,9,FALSE)) -> 237000 | L49: =IF( IFERROR(VLOOKUP(D49,BD_Spec!$A$1:$D$2300,4,FALSE),"")="Producto Terminado", "TERMINADO", IFERROR(_xlfn.XLOOKUP(Ordenes_Mes[[#This Row],[Maquina]],Tiempos!$G$1:$G$766,Tiempos!$O$1:$O$766),"") ) -> PLÁSTICO_LIMA | M49: =IF(OR(Ordenes_Mes[[#This Row],[Proceso]]="Plástico_lima",Ordenes_Mes[[#This Row],[Proceso]]="soplado"),24,12) -> 24 | N49: =+VLOOKUP(D49,BD_Spec!$A$1:$K$2336,7,FALSE) -> Línea_250cc | O49: =+VLOOKUP(D49,BD_Spec!$A$1:$K$2336,8,FALSE) -> Tapa Base | P49: =+VLOOKUP(C49,OP!$A$1:$P$27848,4,FALSE) -> CERRADO | Q49: =+VLOOKUP(C49,OP!$A$1:$P$27848,10,FALSE) -> 237000 | R49: =+Ordenes_Mes[[#This Row],[Fecha Inicio]] -> 46118
A50: =+MONTH(Ordenes_Mes[[#This Row],[Fecha_Conta]]) -> 4 | B50: =+VLOOKUP(C50,OP!$A$1:$P$27848,12,FALSE) -> 46118 | C50: 3914 | D50: 2310160002 | E50: Gotero Para Tinta 4k P.S. | F50: =+_xlfn.XLOOKUP(D50,BD_Spec!$A$1:$A$2336,BD_Spec!$L$1:$L$2336) -> 1 | G50: 46118 | H50: =+VLOOKUP(D50,Tiempos!$A$1:$N$7440,3,FALSE) -> 51054.545 | I50: =+VLOOKUP(D50,Tiempos!$A$1:$N$7440,5,FALSE) -> 24 | J50: =+VLOOKUP(D50,Tiempos!$A$1:$N$7440,7,FALSE) -> INY12 | K50: =IF(VLOOKUP(C50,OP!$A$1:$P$27848,4,FALSE)="Cerrado",VLOOKUP(C50,OP!$A$1:$P$27848,10,FALSE),VLOOKUP(C50,OP!$A$1:$P$27848,9,FALSE)) -> 145000 | L50: =IF( IFERROR(VLOOKUP(D50,BD_Spec!$A$1:$D$2300,4,FALSE),"")="Producto Terminado", "TERMINADO", IFERROR(_xlfn.XLOOKUP(Ordenes_Mes[[#This Row],[Maquina]],Tiempos!$G$1:$G$766,Tiempos!$O$1:$O$766),"") ) -> PLÁSTICO_LIMA | M50: =IF(OR(Ordenes_Mes[[#This Row],[Proceso]]="Plástico_lima",Ordenes_Mes[[#This Row],[Proceso]]="soplado"),24,12) -> 24 | N50: =+VLOOKUP(D50,BD_Spec!$A$1:$K$2336,7,FALSE) -> Línea_126 | O50: =+VLOOKUP(D50,BD_Spec!$A$1:$K$2336,8,FALSE) -> Gotero | P50: =+VLOOKUP(C50,OP!$A$1:$P$27848,4,FALSE) -> CERRADO | Q50: =+VLOOKUP(C50,OP!$A$1:$P$27848,10,FALSE) -> 145000 | R50: =+Ordenes_Mes[[#This Row],[Fecha Inicio]] -> 46118
A51: =+MONTH(Ordenes_Mes[[#This Row],[Fecha_Conta]]) -> 4 | B51: =+VLOOKUP(C51,OP!$A$1:$P$27848,12,FALSE) -> 46118 | C51: 3917 | D51: 2310160269 | E51: Sobre Tapa Dosificador Rojo P.S. | F51: 2 | G51: 46118 | H51: =+VLOOKUP(D51,Tiempos!$A$1:$N$7440,3,FALSE) -> 41142.857 | I51: =+VLOOKUP(D51,Tiempos!$A$1:$N$7440,5,FALSE) -> 24 | J51: =+VLOOKUP(D51,Tiempos!$A$1:$N$7440,7,FALSE) -> INY12 | K51: =IF(VLOOKUP(C51,OP!$A$1:$P$27848,4,FALSE)="Cerrado",VLOOKUP(C51,OP!$A$1:$P$27848,10,FALSE),VLOOKUP(C51,OP!$A$1:$P$27848,9,FALSE)) -> 465000 | L51: =IF( IFERROR(VLOOKUP(D51,BD_Spec!$A$1:$D$2300,4,FALSE),"")="Producto Terminado", "TERMINADO", IFERROR(_xlfn.XLOOKUP(Ordenes_Mes[[#This Row],[Maquina]],Tiempos!$G$1:$G$766,Tiempos!$O$1:$O$766),"") ) -> PLÁSTICO_LIMA | M51: =IF(OR(Ordenes_Mes[[#This Row],[Proceso]]="Plástico_lima",Ordenes_Mes[[#This Row],[Proceso]]="soplado"),24,12) -> 24 | N51: =+VLOOKUP(D51,BD_Spec!$A$1:$K$2336,7,FALSE) -> Línea_250cc | O51: =+VLOOKUP(D51,BD_Spec!$A$1:$K$2336,8,FALSE) -> Sobre Tapa | P51: =+VLOOKUP(C51,OP!$A$1:$P$27848,4,FALSE) -> CERRADO | Q51: =+VLOOKUP(C51,OP!$A$1:$P$27848,10,FALSE) -> 465000 | R51: =+Ordenes_Mes[[#This Row],[Fecha Inicio]] -> 46118
A52: =+MONTH(Ordenes_Mes[[#This Row],[Fecha_Conta]]) -> 4 | B52: =+VLOOKUP(C52,OP!$A$1:$P$27848,12,FALSE) -> 46118 | C52: 3902 | D52: 2310160491 | E52: Tapita Para Plumón 045 - NP Piel | F52: =+_xlfn.XLOOKUP(D52,BD_Spec!$A$1:$A$2336,BD_Spec!$L$1:$L$2336) -> 1 | G52: 46118 | H52: =+VLOOKUP(D52,Tiempos!$A$1:$N$7440,3,FALSE) -> 78801.303 | I52: =+VLOOKUP(D52,Tiempos!$A$1:$N$7440,5,FALSE) -> 24 | J52: =+VLOOKUP(D52,Tiempos!$A$1:$N$7440,7,FALSE) -> INY13 | K52: =IF(VLOOKUP(C52,OP!$A$1:$P$27848,4,FALSE)="Cerrado",VLOOKUP(C52,OP!$A$1:$P$27848,10,FALSE),VLOOKUP(C52,OP!$A$1:$P$27848,9,FALSE)) -> 244000 | L52: =IF( IFERROR(VLOOKUP(D52,BD_Spec!$A$1:$D$2300,4,FALSE),"")="Producto Terminado", "TERMINADO", IFERROR(_xlfn.XLOOKUP(Ordenes_Mes[[#This Row],[Maquina]],Tiempos!$G$1:$G$766,Tiempos!$O$1:$O$766),"") ) -> PLÁSTICO_LIMA | M52: =IF(OR(Ordenes_Mes[[#This Row],[Proceso]]="Plástico_lima",Ordenes_Mes[[#This Row],[Proceso]]="soplado"),24,12) -> 24 | N52: =+VLOOKUP(D52,BD_Spec!$A$1:$K$2336,7,FALSE) -> Línea_045 | O52: =+VLOOKUP(D52,BD_Spec!$A$1:$K$2336,8,FALSE) -> Tapita | P52: =+VLOOKUP(C52,OP!$A$1:$P$27848,4,FALSE) -> CERRADO | Q52: =+VLOOKUP(C52,OP!$A$1:$P$27848,10,FALSE) -> 244000 | R52: =+Ordenes_Mes[[#This Row],[Fecha Inicio]] -> 46118
A53: =+MONTH(Ordenes_Mes[[#This Row],[Fecha_Conta]]) -> 4 | B53: =+VLOOKUP(C53,OP!$A$1:$P$27848,12,FALSE) -> 46118 | C53: 3890 | D53: 2310160484 | E53: Tapita Para Plumón 045 - NP Amarillo | F53: =+_xlfn.XLOOKUP(D53,BD_Spec!$A$1:$A$2336,BD_Spec!$L$1:$L$2336) -> 2 | G53: 46118 | H53: =+VLOOKUP(D53,Tiempos!$A$1:$N$7440,3,FALSE) -> 78801.303 | I53: =+VLOOKUP(D53,Tiempos!$A$1:$N$7440,5,FALSE) -> 24 | J53: =+VLOOKUP(D53,Tiempos!$A$1:$N$7440,7,FALSE) -> INY13 | K53: =IF(VLOOKUP(C53,OP!$A$1:$P$27848,4,FALSE)="Cerrado",VLOOKUP(C53,OP!$A$1:$P$27848,10,FALSE),VLOOKUP(C53,OP!$A$1:$P$27848,9,FALSE)) -> 245350 | L53: =IF( IFERROR(VLOOKUP(D53,BD_Spec!$A$1:$D$2300,4,FALSE),"")="Producto Terminado", "TERMINADO", IFERROR(_xlfn.XLOOKUP(Ordenes_Mes[[#This Row],[Maquina]],Tiempos!$G$1:$G$766,Tiempos!$O$1:$O$766),"") ) -> PLÁSTICO_LIMA | M53: =IF(OR(Ordenes_Mes[[#This Row],[Proceso]]="Plástico_lima",Ordenes_Mes[[#This Row],[Proceso]]="soplado"),24,12) -> 24 | N53: =+VLOOKUP(D53,BD_Spec!$A$1:$K$2336,7,FALSE) -> Línea_045 | O53: =+VLOOKUP(D53,BD_Spec!$A$1:$K$2336,8,FALSE) -> Tapita | P53: =+VLOOKUP(C53,OP!$A$1:$P$27848,4,FALSE) -> CERRADO | Q53: =+VLOOKUP(C53,OP!$A$1:$P$27848,10,FALSE) -> 245350 | R53: =+Ordenes_Mes[[#This Row],[Fecha Inicio]] -> 46118
A54: =+MONTH(Ordenes_Mes[[#This Row],[Fecha_Conta]]) -> 4 | B54: =+VLOOKUP(C54,OP!$A$1:$P$27848,12,FALSE) -> 46118 | C54: 3894 | D54: 2310160488 | E54: Tapita Para Plumón 045 - NP Anaranjado | F54: =+_xlfn.XLOOKUP(D54,BD_Spec!$A$1:$A$2336,BD_Spec!$L$1:$L$2336) -> 3 | G54: 46118 | H54: =+VLOOKUP(D54,Tiempos!$A$1:$N$7440,3,FALSE) -> 78801.303 | I54: =+VLOOKUP(D54,Tiempos!$A$1:$N$7440,5,FALSE) -> 24 | J54: =+VLOOKUP(D54,Tiempos!$A$1:$N$7440,7,FALSE) -> INY13 | K54: =IF(VLOOKUP(C54,OP!$A$1:$P$27848,4,FALSE)="Cerrado",VLOOKUP(C54,OP!$A$1:$P$27848,10,FALSE),VLOOKUP(C54,OP!$A$1:$P$27848,9,FALSE)) -> 242000 | L54: =IF( IFERROR(VLOOKUP(D54,BD_Spec!$A$1:$D$2300,4,FALSE),"")="Producto Terminado", "TERMINADO", IFERROR(_xlfn.XLOOKUP(Ordenes_Mes[[#This Row],[Maquina]],Tiempos!$G$1:$G$766,Tiempos!$O$1:$O$766),"") ) -> PLÁSTICO_LIMA | M54: =IF(OR(Ordenes_Mes[[#This Row],[Proceso]]="Plástico_lima",Ordenes_Mes[[#This Row],[Proceso]]="soplado"),24,12) -> 24 | N54: =+VLOOKUP(D54,BD_Spec!$A$1:$K$2336,7,FALSE) -> Línea_045 | O54: =+VLOOKUP(D54,BD_Spec!$A$1:$K$2336,8,FALSE) -> Tapita | P54: =+VLOOKUP(C54,OP!$A$1:$P$27848,4,FALSE) -> CERRADO | Q54: =+VLOOKUP(C54,OP!$A$1:$P$27848,10,FALSE) -> 242000 | R54: =+Ordenes_Mes[[#This Row],[Fecha Inicio]] -> 46118
A55: =+MONTH(Ordenes_Mes[[#This Row],[Fecha_Conta]]) -> 4 | B55: =+VLOOKUP(C55,OP!$A$1:$P$27848,12,FALSE) -> 46118 | C55: 3893 | D55: 2310160487 | E55: Tapita Para Plumón 045 - NP Rosado | F55: =+_xlfn.XLOOKUP(D55,BD_Spec!$A$1:$A$2336,BD_Spec!$L$1:$L$2336) -> 4 | G55: 46118 | H55: =+VLOOKUP(D55,Tiempos!$A$1:$N$7440,3,FALSE) -> 78801.303 | I55: =+VLOOKUP(D55,Tiempos!$A$1:$N$7440,5,FALSE) -> 24 | J55: =+VLOOKUP(D55,Tiempos!$A$1:$N$7440,7,FALSE) -> INY13 | K55: =IF(VLOOKUP(C55,OP!$A$1:$P$27848,4,FALSE)="Cerrado",VLOOKUP(C55,OP!$A$1:$P$27848,10,FALSE),VLOOKUP(C55,OP!$A$1:$P$27848,9,FALSE)) -> 256000 | L55: =IF( IFERROR(VLOOKUP(D55,BD_Spec!$A$1:$D$2300,4,FALSE),"")="Producto Terminado", "TERMINADO", IFERROR(_xlfn.XLOOKUP(Ordenes_Mes[[#This Row],[Maquina]],Tiempos!$G$1:$G$766,Tiempos!$O$1:$O$766),"") ) -> PLÁSTICO_LIMA | M55: =IF(OR(Ordenes_Mes[[#This Row],[Proceso]]="Plástico_lima",Ordenes_Mes[[#This Row],[Proceso]]="soplado"),24,12) -> 24 | N55: =+VLOOKUP(D55,BD_Spec!$A$1:$K$2336,7,FALSE) -> Línea_045 | O55: =+VLOOKUP(D55,BD_Spec!$A$1:$K$2336,8,FALSE) -> Tapita | P55: =+VLOOKUP(C55,OP!$A$1:$P$27848,4,FALSE) -> CERRADO | Q55: =+VLOOKUP(C55,OP!$A$1:$P$27848,10,FALSE) -> 256000 | R55: =+Ordenes_Mes[[#This Row],[Fecha Inicio]] -> 46118
A56: =+MONTH(Ordenes_Mes[[#This Row],[Fecha_Conta]]) -> 4 | B56: =+VLOOKUP(C56,OP!$A$1:$P$27848,12,FALSE) -> 46118 | C56: 3888 | D56: 2310160481 | E56: Tapita Para Plumón 045 - NP Rojo | F56: =+_xlfn.XLOOKUP(D56,BD_Spec!$A$1:$A$2336,BD_Spec!$L$1:$L$2336) -> 5 | G56: 46118 | H56: =+VLOOKUP(D56,Tiempos!$A$1:$N$7440,3,FALSE) -> 78801.303 | I56: =+VLOOKUP(D56,Tiempos!$A$1:$N$7440,5,FALSE) -> 24 | J56: =+VLOOKUP(D56,Tiempos!$A$1:$N$7440,7,FALSE) -> INY13 | K56: =IF(VLOOKUP(C56,OP!$A$1:$P$27848,4,FALSE)="Cerrado",VLOOKUP(C56,OP!$A$1:$P$27848,10,FALSE),VLOOKUP(C56,OP!$A$1:$P$27848,9,FALSE)) -> 140000 | L56: =IF( IFERROR(VLOOKUP(D56,BD_Spec!$A$1:$D$2300,4,FALSE),"")="Producto Terminado", "TERMINADO", IFERROR(_xlfn.XLOOKUP(Ordenes_Mes[[#This Row],[Maquina]],Tiempos!$G$1:$G$766,Tiempos!$O$1:$O$766),"") ) -> PLÁSTICO_LIMA | M56: =IF(OR(Ordenes_Mes[[#This Row],[Proceso]]="Plástico_lima",Ordenes_Mes[[#This Row],[Proceso]]="soplado"),24,12) -> 24 | N56: =+VLOOKUP(D56,BD_Spec!$A$1:$K$2336,7,FALSE) -> Línea_045 | O56: =+VLOOKUP(D56,BD_Spec!$A$1:$K$2336,8,FALSE) -> Tapita | P56: =+VLOOKUP(C56,OP!$A$1:$P$27848,4,FALSE) -> CERRADO | Q56: =+VLOOKUP(C56,OP!$A$1:$P$27848,10,FALSE) -> 140000 | R56: =+Ordenes_Mes[[#This Row],[Fecha Inicio]] -> 46118
A57: =+MONTH(Ordenes_Mes[[#This Row],[Fecha_Conta]]) -> 4 | B57: =+VLOOKUP(C57,OP!$A$1:$P$27848,12,FALSE) -> 46118 | C57: 3922 | D57: 2310390064 | E57: Peine Patrullero Rojo Sin Cola 16A Lucas | F57: =+_xlfn.XLOOKUP(D57,BD_Spec!$A$1:$A$2336,BD_Spec!$L$1:$L$2336) -> 1 | G57: 46118 | H57: =+VLOOKUP(D57,Tiempos!$A$1:$N$7440,3,FALSE) -> 18000 | I57: =+VLOOKUP(D57,Tiempos!$A$1:$N$7440,5,FALSE) -> 24 | J57: =+VLOOKUP(D57,Tiempos!$A$1:$N$7440,7,FALSE) -> INY14 | K57: =IF(VLOOKUP(C57,OP!$A$1:$P$27848,4,FALSE)="Cerrado",VLOOKUP(C57,OP!$A$1:$P$27848,10,FALSE),VLOOKUP(C57,OP!$A$1:$P$27848,9,FALSE)) -> 100000 | L57: =IF( IFERROR(VLOOKUP(D57,BD_Spec!$A$1:$D$2300,4,FALSE),"")="Producto Terminado", "TERMINADO", IFERROR(_xlfn.XLOOKUP(Ordenes_Mes[[#This Row],[Maquina]],Tiempos!$G$1:$G$766,Tiempos!$O$1:$O$766),"") ) -> PLÁSTICO_LIMA | M57: =IF(OR(Ordenes_Mes[[#This Row],[Proceso]]="Plástico_lima",Ordenes_Mes[[#This Row],[Proceso]]="soplado"),24,12) -> 24 | N57: =+VLOOKUP(D57,BD_Spec!$A$1:$K$2336,7,FALSE) -> Línea_Peine | O57: =+VLOOKUP(D57,BD_Spec!$A$1:$K$2336,8,FALSE) -> Peine | P57: =+VLOOKUP(C57,OP!$A$1:$P$27848,4,FALSE) -> CERRADO | Q57: =+VLOOKUP(C57,OP!$A$1:$P$27848,10,FALSE) -> 100000 | R57: =+Ordenes_Mes[[#This Row],[Fecha Inicio]] -> 46118
A58: =+MONTH(Ordenes_Mes[[#This Row],[Fecha_Conta]]) -> 4 | B58: =+VLOOKUP(C58,OP!$A$1:$P$27848,12,FALSE) -> 46118 | C58: 3913 | D58: 2310160266 | E58: Tapa Roja Para Tinta LT-4 P.S. | F58: 2 | G58: 46139 | H58: =+VLOOKUP(D58,Tiempos!$A$1:$N$7440,3,FALSE) -> 14706.383 | I58: =+VLOOKUP(D58,Tiempos!$A$1:$N$7440,5,FALSE) -> 24 | J58: =+VLOOKUP(D58,Tiempos!$A$1:$N$7440,7,FALSE) -> INY14 | K58: =IF(VLOOKUP(C58,OP!$A$1:$P$27848,4,FALSE)="Cerrado",VLOOKUP(C58,OP!$A$1:$P$27848,10,FALSE),VLOOKUP(C58,OP!$A$1:$P$27848,9,FALSE)) -> 20000 | L58: =IF( IFERROR(VLOOKUP(D58,BD_Spec!$A$1:$D$2300,4,FALSE),"")="Producto Terminado", "TERMINADO", IFERROR(_xlfn.XLOOKUP(Ordenes_Mes[[#This Row],[Maquina]],Tiempos!$G$1:$G$766,Tiempos!$O$1:$O$766),"") ) -> PLÁSTICO_LIMA | M58: =IF(OR(Ordenes_Mes[[#This Row],[Proceso]]="Plástico_lima",Ordenes_Mes[[#This Row],[Proceso]]="soplado"),24,12) -> 24 | N58: =+VLOOKUP(D58,BD_Spec!$A$1:$K$2336,7,FALSE) -> Línea_126 | O58: =+VLOOKUP(D58,BD_Spec!$A$1:$K$2336,8,FALSE) -> Tapa | P58: =+VLOOKUP(C58,OP!$A$1:$P$27848,4,FALSE) -> CERRADO | Q58: =+VLOOKUP(C58,OP!$A$1:$P$27848,10,FALSE) -> 20000 | R58: =+Ordenes_Mes[[#This Row],[Fecha Inicio]] -> 46139
A59: =+MONTH(Ordenes_Mes[[#This Row],[Fecha_Conta]]) -> 4 | B59: =+VLOOKUP(C59,OP!$A$1:$P$27848,12,FALSE) -> 46128 | C59: 3998 | D59: 2110030195 | E59: Témpera Rojo Arti x 250 ML | F59: 1 | G59: 46128 | H59: =+VLOOKUP(D59,Tiempos!$A$1:$N$7440,3,FALSE) -> 7000 | I59: =+VLOOKUP(D59,Tiempos!$A$1:$N$7440,5,FALSE) -> 12 | J59: =+VLOOKUP(D59,Tiempos!$A$1:$N$7440,7,FALSE) -> MAQ_DOS3 | K59: =IF(VLOOKUP(C59,OP!$A$1:$P$27848,4,FALSE)="Cerrado",VLOOKUP(C59,OP!$A$1:$P$27848,10,FALSE),VLOOKUP(C59,OP!$A$1:$P$27848,9,FALSE)) -> 1000 | L59: =IF( IFERROR(VLOOKUP(D59,BD_Spec!$A$1:$D$2300,4,FALSE),"")="Producto Terminado", "TERMINADO", IFERROR(_xlfn.XLOOKUP(Ordenes_Mes[[#This Row],[Maquina]],Tiempos!$G$1:$G$766,Tiempos!$O$1:$O$766),"") ) -> TERMINADO | M59: =IF(OR(Ordenes_Mes[[#This Row],[Proceso]]="Plástico_lima",Ordenes_Mes[[#This Row],[Proceso]]="soplado"),24,12) -> 12 | N59: =+VLOOKUP(D59,BD_Spec!$A$1:$K$2336,7,FALSE) -> Línea_cola | O59: =+VLOOKUP(D59,BD_Spec!$A$1:$K$2336,8,FALSE) -> N/A | P59: =+VLOOKUP(C59,OP!$A$1:$P$27848,4,FALSE) -> CERRADO | Q59: =+VLOOKUP(C59,OP!$A$1:$P$27848,10,FALSE) -> 1000 | R59: =+Ordenes_Mes[[#This Row],[Fecha Inicio]] -> 46128
A60: =+MONTH(Ordenes_Mes[[#This Row],[Fecha_Conta]]) -> 4 | B60: =+VLOOKUP(C60,OP!$A$1:$P$27848,12,FALSE) -> 46125 | C60: 4002 | D60: 2110030200 | E60: Témpera Blanca Arti x 250 ML | F60: 2 | G60: 46134 | H60: =+VLOOKUP(D60,Tiempos!$A$1:$N$7440,3,FALSE) -> 7000 | I60: =+VLOOKUP(D60,Tiempos!$A$1:$N$7440,5,FALSE) -> 12 | J60: =+VLOOKUP(D60,Tiempos!$A$1:$N$7440,7,FALSE) -> MAQ_DOS3 | K60: =IF(VLOOKUP(C60,OP!$A$1:$P$27848,4,FALSE)="Cerrado",VLOOKUP(C60,OP!$A$1:$P$27848,10,FALSE),VLOOKUP(C60,OP!$A$1:$P$27848,9,FALSE)) -> 1200 | L60: =IF( IFERROR(VLOOKUP(D60,BD_Spec!$A$1:$D$2300,4,FALSE),"")="Producto Terminado", "TERMINADO", IFERROR(_xlfn.XLOOKUP(Ordenes_Mes[[#This Row],[Maquina]],Tiempos!$G$1:$G$766,Tiempos!$O$1:$O$766),"") ) -> TERMINADO | M60: =IF(OR(Ordenes_Mes[[#This Row],[Proceso]]="Plástico_lima",Ordenes_Mes[[#This Row],[Proceso]]="soplado"),24,12) -> 12 | N60: =+VLOOKUP(D60,BD_Spec!$A$1:$K$2336,7,FALSE) -> Línea_cola | O60: =+VLOOKUP(D60,BD_Spec!$A$1:$K$2336,8,FALSE) -> N/A | P60: =+VLOOKUP(C60,OP!$A$1:$P$27848,4,FALSE) -> CERRADO | Q60: =+VLOOKUP(C60,OP!$A$1:$P$27848,10,FALSE) -> 1200 | R60: =+Ordenes_Mes[[#This Row],[Fecha Inicio]] -> 46134
A61: =+MONTH(Ordenes_Mes[[#This Row],[Fecha_Conta]]) -> 4 | B61: =+VLOOKUP(C61,OP!$A$1:$P$27848,12,FALSE) -> 46125 | C61: 4000 | D61: 2110030237 | E61: Témpera Marrón Arti x 250 ML | F61: 3 | G61: 46134 | H61: =+VLOOKUP(D61,Tiempos!$A$1:$N$7440,3,FALSE) -> 7000 | I61: =+VLOOKUP(D61,Tiempos!$A$1:$N$7440,5,FALSE) -> 12 | J61: =+VLOOKUP(D61,Tiempos!$A$1:$N$7440,7,FALSE) -> MAQ_DOS3 | K61: =IF(VLOOKUP(C61,OP!$A$1:$P$27848,4,FALSE)="Cerrado",VLOOKUP(C61,OP!$A$1:$P$27848,10,FALSE),VLOOKUP(C61,OP!$A$1:$P$27848,9,FALSE)) -> 1000 | L61: =IF( IFERROR(VLOOKUP(D61,BD_Spec!$A$1:$D$2300,4,FALSE),"")="Producto Terminado", "TERMINADO", IFERROR(_xlfn.XLOOKUP(Ordenes_Mes[[#This Row],[Maquina]],Tiempos!$G$1:$G$766,Tiempos!$O$1:$O$766),"") ) -> TERMINADO | M61: =IF(OR(Ordenes_Mes[[#This Row],[Proceso]]="Plástico_lima",Ordenes_Mes[[#This Row],[Proceso]]="soplado"),24,12) -> 12 | N61: =+VLOOKUP(D61,BD_Spec!$A$1:$K$2336,7,FALSE) -> Línea_cola | O61: =+VLOOKUP(D61,BD_Spec!$A$1:$K$2336,8,FALSE) -> N/A | P61: =+VLOOKUP(C61,OP!$A$1:$P$27848,4,FALSE) -> CERRADO | Q61: =+VLOOKUP(C61,OP!$A$1:$P$27848,10,FALSE) -> 1000 | R61: =+Ordenes_Mes[[#This Row],[Fecha Inicio]] -> 46134
A62: =+MONTH(Ordenes_Mes[[#This Row],[Fecha_Conta]]) -> 4 | B62: =+VLOOKUP(C62,OP!$A$1:$P$27848,12,FALSE) -> 46135 | C62: 4043 | D62: 2110030238 | E62: Témpera Color Carne Arti x 250 ML | F62: 4 | G62: 46134 | H62: =+VLOOKUP(D62,Tiempos!$A$1:$N$7440,3,FALSE) -> 7000 | I62: =+VLOOKUP(D62,Tiempos!$A$1:$N$7440,5,FALSE) -> 12 | J62: =+VLOOKUP(D62,Tiempos!$A$1:$N$7440,7,FALSE) -> MAQ_DOS3 | K62: =IF(VLOOKUP(C62,OP!$A$1:$P$27848,4,FALSE)="Cerrado",VLOOKUP(C62,OP!$A$1:$P$27848,10,FALSE),VLOOKUP(C62,OP!$A$1:$P$27848,9,FALSE)) -> 1000 | L62: =IF( IFERROR(VLOOKUP(D62,BD_Spec!$A$1:$D$2300,4,FALSE),"")="Producto Terminado", "TERMINADO", IFERROR(_xlfn.XLOOKUP(Ordenes_Mes[[#This Row],[Maquina]],Tiempos!$G$1:$G$766,Tiempos!$O$1:$O$766),"") ) -> TERMINADO | M62: =IF(OR(Ordenes_Mes[[#This Row],[Proceso]]="Plástico_lima",Ordenes_Mes[[#This Row],[Proceso]]="soplado"),24,12) -> 12 | N62: =+VLOOKUP(D62,BD_Spec!$A$1:$K$2336,7,FALSE) -> Línea_cola | O62: =+VLOOKUP(D62,BD_Spec!$A$1:$K$2336,8,FALSE) -> N/A | P62: =+VLOOKUP(C62,OP!$A$1:$P$27848,4,FALSE) -> CERRADO | Q62: =+VLOOKUP(C62,OP!$A$1:$P$27848,10,FALSE) -> 1000 | R62: =+Ordenes_Mes[[#This Row],[Fecha Inicio]] -> 46134
A63: =+MONTH(Ordenes_Mes[[#This Row],[Fecha_Conta]]) -> 4 | B63: =+VLOOKUP(C63,OP!$A$1:$P$27848,12,FALSE) -> 46125 | C63: 3999 | D63: 2110030236 | E63: Témpera Violeta Arti x 250 ML | F63: 5 | G63: 46134 | H63: =+VLOOKUP(D63,Tiempos!$A$1:$N$7440,3,FALSE) -> 7000 | I63: =+VLOOKUP(D63,Tiempos!$A$1:$N$7440,5,FALSE) -> 12 | J63: =+VLOOKUP(D63,Tiempos!$A$1:$N$7440,7,FALSE) -> MAQ_DOS3 | K63: =IF(VLOOKUP(C63,OP!$A$1:$P$27848,4,FALSE)="Cerrado",VLOOKUP(C63,OP!$A$1:$P$27848,10,FALSE),VLOOKUP(C63,OP!$A$1:$P$27848,9,FALSE)) -> 750 | L63: =IF( IFERROR(VLOOKUP(D63,BD_Spec!$A$1:$D$2300,4,FALSE),"")="Producto Terminado", "TERMINADO", IFERROR(_xlfn.XLOOKUP(Ordenes_Mes[[#This Row],[Maquina]],Tiempos!$G$1:$G$766,Tiempos!$O$1:$O$766),"") ) -> TERMINADO | M63: =IF(OR(Ordenes_Mes[[#This Row],[Proceso]]="Plástico_lima",Ordenes_Mes[[#This Row],[Proceso]]="soplado"),24,12) -> 12 | N63: =+VLOOKUP(D63,BD_Spec!$A$1:$K$2336,7,FALSE) -> Línea_cola | O63: =+VLOOKUP(D63,BD_Spec!$A$1:$K$2336,8,FALSE) -> N/A | P63: =+VLOOKUP(C63,OP!$A$1:$P$27848,4,FALSE) -> CERRADO | Q63: =+VLOOKUP(C63,OP!$A$1:$P$27848,10,FALSE) -> 750 | R63: =+Ordenes_Mes[[#This Row],[Fecha Inicio]] -> 46134
A64: =+MONTH(Ordenes_Mes[[#This Row],[Fecha_Conta]]) -> 4 | B64: =+VLOOKUP(C64,OP!$A$1:$P$27848,12,FALSE) -> 46125 | C64: 4001 | D64: 2110030239 | E64: Témpera Azul Celeste Arti x 250 ML | F64: 6 | G64: 46134 | H64: =+VLOOKUP(D64,Tiempos!$A$1:$N$7440,3,FALSE) -> 7000 | I64: =+VLOOKUP(D64,Tiempos!$A$1:$N$7440,5,FALSE) -> 12 | J64: =+VLOOKUP(D64,Tiempos!$A$1:$N$7440,7,FALSE) -> MAQ_DOS3 | K64: =IF(VLOOKUP(C64,OP!$A$1:$P$27848,4,FALSE)="Cerrado",VLOOKUP(C64,OP!$A$1:$P$27848,10,FALSE),VLOOKUP(C64,OP!$A$1:$P$27848,9,FALSE)) -> 1000 | L64: =IF( IFERROR(VLOOKUP(D64,BD_Spec!$A$1:$D$2300,4,FALSE),"")="Producto Terminado", "TERMINADO", IFERROR(_xlfn.XLOOKUP(Ordenes_Mes[[#This Row],[Maquina]],Tiempos!$G$1:$G$766,Tiempos!$O$1:$O$766),"") ) -> TERMINADO | M64: =IF(OR(Ordenes_Mes[[#This Row],[Proceso]]="Plástico_lima",Ordenes_Mes[[#This Row],[Proceso]]="soplado"),24,12) -> 12 | N64: =+VLOOKUP(D64,BD_Spec!$A$1:$K$2336,7,FALSE) -> Línea_cola | O64: =+VLOOKUP(D64,BD_Spec!$A$1:$K$2336,8,FALSE) -> N/A | P64: =+VLOOKUP(C64,OP!$A$1:$P$27848,4,FALSE) -> CERRADO | Q64: =+VLOOKUP(C64,OP!$A$1:$P$27848,10,FALSE) -> 1000 | R64: =+Ordenes_Mes[[#This Row],[Fecha Inicio]] -> 46134
A65: =+MONTH(Ordenes_Mes[[#This Row],[Fecha_Conta]]) -> 4 | B65: =+VLOOKUP(C65,OP!$A$1:$P$27848,12,FALSE) -> 46118 | C65: 3944 | D65: 2500120066 | E65: Frascos Transparente de 125cc Para Témpera P.S. | F65: 1 | G65: 46118 | H65: =+VLOOKUP(D65,Tiempos!$A$1:$N$7440,3,FALSE) -> 6545.4545 | I65: =+VLOOKUP(D65,Tiempos!$A$1:$N$7440,5,FALSE) -> 24 | J65: =+VLOOKUP(D65,Tiempos!$A$1:$N$7440,7,FALSE) -> SOP01 | K65: =IF(VLOOKUP(C65,OP!$A$1:$P$27848,4,FALSE)="Cerrado",VLOOKUP(C65,OP!$A$1:$P$27848,10,FALSE),VLOOKUP(C65,OP!$A$1:$P$27848,9,FALSE)) -> 62300 | L65: =IF( IFERROR(VLOOKUP(D65,BD_Spec!$A$1:$D$2300,4,FALSE),"")="Producto Terminado", "TERMINADO", IFERROR(_xlfn.XLOOKUP(Ordenes_Mes[[#This Row],[Maquina]],Tiempos!$G$1:$G$766,Tiempos!$O$1:$O$766),"") ) -> PLÁSTICO_LIMA | M65: =IF(OR(Ordenes_Mes[[#This Row],[Proceso]]="Plástico_lima",Ordenes_Mes[[#This Row],[Proceso]]="soplado"),24,12) -> 24 | N65: =+VLOOKUP(D65,BD_Spec!$A$1:$K$2336,7,FALSE) -> Línea_Cola | O65: =+VLOOKUP(D65,BD_Spec!$A$1:$K$2336,8,FALSE) -> Frasco | P65: =+VLOOKUP(C65,OP!$A$1:$P$27848,4,FALSE) -> CERRADO | Q65: =+VLOOKUP(C65,OP!$A$1:$P$27848,10,FALSE) -> 62300 | R65: =+Ordenes_Mes[[#This Row],[Fecha Inicio]] -> 46118
A66: =+MONTH(Ordenes_Mes[[#This Row],[Fecha_Conta]]) -> 4 | B66: =+VLOOKUP(C66,OP!$A$1:$P$27848,12,FALSE) -> 46134 | C66: 4038 | D66: 2310230040 | E66: Frasco Blanco Ovalado Para Cola Sintética con Aplicador 125Gr P.S. | F66: 2 | G66: 46135 | H66: =+VLOOKUP(D66,Tiempos!$A$1:$N$7440,3,FALSE) -> 6545.4545 | I66: =+VLOOKUP(D66,Tiempos!$A$1:$N$7440,5,FALSE) -> 24 | J66: =+VLOOKUP(D66,Tiempos!$A$1:$N$7440,7,FALSE) -> SOP01 | K66: =IF(VLOOKUP(C66,OP!$A$1:$P$27848,4,FALSE)="Cerrado",VLOOKUP(C66,OP!$A$1:$P$27848,10,FALSE),VLOOKUP(C66,OP!$A$1:$P$27848,9,FALSE)) -> 14700 | L66: =IF( IFERROR(VLOOKUP(D66,BD_Spec!$A$1:$D$2300,4,FALSE),"")="Producto Terminado", "TERMINADO", IFERROR(_xlfn.XLOOKUP(Ordenes_Mes[[#This Row],[Maquina]],Tiempos!$G$1:$G$766,Tiempos!$O$1:$O$766),"") ) -> PLÁSTICO_LIMA | M66: =IF(OR(Ordenes_Mes[[#This Row],[Proceso]]="Plástico_lima",Ordenes_Mes[[#This Row],[Proceso]]="soplado"),24,12) -> 24 | N66: =+VLOOKUP(D66,BD_Spec!$A$1:$K$2336,7,FALSE) -> Línea_Cola | O66: =+VLOOKUP(D66,BD_Spec!$A$1:$K$2336,8,FALSE) -> Frasco | P66: =+VLOOKUP(C66,OP!$A$1:$P$27848,4,FALSE) -> CERRADO | Q66: =+VLOOKUP(C66,OP!$A$1:$P$27848,10,FALSE) -> 14700 | R66: =+Ordenes_Mes[[#This Row],[Fecha Inicio]] -> 46135
A67: =+MONTH(Ordenes_Mes[[#This Row],[Fecha_Conta]]) -> 4 | B67: =+VLOOKUP(C67,OP!$A$1:$P$27848,12,FALSE) -> 46118 | C67: 3938 | D67: 2310230012 | E67: Frasco Transparente de 250Gr Para Témpera P.S. | F67: =+_xlfn.XLOOKUP(D67,BD_Spec!$A$1:$A$2336,BD_Spec!$L$1:$L$2336) -> 1 | G67: 46118 | H67: =+VLOOKUP(D67,Tiempos!$A$1:$N$7440,3,FALSE) -> 13090.909 | I67: =+VLOOKUP(D67,Tiempos!$A$1:$N$7440,5,FALSE) -> 24 | J67: =+VLOOKUP(D67,Tiempos!$A$1:$N$7440,7,FALSE) -> SOP02 | K67: =IF(VLOOKUP(C67,OP!$A$1:$P$27848,4,FALSE)="Cerrado",VLOOKUP(C67,OP!$A$1:$P$27848,10,FALSE),VLOOKUP(C67,OP!$A$1:$P$27848,9,FALSE)) -> 20000 | L67: =IF( IFERROR(VLOOKUP(D67,BD_Spec!$A$1:$D$2300,4,FALSE),"")="Producto Terminado", "TERMINADO", IFERROR(_xlfn.XLOOKUP(Ordenes_Mes[[#This Row],[Maquina]],Tiempos!$G$1:$G$766,Tiempos!$O$1:$O$766),"") ) -> PLÁSTICO_LIMA | M67: =IF(OR(Ordenes_Mes[[#This Row],[Proceso]]="Plástico_lima",Ordenes_Mes[[#This Row],[Proceso]]="soplado"),24,12) -> 24 | N67: =+VLOOKUP(D67,BD_Spec!$A$1:$K$2336,7,FALSE) -> Línea_250cc | O67: =+VLOOKUP(D67,BD_Spec!$A$1:$K$2336,8,FALSE) -> Frasco | P67: =+VLOOKUP(C67,OP!$A$1:$P$27848,4,FALSE) -> CERRADO | Q67: =+VLOOKUP(C67,OP!$A$1:$P$27848,10,FALSE) -> 20000 | R67: =+Ordenes_Mes[[#This Row],[Fecha Inicio]] -> 46118
A68: =+MONTH(Ordenes_Mes[[#This Row],[Fecha_Conta]]) -> 4 | B68: =+VLOOKUP(C68,OP!$A$1:$P$27848,12,FALSE) -> 46132 | C68: 4031 | D68: 2310230012 | E68: Frasco Transparente de 250Gr Para Témpera P.S. | F68: 2 | G68: 46132 | H68: =+VLOOKUP(D68,Tiempos!$A$1:$N$7440,3,FALSE) -> 13090.909 | I68: =+VLOOKUP(D68,Tiempos!$A$1:$N$7440,5,FALSE) -> 24 | J68: =+VLOOKUP(D68,Tiempos!$A$1:$N$7440,7,FALSE) -> SOP02 | K68: =IF(VLOOKUP(C68,OP!$A$1:$P$27848,4,FALSE)="Cerrado",VLOOKUP(C68,OP!$A$1:$P$27848,10,FALSE),VLOOKUP(C68,OP!$A$1:$P$27848,9,FALSE)) -> 6000 | L68: =IF( IFERROR(VLOOKUP(D68,BD_Spec!$A$1:$D$2300,4,FALSE),"")="Producto Terminado", "TERMINADO", IFERROR(_xlfn.XLOOKUP(Ordenes_Mes[[#This Row],[Maquina]],Tiempos!$G$1:$G$766,Tiempos!$O$1:$O$766),"") ) -> PLÁSTICO_LIMA | M68: =IF(OR(Ordenes_Mes[[#This Row],[Proceso]]="Plástico_lima",Ordenes_Mes[[#This Row],[Proceso]]="soplado"),24,12) -> 24 | N68: =+VLOOKUP(D68,BD_Spec!$A$1:$K$2336,7,FALSE) -> Línea_250cc | O68: =+VLOOKUP(D68,BD_Spec!$A$1:$K$2336,8,FALSE) -> Frasco | P68: =+VLOOKUP(C68,OP!$A$1:$P$27848,4,FALSE) -> CERRADO | Q68: =+VLOOKUP(C68,OP!$A$1:$P$27848,10,FALSE) -> 6000 | R68: =+Ordenes_Mes[[#This Row],[Fecha Inicio]] -> 46132
A69: =+MONTH(Ordenes_Mes[[#This Row],[Fecha_Conta]]) -> 4 | B69: =+VLOOKUP(C69,OP!$A$1:$P$27848,12,FALSE) -> 46118 | C69: 3921 | D69: 2310230030 | E69: Frasco Blanco Ovalado Para Cola Sintética con Aplicador 250Gr P.S. | F69: 3 | G69: 46118 | H69: =+VLOOKUP(D69,Tiempos!$A$1:$N$7440,3,FALSE) -> 13090.909 | I69: =+VLOOKUP(D69,Tiempos!$A$1:$N$7440,5,FALSE) -> 24 | J69: =+VLOOKUP(D69,Tiempos!$A$1:$N$7440,7,FALSE) -> SOP02 | K69: =IF(VLOOKUP(C69,OP!$A$1:$P$27848,4,FALSE)="Cerrado",VLOOKUP(C69,OP!$A$1:$P$27848,10,FALSE),VLOOKUP(C69,OP!$A$1:$P$27848,9,FALSE)) -> 190000 | L69: =IF( IFERROR(VLOOKUP(D69,BD_Spec!$A$1:$D$2300,4,FALSE),"")="Producto Terminado", "TERMINADO", IFERROR(_xlfn.XLOOKUP(Ordenes_Mes[[#This Row],[Maquina]],Tiempos!$G$1:$G$766,Tiempos!$O$1:$O$766),"") ) -> PLÁSTICO_LIMA | M69: =IF(OR(Ordenes_Mes[[#This Row],[Proceso]]="Plástico_lima",Ordenes_Mes[[#This Row],[Proceso]]="soplado"),24,12) -> 24 | N69: =+VLOOKUP(D69,BD_Spec!$A$1:$K$2336,7,FALSE) -> Línea_Cola | O69: =+VLOOKUP(D69,BD_Spec!$A$1:$K$2336,8,FALSE) -> Frasco | P69: =+VLOOKUP(C69,OP!$A$1:$P$27848,4,FALSE) -> CERRADO | Q69: =+VLOOKUP(C69,OP!$A$1:$P$27848,10,FALSE) -> 190000 | R69: =+Ordenes_Mes[[#This Row],[Fecha Inicio]] -> 46118
A70: =+MONTH(Ordenes_Mes[[#This Row],[Fecha_Conta]]) -> 5 | B70: =+VLOOKUP(C70,OP!$A$1:$P$27848,12,FALSE) -> 46146 | C70: 4130 | D70: 2140150001 | E70: Archivador Plastificado Negro, Lomo Ancho, t/Oficio Layconsa Office | F70: 1 | G70: 46146 | H70: =+VLOOKUP(D70,Tiempos!$A$1:$N$7440,3,FALSE) -> 3500 | I70: =+VLOOKUP(D70,Tiempos!$A$1:$N$7440,5,FALSE) -> 12 | J70: =+VLOOKUP(D70,Tiempos!$A$1:$N$7440,7,FALSE) -> AMAN02 | K70: =IF(VLOOKUP(C70,OP!$A$1:$P$27848,4,FALSE)="Cerrado",VLOOKUP(C70,OP!$A$1:$P$27848,10,FALSE),VLOOKUP(C70,OP!$A$1:$P$27848,9,FALSE))+10000 -> 50000 | L70: =IF( IFERROR(VLOOKUP(D70,BD_Spec!$A$1:$D$2300,4,FALSE),"")="Producto Terminado", "TERMINADO", IFERROR(_xlfn.XLOOKUP(Ordenes_Mes[[#This Row],[Maquina]],Tiempos!$G$1:$G$766,Tiempos!$O$1:$O$766),"") ) -> TERMINADO | M70: =IF(OR(Ordenes_Mes[[#This Row],[Proceso]]="Plástico_lima",Ordenes_Mes[[#This Row],[Proceso]]="soplado"),24,12) -> 12 | N70: =+VLOOKUP(D70,BD_Spec!$A$1:$K$2336,7,FALSE) -> Manuales | O70: =+VLOOKUP(D70,BD_Spec!$A$1:$K$2336,8,FALSE) -> Archivador | P70: =+VLOOKUP(C70,OP!$A$1:$P$27848,4,FALSE) -> ABIERTO | Q70: =+VLOOKUP(C70,OP!$A$1:$P$27848,10,FALSE) -> 37632 | R70: =+Ordenes_Mes[[#This Row],[Fecha Inicio]] -> 46146
A71: =+MONTH(Ordenes_Mes[[#This Row],[Fecha_Conta]]) -> 5 | B71: =+VLOOKUP(C71,OP!$A$1:$P$27848,12,FALSE) -> 46146 | C71: 4037 | D71: 2140420001 | E71: Papel Mantequilla Rll x 1 Layconsa 50x70 | F71: 1 | G71: 46141 | H71: =+VLOOKUP(D71,Tiempos!$A$1:$N$7440,3,FALSE) -> 800 | I71: =+VLOOKUP(D71,Tiempos!$A$1:$N$7440,5,FALSE) -> 0 | J71: =+VLOOKUP(D71,Tiempos!$A$1:$N$7440,7,FALSE) -> AMAN02 | K71: =IF(VLOOKUP(C71,OP!$A$1:$P$27848,4,FALSE)="Cerrado",VLOOKUP(C71,OP!$A$1:$P$27848,10,FALSE),VLOOKUP(C71,OP!$A$1:$P$27848,9,FALSE)) -> 479 | L71: =IF( IFERROR(VLOOKUP(D71,BD_Spec!$A$1:$D$2300,4,FALSE),"")="Producto Terminado", "TERMINADO", IFERROR(_xlfn.XLOOKUP(Ordenes_Mes[[#This Row],[Maquina]],Tiempos!$G$1:$G$766,Tiempos!$O$1:$O$766),"") ) -> TERMINADO | M71: =IF(OR(Ordenes_Mes[[#This Row],[Proceso]]="Plástico_lima",Ordenes_Mes[[#This Row],[Proceso]]="soplado"),24,12) -> 12 | N71: =+VLOOKUP(D71,BD_Spec!$A$1:$K$2336,7,FALSE) -> Manuales | O71: =+VLOOKUP(D71,BD_Spec!$A$1:$K$2336,8,FALSE) -> Papelería | P71: =+VLOOKUP(C71,OP!$A$1:$P$27848,4,FALSE) -> CERRADO | Q71: =+VLOOKUP(C71,OP!$A$1:$P$27848,10,FALSE) -> 479 | R71: =+Ordenes_Mes[[#This Row],[Fecha Inicio]] -> 46141
A72: =+MONTH(Ordenes_Mes[[#This Row],[Fecha_Conta]]) -> 5 | B72: =+VLOOKUP(C72,OP!$A$1:$P$27848,12,FALSE) -> 46146 | C72: 4134 | D72: 2310320329 | E72: Carga Para Bolígrafo 036 PFTR Rojo N | F72: 1 | G72: 46141 | H72: =+VLOOKUP(D72,Tiempos!$A$1:$N$7440,3,FALSE) -> 35000 | I72: =+VLOOKUP(D72,Tiempos!$A$1:$N$7440,5,FALSE) -> 12 | J72: =+VLOOKUP(D72,Tiempos!$A$1:$N$7440,7,FALSE) -> CAR02 | K72: =IF(VLOOKUP(C72,OP!$A$1:$P$27848,4,FALSE)="Cerrado",VLOOKUP(C72,OP!$A$1:$P$27848,10,FALSE),VLOOKUP(C72,OP!$A$1:$P$27848,9,FALSE)) -> 62871 | L72: =IF( IFERROR(VLOOKUP(D72,BD_Spec!$A$1:$D$2300,4,FALSE),"")="Producto Terminado", "TERMINADO", IFERROR(_xlfn.XLOOKUP(Ordenes_Mes[[#This Row],[Maquina]],Tiempos!$G$1:$G$766,Tiempos!$O$1:$O$766),"") ) -> ENSAMBLE_LIMA | M72: =IF(OR(Ordenes_Mes[[#This Row],[Proceso]]="Plástico_lima",Ordenes_Mes[[#This Row],[Proceso]]="soplado"),24,12) -> 12 | N72: =+VLOOKUP(D72,BD_Spec!$A$1:$K$2336,7,FALSE) -> Línea_036 | O72: =+VLOOKUP(D72,BD_Spec!$A$1:$K$2336,8,FALSE) -> Colores | P72: =+VLOOKUP(C72,OP!$A$1:$P$27848,4,FALSE) -> CERRADO | Q72: =+VLOOKUP(C72,OP!$A$1:$P$27848,10,FALSE) -> 62871 | R72: =+Ordenes_Mes[[#This Row],[Fecha Inicio]] -> 46141
A73: =+MONTH(Ordenes_Mes[[#This Row],[Fecha_Conta]]) -> 5 | B73: =+VLOOKUP(C73,OP!$A$1:$P$27848,12,FALSE) -> 46146 | C73: 4008 | D73: 2310320330 | E73: Carga Para Bolígrafo 036 PFTR Negro N | F73: 2 | G73: 46141 | H73: =+VLOOKUP(D73,Tiempos!$A$1:$N$7440,3,FALSE) -> 35000 | I73: =+VLOOKUP(D73,Tiempos!$A$1:$N$7440,5,FALSE) -> 12 | J73: =+VLOOKUP(D73,Tiempos!$A$1:$N$7440,7,FALSE) -> CAR02 | K73: =IF(VLOOKUP(C73,OP!$A$1:$P$27848,4,FALSE)="Cerrado",VLOOKUP(C73,OP!$A$1:$P$27848,10,FALSE),VLOOKUP(C73,OP!$A$1:$P$27848,9,FALSE)) -> 100967 | L73: =IF( IFERROR(VLOOKUP(D73,BD_Spec!$A$1:$D$2300,4,FALSE),"")="Producto Terminado", "TERMINADO", IFERROR(_xlfn.XLOOKUP(Ordenes_Mes[[#This Row],[Maquina]],Tiempos!$G$1:$G$766,Tiempos!$O$1:$O$766),"") ) -> ENSAMBLE_LIMA | M73: =IF(OR(Ordenes_Mes[[#This Row],[Proceso]]="Plástico_lima",Ordenes_Mes[[#This Row],[Proceso]]="soplado"),24,12) -> 12 | N73: =+VLOOKUP(D73,BD_Spec!$A$1:$K$2336,7,FALSE) -> Línea_036 | O73: =+VLOOKUP(D73,BD_Spec!$A$1:$K$2336,8,FALSE) -> Colores | P73: =+VLOOKUP(C73,OP!$A$1:$P$27848,4,FALSE) -> CERRADO | Q73: =+VLOOKUP(C73,OP!$A$1:$P$27848,10,FALSE) -> 100967 | R73: =+Ordenes_Mes[[#This Row],[Fecha Inicio]] -> 46141
A74: =+MONTH(Ordenes_Mes[[#This Row],[Fecha_Conta]]) -> 5 | B74: =+VLOOKUP(C74,OP!$A$1:$P$27848,12,FALSE) -> 46146 | C74: 4133 | D74: 2110030170 | E74: Témperas Set x 7 x 30cc ARTI | F74: 2 | G74: 46141 | H74: =+VLOOKUP(D74,Tiempos!$A$1:$N$7440,3,FALSE) -> 6000 | I74: =+VLOOKUP(D74,Tiempos!$A$1:$N$7440,5,FALSE) -> 12 | J74: =+VLOOKUP(D74,Tiempos!$A$1:$N$7440,7,FALSE) -> DOSI_TEMP01 | K74: =IF(VLOOKUP(C74,OP!$A$1:$P$27848,4,FALSE)="Cerrado",VLOOKUP(C74,OP!$A$1:$P$27848,10,FALSE),VLOOKUP(C74,OP!$A$1:$P$27848,9,FALSE)) -> 5187 | L74: =IF( IFERROR(VLOOKUP(D74,BD_Spec!$A$1:$D$2300,4,FALSE),"")="Producto Terminado", "TERMINADO", IFERROR(_xlfn.XLOOKUP(Ordenes_Mes[[#This Row],[Maquina]],Tiempos!$G$1:$G$766,Tiempos!$O$1:$O$766),"") ) -> TERMINADO | M74: =IF(OR(Ordenes_Mes[[#This Row],[Proceso]]="Plástico_lima",Ordenes_Mes[[#This Row],[Proceso]]="soplado"),24,12) -> 12 | N74: =+VLOOKUP(D74,BD_Spec!$A$1:$K$2336,7,FALSE) -> Línea_30cc | O74: =+VLOOKUP(D74,BD_Spec!$A$1:$K$2336,8,FALSE) -> Témpera | P74: =+VLOOKUP(C74,OP!$A$1:$P$27848,4,FALSE) -> CERRADO | Q74: =+VLOOKUP(C74,OP!$A$1:$P$27848,10,FALSE) -> 5187 | R74: =+Ordenes_Mes[[#This Row],[Fecha Inicio]] -> 46141
A75: =+MONTH(Ordenes_Mes[[#This Row],[Fecha_Conta]]) -> 5 | B75: =+VLOOKUP(C75,OP!$A$1:$P$27848,12,FALSE) -> 46146 | C75: 4096 | D75: 2110080227 | E75: Bolígrafo Layconsa crystal L-036 Azul | F75: 1 | G75: 46141 | H75: =+VLOOKUP(D75,Tiempos!$A$1:$N$7440,3,FALSE) -> 35000 | I75: =+VLOOKUP(D75,Tiempos!$A$1:$N$7440,5,FALSE) -> 12 | J75: =+VLOOKUP(D75,Tiempos!$A$1:$N$7440,7,FALSE) -> ENS03 | K75: =IF(VLOOKUP(C75,OP!$A$1:$P$27848,4,FALSE)="Cerrado",VLOOKUP(C75,OP!$A$1:$P$27848,10,FALSE),VLOOKUP(C75,OP!$A$1:$P$27848,9,FALSE)) -> 99250 | L75: =IF( IFERROR(VLOOKUP(D75,BD_Spec!$A$1:$D$2300,4,FALSE),"")="Producto Terminado", "TERMINADO", IFERROR(_xlfn.XLOOKUP(Ordenes_Mes[[#This Row],[Maquina]],Tiempos!$G$1:$G$766,Tiempos!$O$1:$O$766),"") ) -> TERMINADO | M75: =IF(OR(Ordenes_Mes[[#This Row],[Proceso]]="Plástico_lima",Ordenes_Mes[[#This Row],[Proceso]]="soplado"),24,12) -> 12 | N75: =+VLOOKUP(D75,BD_Spec!$A$1:$K$2336,7,FALSE) -> Línea_036 | O75: =+VLOOKUP(D75,BD_Spec!$A$1:$K$2336,8,FALSE) -> N/A | P75: =+VLOOKUP(C75,OP!$A$1:$P$27848,4,FALSE) -> CERRADO | Q75: =+VLOOKUP(C75,OP!$A$1:$P$27848,10,FALSE) -> 99250 | R75: =+Ordenes_Mes[[#This Row],[Fecha Inicio]] -> 46141
A76: =+MONTH(Ordenes_Mes[[#This Row],[Fecha_Conta]]) -> 5 | B76: =+VLOOKUP(C76,OP!$A$1:$P$27848,12,FALSE) -> 46146 | C76: 4135 | D76: 2310160282 | E76: Tapa Dosificador Ensamblada Rojo | F76: 1 | G76: 46146 | H76: =+VLOOKUP(D76,Tiempos!$A$1:$N$7440,3,FALSE) -> 30000 | I76: =+VLOOKUP(D76,Tiempos!$A$1:$N$7440,5,FALSE) -> 12 | J76: =+VLOOKUP(D76,Tiempos!$A$1:$N$7440,7,FALSE) -> ENS04 | K76: =IF(VLOOKUP(C76,OP!$A$1:$P$27848,4,FALSE)="Cerrado",VLOOKUP(C76,OP!$A$1:$P$27848,10,FALSE),VLOOKUP(C76,OP!$A$1:$P$27848,9,FALSE)) -> 349814 | L76: =IF( IFERROR(VLOOKUP(D76,BD_Spec!$A$1:$D$2300,4,FALSE),"")="Producto Terminado", "TERMINADO", IFERROR(_xlfn.XLOOKUP(Ordenes_Mes[[#This Row],[Maquina]],Tiempos!$G$1:$G$766,Tiempos!$O$1:$O$766),"") ) -> ENSAMBLE_LIMA | M76: =IF(OR(Ordenes_Mes[[#This Row],[Proceso]]="Plástico_lima",Ordenes_Mes[[#This Row],[Proceso]]="soplado"),24,12) -> 12 | N76: =+VLOOKUP(D76,BD_Spec!$A$1:$K$2336,7,FALSE) -> Línea_250cc | O76: =+VLOOKUP(D76,BD_Spec!$A$1:$K$2336,8,FALSE) -> Dosificador | P76: =+VLOOKUP(C76,OP!$A$1:$P$27848,4,FALSE) -> CERRADO | Q76: =+VLOOKUP(C76,OP!$A$1:$P$27848,10,FALSE) -> 349814 | R76: =+Ordenes_Mes[[#This Row],[Fecha Inicio]] -> 46146
A77: =+MONTH(Ordenes_Mes[[#This Row],[Fecha_Conta]]) -> 5 | B77: =+VLOOKUP(C77,OP!$A$1:$P$27848,12,FALSE) -> 46146 | C77: 4136 | D77: 2310160552 | E77: Tapa Dosificador Ensamblada Rojo Paleta | F77: 2 | G77: 46160 | H77: =+VLOOKUP(D77,Tiempos!$A$1:$N$7440,3,FALSE) -> 24000 | I77: =+VLOOKUP(D77,Tiempos!$A$1:$N$7440,5,FALSE) -> 12 | J77: =+VLOOKUP(D77,Tiempos!$A$1:$N$7440,7,FALSE) -> ENS04 | K77: =IF(VLOOKUP(C77,OP!$A$1:$P$27848,4,FALSE)="Cerrado",VLOOKUP(C77,OP!$A$1:$P$27848,10,FALSE),VLOOKUP(C77,OP!$A$1:$P$27848,9,FALSE)) -> 150000 | L77: =IF( IFERROR(VLOOKUP(D77,BD_Spec!$A$1:$D$2300,4,FALSE),"")="Producto Terminado", "TERMINADO", IFERROR(_xlfn.XLOOKUP(Ordenes_Mes[[#This Row],[Maquina]],Tiempos!$G$1:$G$766,Tiempos!$O$1:$O$766),"") ) -> ENSAMBLE_LIMA | M77: =IF(OR(Ordenes_Mes[[#This Row],[Proceso]]="Plástico_lima",Ordenes_Mes[[#This Row],[Proceso]]="soplado"),24,12) -> 12 | N77: =+VLOOKUP(D77,BD_Spec!$A$1:$K$2336,7,FALSE) -> Línea_Cola | O77: =+VLOOKUP(D77,BD_Spec!$A$1:$K$2336,8,FALSE) -> Dosificador | P77: =+VLOOKUP(C77,OP!$A$1:$P$27848,4,FALSE) -> ABIERTO | Q77: =+VLOOKUP(C77,OP!$A$1:$P$27848,10,FALSE) -> 50150 | R77: =+Ordenes_Mes[[#This Row],[Fecha Inicio]] -> 46160
A78: =+MONTH(Ordenes_Mes[[#This Row],[Fecha_Conta]]) -> 5 | B78: =+VLOOKUP(C78,OP!$A$1:$P$27848,12,FALSE) -> 46146 | C78: 4132 | D78: 2310340006 | E78: Punta Carga 036F + Adaptador | F78: 1 | G78: 46141 | H78: =+VLOOKUP(D78,Tiempos!$A$1:$N$7440,3,FALSE) -> 30000 | I78: =+VLOOKUP(D78,Tiempos!$A$1:$N$7440,5,FALSE) -> 12 | J78: =+VLOOKUP(D78,Tiempos!$A$1:$N$7440,7,FALSE) -> ENS05 | K78: =IF(VLOOKUP(C78,OP!$A$1:$P$27848,4,FALSE)="Cerrado",VLOOKUP(C78,OP!$A$1:$P$27848,10,FALSE),VLOOKUP(C78,OP!$A$1:$P$27848,9,FALSE)) -> 500000 | L78: =IF( IFERROR(VLOOKUP(D78,BD_Spec!$A$1:$D$2300,4,FALSE),"")="Producto Terminado", "TERMINADO", IFERROR(_xlfn.XLOOKUP(Ordenes_Mes[[#This Row],[Maquina]],Tiempos!$G$1:$G$766,Tiempos!$O$1:$O$766),"") ) -> ENSAMBLE_LIMA | M78: =IF(OR(Ordenes_Mes[[#This Row],[Proceso]]="Plástico_lima",Ordenes_Mes[[#This Row],[Proceso]]="soplado"),24,12) -> 12 | N78: =+VLOOKUP(D78,BD_Spec!$A$1:$K$2336,7,FALSE) -> Línea_036 | O78: =+VLOOKUP(D78,BD_Spec!$A$1:$K$2336,8,FALSE) -> Colores | P78: =+VLOOKUP(C78,OP!$A$1:$P$27848,4,FALSE) -> ABIERTO | Q78: =+VLOOKUP(C78,OP!$A$1:$P$27848,10,FALSE) -> 700000 | R78: =+Ordenes_Mes[[#This Row],[Fecha Inicio]] -> 46141
A79: =+MONTH(Ordenes_Mes[[#This Row],[Fecha_Conta]]) -> 5 | B79: =+VLOOKUP(C79,OP!$A$1:$P$27848,12,FALSE) -> 46146 | C79: 4131 | D79: 2310360001 | E79: Tubito Para Bolígrafo 036 | F79: 1 | G79: 46141 | H79: =+VLOOKUP(D79,Tiempos!$A$1:$N$7440,3,FALSE) -> 50000 | I79: =+VLOOKUP(D79,Tiempos!$A$1:$N$7440,5,FALSE) -> 12 | J79: =+VLOOKUP(D79,Tiempos!$A$1:$N$7440,7,FALSE) -> EXT01 | K79: =IF(VLOOKUP(C79,OP!$A$1:$P$27848,4,FALSE)="Cerrado",VLOOKUP(C79,OP!$A$1:$P$27848,10,FALSE),VLOOKUP(C79,OP!$A$1:$P$27848,9,FALSE)) -> 1000000 | L79: =IF( IFERROR(VLOOKUP(D79,BD_Spec!$A$1:$D$2300,4,FALSE),"")="Producto Terminado", "TERMINADO", IFERROR(_xlfn.XLOOKUP(Ordenes_Mes[[#This Row],[Maquina]],Tiempos!$G$1:$G$766,Tiempos!$O$1:$O$766),"") ) -> ENSAMBLE_LIMA | M79: =IF(OR(Ordenes_Mes[[#This Row],[Proceso]]="Plástico_lima",Ordenes_Mes[[#This Row],[Proceso]]="soplado"),24,12) -> 12 | N79: =+VLOOKUP(D79,BD_Spec!$A$1:$K$2336,7,FALSE) -> Línea_036 | O79: =+VLOOKUP(D79,BD_Spec!$A$1:$K$2336,8,FALSE) -> Tubo | P79: =+VLOOKUP(C79,OP!$A$1:$P$27848,4,FALSE) -> ABIERTO | Q79: =+VLOOKUP(C79,OP!$A$1:$P$27848,10,FALSE) -> 751893 | R79: =+Ordenes_Mes[[#This Row],[Fecha Inicio]] -> 46141
A80: =+MONTH(Ordenes_Mes[[#This Row],[Fecha_Conta]]) -> 4 | B80: =+VLOOKUP(C80,OP!$A$1:$P$27848,12,FALSE) -> 46140 | C80: 4107 | D80: 2310030020 | E80: Masa Para Témperas Blanca LYC P.S. | F80: 1 | G80: 46141 | H80: =+VLOOKUP(D80,Tiempos!$A$1:$N$7440,3,FALSE) -> 2850 | I80: =+VLOOKUP(D80,Tiempos!$A$1:$N$7440,5,FALSE) -> 12 | J80: =+VLOOKUP(D80,Tiempos!$A$1:$N$7440,7,FALSE) -> HUBBES02 | K80: =IF(VLOOKUP(C80,OP!$A$1:$P$27848,4,FALSE)="Cerrado",VLOOKUP(C80,OP!$A$1:$P$27848,10,FALSE),VLOOKUP(C80,OP!$A$1:$P$27848,9,FALSE)) -> 600 | L80: =IF( IFERROR(VLOOKUP(D80,BD_Spec!$A$1:$D$2300,4,FALSE),"")="Producto Terminado", "TERMINADO", IFERROR(_xlfn.XLOOKUP(Ordenes_Mes[[#This Row],[Maquina]],Tiempos!$G$1:$G$766,Tiempos!$O$1:$O$766),"") ) -> MASAS_TINTAS_LIMA | M80: =IF(OR(Ordenes_Mes[[#This Row],[Proceso]]="Plástico_lima",Ordenes_Mes[[#This Row],[Proceso]]="soplado"),24,12) -> 12 | N80: =+VLOOKUP(D80,BD_Spec!$A$1:$K$2336,7,FALSE) -> Línea_30cc | O80: =+VLOOKUP(D80,BD_Spec!$A$1:$K$2336,8,FALSE) -> Colores | P80: =+VLOOKUP(C80,OP!$A$1:$P$27848,4,FALSE) -> CERRADO | Q80: =+VLOOKUP(C80,OP!$A$1:$P$27848,10,FALSE) -> 600 | R80: =+Ordenes_Mes[[#This Row],[Fecha Inicio]] -> 46141
A81: =+MONTH(Ordenes_Mes[[#This Row],[Fecha_Conta]]) -> 4 | B81: =+VLOOKUP(C81,OP!$A$1:$P$27848,12,FALSE) -> 46140 | C81: 4106 | D81: 2310030017 | E81: Masa Para Témperas Roja LYC P.S. | F81: 2 | G81: 46141 | H81: =+VLOOKUP(D81,Tiempos!$A$1:$N$7440,3,FALSE) -> 2700 | I81: =+VLOOKUP(D81,Tiempos!$A$1:$N$7440,5,FALSE) -> 12 | J81: =+VLOOKUP(D81,Tiempos!$A$1:$N$7440,7,FALSE) -> HUBBES02 | K81: =IF(VLOOKUP(C81,OP!$A$1:$P$27848,4,FALSE)="Cerrado",VLOOKUP(C81,OP!$A$1:$P$27848,10,FALSE),VLOOKUP(C81,OP!$A$1:$P$27848,9,FALSE)) -> 600 | L81: =IF( IFERROR(VLOOKUP(D81,BD_Spec!$A$1:$D$2300,4,FALSE),"")="Producto Terminado", "TERMINADO", IFERROR(_xlfn.XLOOKUP(Ordenes_Mes[[#This Row],[Maquina]],Tiempos!$G$1:$G$766,Tiempos!$O$1:$O$766),"") ) -> MASAS_TINTAS_LIMA | M81: =IF(OR(Ordenes_Mes[[#This Row],[Proceso]]="Plástico_lima",Ordenes_Mes[[#This Row],[Proceso]]="soplado"),24,12) -> 12 | N81: =+VLOOKUP(D81,BD_Spec!$A$1:$K$2336,7,FALSE) -> Línea_30cc | O81: =+VLOOKUP(D81,BD_Spec!$A$1:$K$2336,8,FALSE) -> Colores | P81: =+VLOOKUP(C81,OP!$A$1:$P$27848,4,FALSE) -> CERRADO | Q81: =+VLOOKUP(C81,OP!$A$1:$P$27848,10,FALSE) -> 600 | R81: =+Ordenes_Mes[[#This Row],[Fecha Inicio]] -> 46141
A82: =+MONTH(Ordenes_Mes[[#This Row],[Fecha_Conta]]) -> 5 | B82: =+VLOOKUP(C82,OP!$A$1:$P$27848,12,FALSE) -> 46146 | C82: 4123 | D82: 2310160062 | E82: Tapa Para Bolígrafo 036 Azul | F82: 1 | G82: 46146 | H82: =+VLOOKUP(D82,Tiempos!$A$1:$N$7440,3,FALSE) -> 69120 | I82: =+VLOOKUP(D82,Tiempos!$A$1:$N$7440,5,FALSE) -> 24 | J82: =+VLOOKUP(D82,Tiempos!$A$1:$N$7440,7,FALSE) -> INY01 | K82: =IF(VLOOKUP(C82,OP!$A$1:$P$27848,4,FALSE)="Cerrado",VLOOKUP(C82,OP!$A$1:$P$27848,10,FALSE),VLOOKUP(C82,OP!$A$1:$P$27848,9,FALSE)) -> 198600 | L82: =IF( IFERROR(VLOOKUP(D82,BD_Spec!$A$1:$D$2300,4,FALSE),"")="Producto Terminado", "TERMINADO", IFERROR(_xlfn.XLOOKUP(Ordenes_Mes[[#This Row],[Maquina]],Tiempos!$G$1:$G$766,Tiempos!$O$1:$O$766),"") ) -> PLÁSTICO_LIMA | M82: =IF(OR(Ordenes_Mes[[#This Row],[Proceso]]="Plástico_lima",Ordenes_Mes[[#This Row],[Proceso]]="soplado"),24,12) -> 24 | N82: =+VLOOKUP(D82,BD_Spec!$A$1:$K$2336,7,FALSE) -> Línea_036 | O82: =+VLOOKUP(D82,BD_Spec!$A$1:$K$2336,8,FALSE) -> Tapa | P82: =+VLOOKUP(C82,OP!$A$1:$P$27848,4,FALSE) -> CERRADO | Q82: =+VLOOKUP(C82,OP!$A$1:$P$27848,10,FALSE) -> 198600 | R82: =+Ordenes_Mes[[#This Row],[Fecha Inicio]] -> 46146
... A84: =+MONTH(Ordenes_Mes[[#This Row],[Fecha_Conta]]) -> 5 | B84: =+VLOOKUP(C84,OP!$A$1:$P$27848,12,FALSE) -> 46146 | C84: 4125 | D84: 2310160064 | E84: Tapa Para Bolígrafo 036 Negro | F84: 3 | G84: 46146 | H84: =+VLOOKUP(D84,Tiempos!$A$1:$N$7440,3,FALSE) -> 69120 | I84: =+VLOOKUP(D84,Tiempos!$A$1:$N$7440,5,FALSE) -> 24 | J84: =+VLOOKUP(D84,Tiempos!$A$1:$N$7440,7,FALSE) -> INY01 | K84: =IF(VLOOKUP(C84,OP!$A$1:$P$27848,4,FALSE)="Cerrado",VLOOKUP(C84,OP!$A$1:$P$27848,10,FALSE),VLOOKUP(C84,OP!$A$1:$P$27848,9,FALSE)) -> 109850 | L84: =IF( IFERROR(VLOOKUP(D84,BD_Spec!$A$1:$D$2300,4,FALSE),"")="Producto Terminado", "TERMINADO", IFERROR(_xlfn.XLOOKUP(Ordenes_Mes[[#This Row],[Maquina]],Tiempos!$G$1:$G$766,Tiempos!$O$1:$O$766),"") ) -> PLÁSTICO_LIMA | M84: =IF(OR(Ordenes_Mes[[#This Row],[Proceso]]="Plástico_lima",Ordenes_Mes[[#This Row],[Proceso]]="soplado"),24,12) -> 24 | N84: =+VLOOKUP(D84,BD_Spec!$A$1:$K$2336,7,FALSE) -> Línea_036 | O84: =+VLOOKUP(D84,BD_Spec!$A$1:$K$2336,8,FALSE) -> Tapa | P84: =+VLOOKUP(C84,OP!$A$1:$P$27848,4,FALSE) -> CERRADO | Q84: =+VLOOKUP(C84,OP!$A$1:$P$27848,10,FALSE) -> 109850 | R84: =+Ordenes_Mes[[#This Row],[Fecha Inicio]] -> 46146
A85: =+MONTH(Ordenes_Mes[[#This Row],[Fecha_Conta]]) -> 6 | B85: =+VLOOKUP(C85,OP!$A$1:$P$27848,12,FALSE) -> 46174 | C85: 4052 | D85: 2310170002 | E85: Base Para Limpiatipos x 35gr P.S. | F85: 4 | G85: 46198 | H85: =+VLOOKUP(D85,Tiempos!$A$1:$N$7440,3,FALSE) -> 41739.13 | I85: =+VLOOKUP(D85,Tiempos!$A$1:$N$7440,5,FALSE) -> 24 | J85: =+VLOOKUP(D85,Tiempos!$A$1:$N$7440,7,FALSE) -> INY01 | K85: 400000 | L85: =IF( IFERROR(VLOOKUP(D85,BD_Spec!$A$1:$D$2300,4,FALSE),"")="Producto Terminado", "TERMINADO", IFERROR(_xlfn.XLOOKUP(Ordenes_Mes[[#This Row],[Maquina]],Tiempos!$G$1:$G$766,Tiempos!$O$1:$O$766),"") ) -> PLÁSTICO_LIMA | M85: =IF(OR(Ordenes_Mes[[#This Row],[Proceso]]="Plástico_lima",Ordenes_Mes[[#This Row],[Proceso]]="soplado"),24,12) -> 24 | N85: =+VLOOKUP(D85,BD_Spec!$A$1:$K$2336,7,FALSE) -> Línea_Limpiatipo | O85: =+VLOOKUP(D85,BD_Spec!$A$1:$K$2336,8,FALSE) -> Base | P85: =+VLOOKUP(C85,OP!$A$1:$P$27848,4,FALSE) -> ABIERTO | Q85: =+VLOOKUP(C85,OP!$A$1:$P$27848,10,FALSE) -> 0 | R85: =+Ordenes_Mes[[#This Row],[Fecha Inicio]] -> 46198
A86: =+MONTH(Ordenes_Mes[[#This Row],[Fecha_Conta]]) -> 5 | B86: =+VLOOKUP(C86,OP!$A$1:$P$27848,12,FALSE) -> 46146 | C86: 4139 | D86: 2310230097 | E86: Frasco Para Témperas 30 cc NP P.S. | F86: 0 | G86: 46141 | H86: =+VLOOKUP(D86,Tiempos!$A$1:$N$7440,3,FALSE) -> 44204.651 | I86: =+VLOOKUP(D86,Tiempos!$A$1:$N$7440,5,FALSE) -> 24 | J86: =+VLOOKUP(D86,Tiempos!$A$1:$N$7440,7,FALSE) -> INY02 | K86: =IF(VLOOKUP(C86,OP!$A$1:$P$27848,4,FALSE)="Cerrado",VLOOKUP(C86,OP!$A$1:$P$27848,10,FALSE),VLOOKUP(C86,OP!$A$1:$P$27848,9,FALSE)) -> 93000 | L86: =IF( IFERROR(VLOOKUP(D86,BD_Spec!$A$1:$D$2300,4,FALSE),"")="Producto Terminado", "TERMINADO", IFERROR(_xlfn.XLOOKUP(Ordenes_Mes[[#This Row],[Maquina]],Tiempos!$G$1:$G$766,Tiempos!$O$1:$O$766),"") ) -> PLÁSTICO_LIMA | M86: =IF(OR(Ordenes_Mes[[#This Row],[Proceso]]="Plástico_lima",Ordenes_Mes[[#This Row],[Proceso]]="soplado"),24,12) -> 24 | N86: =+VLOOKUP(D86,BD_Spec!$A$1:$K$2336,7,FALSE) -> Línea_30cc | O86: =+VLOOKUP(D86,BD_Spec!$A$1:$K$2336,8,FALSE) -> Frasco PLK | P86: =+VLOOKUP(C86,OP!$A$1:$P$27848,4,FALSE) -> CERRADO | Q86: =+VLOOKUP(C86,OP!$A$1:$P$27848,10,FALSE) -> 93000 | R86: =+Ordenes_Mes[[#This Row],[Fecha Inicio]] -> 46141
A87: =+MONTH(Ordenes_Mes[[#This Row],[Fecha_Conta]]) -> 5 | B87: =+VLOOKUP(C87,OP!$A$1:$P$27848,12,FALSE) -> 46156 | C87: 4217 | D87: 2310230097 | E87: Frasco Para Témperas 30 cc NP P.S. | F87: 1 | G87: 46160 | H87: =+VLOOKUP(D87,Tiempos!$A$1:$N$7440,3,FALSE) -> 44204.651 | I87: =+VLOOKUP(D87,Tiempos!$A$1:$N$7440,5,FALSE) -> 24 | J87: =+VLOOKUP(D87,Tiempos!$A$1:$N$7440,7,FALSE) -> INY02 | K87: =IF(VLOOKUP(C87,OP!$A$1:$P$27848,4,FALSE)="Cerrado",VLOOKUP(C87,OP!$A$1:$P$27848,10,FALSE),VLOOKUP(C87,OP!$A$1:$P$27848,9,FALSE)) -> 440000 | L87: =IF( IFERROR(VLOOKUP(D87,BD_Spec!$A$1:$D$2300,4,FALSE),"")="Producto Terminado", "TERMINADO", IFERROR(_xlfn.XLOOKUP(Ordenes_Mes[[#This Row],[Maquina]],Tiempos!$G$1:$G$766,Tiempos!$O$1:$O$766),"") ) -> PLÁSTICO_LIMA | M87: =IF(OR(Ordenes_Mes[[#This Row],[Proceso]]="Plástico_lima",Ordenes_Mes[[#This Row],[Proceso]]="soplado"),24,12) -> 24 | N87: =+VLOOKUP(D87,BD_Spec!$A$1:$K$2336,7,FALSE) -> Línea_30cc | O87: =+VLOOKUP(D87,BD_Spec!$A$1:$K$2336,8,FALSE) -> Frasco PLK | P87: =+VLOOKUP(C87,OP!$A$1:$P$27848,4,FALSE) -> ABIERTO | Q87: =+VLOOKUP(C87,OP!$A$1:$P$27848,10,FALSE) -> 0 | R87: =+Ordenes_Mes[[#This Row],[Fecha Inicio]] -> 46160
A88: =+MONTH(Ordenes_Mes[[#This Row],[Fecha_Conta]]) -> 5 | B88: =+VLOOKUP(C88,OP!$A$1:$P$27848,12,FALSE) -> 46146 | C88: 4055 | D88: 2310230101 | E88: Frasco Para Témperas 20 cc P.S. | F88: 1 | G88: 46146 | H88: =+VLOOKUP(D88,Tiempos!$A$1:$N$7440,3,FALSE) -> 42842.975 | I88: =+VLOOKUP(D88,Tiempos!$A$1:$N$7440,5,FALSE) -> 24 | J88: =+VLOOKUP(D88,Tiempos!$A$1:$N$7440,7,FALSE) -> INY03 | K88: =IF(VLOOKUP(C88,OP!$A$1:$P$27848,4,FALSE)="Cerrado",VLOOKUP(C88,OP!$A$1:$P$27848,10,FALSE),VLOOKUP(C88,OP!$A$1:$P$27848,9,FALSE)) -> 600000 | L88: =IF( IFERROR(VLOOKUP(D88,BD_Spec!$A$1:$D$2300,4,FALSE),"")="Producto Terminado", "TERMINADO", IFERROR(_xlfn.XLOOKUP(Ordenes_Mes[[#This Row],[Maquina]],Tiempos!$G$1:$G$766,Tiempos!$O$1:$O$766),"") ) -> PLÁSTICO_LIMA | M88: =IF(OR(Ordenes_Mes[[#This Row],[Proceso]]="Plástico_lima",Ordenes_Mes[[#This Row],[Proceso]]="soplado"),24,12) -> 24 | N88: =+VLOOKUP(D88,BD_Spec!$A$1:$K$2336,7,FALSE) -> Línea_20cc | O88: =+VLOOKUP(D88,BD_Spec!$A$1:$K$2336,8,FALSE) -> Frasco 20cc | P88: =+VLOOKUP(C88,OP!$A$1:$P$27848,4,FALSE) -> ABIERTO | Q88: =+VLOOKUP(C88,OP!$A$1:$P$27848,10,FALSE) -> 435000 | R88: =+Ordenes_Mes[[#This Row],[Fecha Inicio]] -> 46146
A89: =+MONTH(Ordenes_Mes[[#This Row],[Fecha_Conta]]) -> 6 | B89: =+VLOOKUP(C89,OP!$A$1:$P$27848,12,FALSE) -> 46174 | C89: 4056 | D89: 2310160005 | E89: Tapa Para Limpiatipos x 35gr P.S. | F89: 2 | G89: 46174 | H89: =+VLOOKUP(D89,Tiempos!$A$1:$N$7440,3,FALSE) -> 30104.53 | I89: =+VLOOKUP(D89,Tiempos!$A$1:$N$7440,5,FALSE) -> 24 | J89: =+VLOOKUP(D89,Tiempos!$A$1:$N$7440,7,FALSE) -> INY03 | K89: 400000 | L89: =IF( IFERROR(VLOOKUP(D89,BD_Spec!$A$1:$D$2300,4,FALSE),"")="Producto Terminado", "TERMINADO", IFERROR(_xlfn.XLOOKUP(Ordenes_Mes[[#This Row],[Maquina]],Tiempos!$G$1:$G$766,Tiempos!$O$1:$O$766),"") ) -> PLÁSTICO_LIMA | M89: =IF(OR(Ordenes_Mes[[#This Row],[Proceso]]="Plástico_lima",Ordenes_Mes[[#This Row],[Proceso]]="soplado"),24,12) -> 24 | N89: =+VLOOKUP(D89,BD_Spec!$A$1:$K$2336,7,FALSE) -> Línea_Limpiatipo | O89: =+VLOOKUP(D89,BD_Spec!$A$1:$K$2336,8,FALSE) -> Tapa | P89: =+VLOOKUP(C89,OP!$A$1:$P$27848,4,FALSE) -> ABIERTO | Q89: =+VLOOKUP(C89,OP!$A$1:$P$27848,10,FALSE) -> 0 | R89: =+Ordenes_Mes[[#This Row],[Fecha Inicio]] -> 46174
A90: =+MONTH(Ordenes_Mes[[#This Row],[Fecha_Conta]]) -> 5 | B90: =+VLOOKUP(C90,OP!$A$1:$P$27848,12,FALSE) -> 46146 | C90: 4057 | D90: 2310090524 | E90: Barril Para Marcador 042 (123P) - NP Blanco P.S. | F90: 0 | G90: 46146 | H90: =+VLOOKUP(D90,Tiempos!$A$1:$N$7440,3,FALSE) -> 68844.622 | I90: =+VLOOKUP(D90,Tiempos!$A$1:$N$7440,5,FALSE) -> 24 | J90: =+VLOOKUP(D90,Tiempos!$A$1:$N$7440,7,FALSE) -> INY04 | K90: =IF(VLOOKUP(C90,OP!$A$1:$P$27848,4,FALSE)="Cerrado",VLOOKUP(C90,OP!$A$1:$P$27848,10,FALSE),VLOOKUP(C90,OP!$A$1:$P$27848,9,FALSE)) -> 200000 | L90: =IF( IFERROR(VLOOKUP(D90,BD_Spec!$A$1:$D$2300,4,FALSE),"")="Producto Terminado", "TERMINADO", IFERROR(_xlfn.XLOOKUP(Ordenes_Mes[[#This Row],[Maquina]],Tiempos!$G$1:$G$766,Tiempos!$O$1:$O$766),"") ) -> PLÁSTICO_LIMA | M90: =IF(OR(Ordenes_Mes[[#This Row],[Proceso]]="Plástico_lima",Ordenes_Mes[[#This Row],[Proceso]]="soplado"),24,12) -> 24 | N90: =+VLOOKUP(D90,BD_Spec!$A$1:$K$2336,7,FALSE) -> Línea_042 | O90: =+VLOOKUP(D90,BD_Spec!$A$1:$K$2336,8,FALSE) -> Barril | P90: =+VLOOKUP(C90,OP!$A$1:$P$27848,4,FALSE) -> ABIERTO | Q90: =+VLOOKUP(C90,OP!$A$1:$P$27848,10,FALSE) -> 201600 | R90: =+Ordenes_Mes[[#This Row],[Fecha Inicio]] -> 46146
A91: =+MONTH(Ordenes_Mes[[#This Row],[Fecha_Conta]]) -> 5 | B91: =+VLOOKUP(C91,OP!$A$1:$P$27848,12,FALSE) -> 46146 | C91: 4058 | D91: 2310090469 | E91: Barril Para Marcador 042 - NP Piel P.S. | F91: 13 | G91: 46146 | H91: =+VLOOKUP(D91,Tiempos!$A$1:$N$7440,3,FALSE) -> 68844.622 | I91: =+VLOOKUP(D91,Tiempos!$A$1:$N$7440,5,FALSE) -> 24 | J91: =+VLOOKUP(D91,Tiempos!$A$1:$N$7440,7,FALSE) -> INY04 | K91: =IF(VLOOKUP(C91,OP!$A$1:$P$27848,4,FALSE)="Cerrado",VLOOKUP(C91,OP!$A$1:$P$27848,10,FALSE),VLOOKUP(C91,OP!$A$1:$P$27848,9,FALSE)) -> 70000 | L91: =IF( IFERROR(VLOOKUP(D91,BD_Spec!$A$1:$D$2300,4,FALSE),"")="Producto Terminado", "TERMINADO", IFERROR(_xlfn.XLOOKUP(Ordenes_Mes[[#This Row],[Maquina]],Tiempos!$G$1:$G$766,Tiempos!$O$1:$O$766),"") ) -> PLÁSTICO_LIMA | M91: =IF(OR(Ordenes_Mes[[#This Row],[Proceso]]="Plástico_lima",Ordenes_Mes[[#This Row],[Proceso]]="soplado"),24,12) -> 24 | N91: =+VLOOKUP(D91,BD_Spec!$A$1:$K$2336,7,FALSE) -> Línea_042 | O91: =+VLOOKUP(D91,BD_Spec!$A$1:$K$2336,8,FALSE) -> Barril | P91: =+VLOOKUP(C91,OP!$A$1:$P$27848,4,FALSE) -> ABIERTO | Q91: =+VLOOKUP(C91,OP!$A$1:$P$27848,10,FALSE) -> 0 | R91: =+Ordenes_Mes[[#This Row],[Fecha Inicio]] -> 46146
A92: =+MONTH(Ordenes_Mes[[#This Row],[Fecha_Conta]]) -> 5 | B92: =+VLOOKUP(C92,OP!$A$1:$P$27848,12,FALSE) -> 46146 | C92: 4059 | D92: 2310090461 | E92: Barril Para Marcador 042 - NP Amarillo P.S. | F92: 1 | G92: 46146 | H92: =+VLOOKUP(D92,Tiempos!$A$1:$N$7440,3,FALSE) -> 68844.622 | I92: =+VLOOKUP(D92,Tiempos!$A$1:$N$7440,5,FALSE) -> 24 | J92: =+VLOOKUP(D92,Tiempos!$A$1:$N$7440,7,FALSE) -> INY04 | K92: =IF(VLOOKUP(C92,OP!$A$1:$P$27848,4,FALSE)="Cerrado",VLOOKUP(C92,OP!$A$1:$P$27848,10,FALSE),VLOOKUP(C92,OP!$A$1:$P$27848,9,FALSE)) -> 141400 | L92: =IF( IFERROR(VLOOKUP(D92,BD_Spec!$A$1:$D$2300,4,FALSE),"")="Producto Terminado", "TERMINADO", IFERROR(_xlfn.XLOOKUP(Ordenes_Mes[[#This Row],[Maquina]],Tiempos!$G$1:$G$766,Tiempos!$O$1:$O$766),"") ) -> PLÁSTICO_LIMA | M92: =IF(OR(Ordenes_Mes[[#This Row],[Proceso]]="Plástico_lima",Ordenes_Mes[[#This Row],[Proceso]]="soplado"),24,12) -> 24 | N92: =+VLOOKUP(D92,BD_Spec!$A$1:$K$2336,7,FALSE) -> Línea_042 | O92: =+VLOOKUP(D92,BD_Spec!$A$1:$K$2336,8,FALSE) -> Barril | P92: =+VLOOKUP(C92,OP!$A$1:$P$27848,4,FALSE) -> CERRADO | Q92: =+VLOOKUP(C92,OP!$A$1:$P$27848,10,FALSE) -> 141400 | R92: =+Ordenes_Mes[[#This Row],[Fecha Inicio]] -> 46146
A93: =+MONTH(Ordenes_Mes[[#This Row],[Fecha_Conta]]) -> 5 | B93: =+VLOOKUP(C93,OP!$A$1:$P$27848,12,FALSE) -> 46146 | C93: 4060 | D93: 2310090466 | E93: Barril Para Marcador 042 - NP Anaranjado P.S. | F93: 2 | G93: 46160 | H93: =+VLOOKUP(D93,Tiempos!$A$1:$N$7440,3,FALSE) -> 68844.622 | I93: =+VLOOKUP(D93,Tiempos!$A$1:$N$7440,5,FALSE) -> 24 | J93: =+VLOOKUP(D93,Tiempos!$A$1:$N$7440,7,FALSE) -> INY04 | K93: =IF(VLOOKUP(C93,OP!$A$1:$P$27848,4,FALSE)="Cerrado",VLOOKUP(C93,OP!$A$1:$P$27848,10,FALSE),VLOOKUP(C93,OP!$A$1:$P$27848,9,FALSE)) -> 140700 | L93: =IF( IFERROR(VLOOKUP(D93,BD_Spec!$A$1:$D$2300,4,FALSE),"")="Producto Terminado", "TERMINADO", IFERROR(_xlfn.XLOOKUP(Ordenes_Mes[[#This Row],[Maquina]],Tiempos!$G$1:$G$766,Tiempos!$O$1:$O$766),"") ) -> PLÁSTICO_LIMA | M93: =IF(OR(Ordenes_Mes[[#This Row],[Proceso]]="Plástico_lima",Ordenes_Mes[[#This Row],[Proceso]]="soplado"),24,12) -> 24 | N93: =+VLOOKUP(D93,BD_Spec!$A$1:$K$2336,7,FALSE) -> Línea_042 | O93: =+VLOOKUP(D93,BD_Spec!$A$1:$K$2336,8,FALSE) -> Barril | P93: =+VLOOKUP(C93,OP!$A$1:$P$27848,4,FALSE) -> CERRADO | Q93: =+VLOOKUP(C93,OP!$A$1:$P$27848,10,FALSE) -> 140700 | R93: =+Ordenes_Mes[[#This Row],[Fecha Inicio]] -> 46160
A94: =+MONTH(Ordenes_Mes[[#This Row],[Fecha_Conta]]) -> 5 | B94: =+VLOOKUP(C94,OP!$A$1:$P$27848,12,FALSE) -> 46146 | C94: 4061 | D94: 2310090464 | E94: Barril Para Marcador 042 - NP Rosado P.S. | F94: 3 | G94: 46160 | H94: =+VLOOKUP(D94,Tiempos!$A$1:$N$7440,3,FALSE) -> 68844.622 | I94: =+VLOOKUP(D94,Tiempos!$A$1:$N$7440,5,FALSE) -> 24 | J94: =+VLOOKUP(D94,Tiempos!$A$1:$N$7440,7,FALSE) -> INY04 | K94: =IF(VLOOKUP(C94,OP!$A$1:$P$27848,4,FALSE)="Cerrado",VLOOKUP(C94,OP!$A$1:$P$27848,10,FALSE),VLOOKUP(C94,OP!$A$1:$P$27848,9,FALSE)) -> 100000 | L94: =IF( IFERROR(VLOOKUP(D94,BD_Spec!$A$1:$D$2300,4,FALSE),"")="Producto Terminado", "TERMINADO", IFERROR(_xlfn.XLOOKUP(Ordenes_Mes[[#This Row],[Maquina]],Tiempos!$G$1:$G$766,Tiempos!$O$1:$O$766),"") ) -> PLÁSTICO_LIMA | M94: =IF(OR(Ordenes_Mes[[#This Row],[Proceso]]="Plástico_lima",Ordenes_Mes[[#This Row],[Proceso]]="soplado"),24,12) -> 24 | N94: =+VLOOKUP(D94,BD_Spec!$A$1:$K$2336,7,FALSE) -> Línea_042 | O94: =+VLOOKUP(D94,BD_Spec!$A$1:$K$2336,8,FALSE) -> Barril | P94: =+VLOOKUP(C94,OP!$A$1:$P$27848,4,FALSE) -> ABIERTO | Q94: =+VLOOKUP(C94,OP!$A$1:$P$27848,10,FALSE) -> 27300 | R94: =+Ordenes_Mes[[#This Row],[Fecha Inicio]] -> 46160
A95: =+MONTH(Ordenes_Mes[[#This Row],[Fecha_Conta]]) -> 5 | B95: =+VLOOKUP(C95,OP!$A$1:$P$27848,12,FALSE) -> 46146 | C95: 4062 | D95: 2310090459 | E95: Barril Para Marcador 042 - NP Rojo P.S. | F95: 4 | G95: 46160 | H95: =+VLOOKUP(D95,Tiempos!$A$1:$N$7440,3,FALSE) -> 68844.622 | I95: =+VLOOKUP(D95,Tiempos!$A$1:$N$7440,5,FALSE) -> 24 | J95: =+VLOOKUP(D95,Tiempos!$A$1:$N$7440,7,FALSE) -> INY04 | K95: =IF(VLOOKUP(C95,OP!$A$1:$P$27848,4,FALSE)="Cerrado",VLOOKUP(C95,OP!$A$1:$P$27848,10,FALSE),VLOOKUP(C95,OP!$A$1:$P$27848,9,FALSE)) -> 140000 | L95: =IF( IFERROR(VLOOKUP(D95,BD_Spec!$A$1:$D$2300,4,FALSE),"")="Producto Terminado", "TERMINADO", IFERROR(_xlfn.XLOOKUP(Ordenes_Mes[[#This Row],[Maquina]],Tiempos!$G$1:$G$766,Tiempos!$O$1:$O$766),"") ) -> PLÁSTICO_LIMA | M95: =IF(OR(Ordenes_Mes[[#This Row],[Proceso]]="Plástico_lima",Ordenes_Mes[[#This Row],[Proceso]]="soplado"),24,12) -> 24 | N95: =+VLOOKUP(D95,BD_Spec!$A$1:$K$2336,7,FALSE) -> Línea_042 | O95: =+VLOOKUP(D95,BD_Spec!$A$1:$K$2336,8,FALSE) -> Barril | P95: =+VLOOKUP(C95,OP!$A$1:$P$27848,4,FALSE) -> ABIERTO | Q95: =+VLOOKUP(C95,OP!$A$1:$P$27848,10,FALSE) -> 0 | R95: =+Ordenes_Mes[[#This Row],[Fecha Inicio]] -> 46160
A96: =+MONTH(Ordenes_Mes[[#This Row],[Fecha_Conta]]) -> 5 | B96: =+VLOOKUP(C96,OP!$A$1:$P$27848,12,FALSE) -> 46146 | C96: 4063 | D96: 2310090465 | E96: Barril Para Marcador 042 - NP Morado P.S. | F96: 5 | G96: 46160 | H96: =+VLOOKUP(D96,Tiempos!$A$1:$N$7440,3,FALSE) -> 68844.622 | I96: =+VLOOKUP(D96,Tiempos!$A$1:$N$7440,5,FALSE) -> 24 | J96: =+VLOOKUP(D96,Tiempos!$A$1:$N$7440,7,FALSE) -> INY04 | K96: =IF(VLOOKUP(C96,OP!$A$1:$P$27848,4,FALSE)="Cerrado",VLOOKUP(C96,OP!$A$1:$P$27848,10,FALSE),VLOOKUP(C96,OP!$A$1:$P$27848,9,FALSE)) -> 100000 | L96: =IF( IFERROR(VLOOKUP(D96,BD_Spec!$A$1:$D$2300,4,FALSE),"")="Producto Terminado", "TERMINADO", IFERROR(_xlfn.XLOOKUP(Ordenes_Mes[[#This Row],[Maquina]],Tiempos!$G$1:$G$766,Tiempos!$O$1:$O$766),"") ) -> PLÁSTICO_LIMA | M96: =IF(OR(Ordenes_Mes[[#This Row],[Proceso]]="Plástico_lima",Ordenes_Mes[[#This Row],[Proceso]]="soplado"),24,12) -> 24 | N96: =+VLOOKUP(D96,BD_Spec!$A$1:$K$2336,7,FALSE) -> Línea_042 | O96: =+VLOOKUP(D96,BD_Spec!$A$1:$K$2336,8,FALSE) -> Barril | P96: =+VLOOKUP(C96,OP!$A$1:$P$27848,4,FALSE) -> ABIERTO | Q96: =+VLOOKUP(C96,OP!$A$1:$P$27848,10,FALSE) -> 0 | R96: =+Ordenes_Mes[[#This Row],[Fecha Inicio]] -> 46160
A97: =+MONTH(Ordenes_Mes[[#This Row],[Fecha_Conta]]) -> 5 | B97: =+VLOOKUP(C97,OP!$A$1:$P$27848,12,FALSE) -> 46146 | C97: 4138 | D97: 2310090448 | E97: Barril Para Plumón 045 - NP Celeste | F97: 6 | G97: 46141 | H97: =+VLOOKUP(D97,Tiempos!$A$1:$N$7440,3,FALSE) -> 98742.857 | I97: =+VLOOKUP(D97,Tiempos!$A$1:$N$7440,5,FALSE) -> 24 | J97: =+VLOOKUP(D97,Tiempos!$A$1:$N$7440,7,FALSE) -> INY05 | K97: =IF(VLOOKUP(C97,OP!$A$1:$P$27848,4,FALSE)="Cerrado",VLOOKUP(C97,OP!$A$1:$P$27848,10,FALSE),VLOOKUP(C97,OP!$A$1:$P$27848,9,FALSE)) -> 156120 | L97: =IF( IFERROR(VLOOKUP(D97,BD_Spec!$A$1:$D$2300,4,FALSE),"")="Producto Terminado", "TERMINADO", IFERROR(_xlfn.XLOOKUP(Ordenes_Mes[[#This Row],[Maquina]],Tiempos!$G$1:$G$766,Tiempos!$O$1:$O$766),"") ) -> PLÁSTICO_LIMA | M97: =IF(OR(Ordenes_Mes[[#This Row],[Proceso]]="Plástico_lima",Ordenes_Mes[[#This Row],[Proceso]]="soplado"),24,12) -> 24 | N97: =+VLOOKUP(D97,BD_Spec!$A$1:$K$2336,7,FALSE) -> Línea_045 | O97: =+VLOOKUP(D97,BD_Spec!$A$1:$K$2336,8,FALSE) -> Barril | P97: =+VLOOKUP(C97,OP!$A$1:$P$27848,4,FALSE) -> CERRADO | Q97: =+VLOOKUP(C97,OP!$A$1:$P$27848,10,FALSE) -> 156120 | R97: =+Ordenes_Mes[[#This Row],[Fecha Inicio]] -> 46141
A98: =+MONTH(Ordenes_Mes[[#This Row],[Fecha_Conta]]) -> 5 | B98: =+VLOOKUP(C98,OP!$A$1:$P$27848,12,FALSE) -> 46146 | C98: 3860 | D98: 2310090439 | E98: Barril Para Plumón 045 - NP Azul | F98: 7 | G98: 46141 | H98: =+VLOOKUP(D98,Tiempos!$A$1:$N$7440,3,FALSE) -> 98742.857 | I98: =+VLOOKUP(D98,Tiempos!$A$1:$N$7440,5,FALSE) -> 24 | J98: =+VLOOKUP(D98,Tiempos!$A$1:$N$7440,7,FALSE) -> INY05 | K98: =IF(VLOOKUP(C98,OP!$A$1:$P$27848,4,FALSE)="Cerrado",VLOOKUP(C98,OP!$A$1:$P$27848,10,FALSE),VLOOKUP(C98,OP!$A$1:$P$27848,9,FALSE)) -> 226740 | L98: =IF( IFERROR(VLOOKUP(D98,BD_Spec!$A$1:$D$2300,4,FALSE),"")="Producto Terminado", "TERMINADO", IFERROR(_xlfn.XLOOKUP(Ordenes_Mes[[#This Row],[Maquina]],Tiempos!$G$1:$G$766,Tiempos!$O$1:$O$766),"") ) -> PLÁSTICO_LIMA | M98: =IF(OR(Ordenes_Mes[[#This Row],[Proceso]]="Plástico_lima",Ordenes_Mes[[#This Row],[Proceso]]="soplado"),24,12) -> 24 | N98: =+VLOOKUP(D98,BD_Spec!$A$1:$K$2336,7,FALSE) -> Línea_045 | O98: =+VLOOKUP(D98,BD_Spec!$A$1:$K$2336,8,FALSE) -> Barril | P98: =+VLOOKUP(C98,OP!$A$1:$P$27848,4,FALSE) -> CERRADO | Q98: =+VLOOKUP(C98,OP!$A$1:$P$27848,10,FALSE) -> 226740 | R98: =+Ordenes_Mes[[#This Row],[Fecha Inicio]] -> 46141
A99: =+MONTH(Ordenes_Mes[[#This Row],[Fecha_Conta]]) -> 5 | B99: =+VLOOKUP(C99,OP!$A$1:$P$27848,12,FALSE) -> 46146 | C99: 3866 | D99: 2310090445 | E99: Barril Para Plumón 045 - NP Verde Claro | F99: 8 | G99: 46146 | H99: =+VLOOKUP(D99,Tiempos!$A$1:$N$7440,3,FALSE) -> 98742.857 | I99: =+VLOOKUP(D99,Tiempos!$A$1:$N$7440,5,FALSE) -> 24 | J99: =+VLOOKUP(D99,Tiempos!$A$1:$N$7440,7,FALSE) -> INY05 | K99: =IF(VLOOKUP(C99,OP!$A$1:$P$27848,4,FALSE)="Cerrado",VLOOKUP(C99,OP!$A$1:$P$27848,10,FALSE),VLOOKUP(C99,OP!$A$1:$P$27848,9,FALSE)) -> 242700 | L99: =IF( IFERROR(VLOOKUP(D99,BD_Spec!$A$1:$D$2300,4,FALSE),"")="Producto Terminado", "TERMINADO", IFERROR(_xlfn.XLOOKUP(Ordenes_Mes[[#This Row],[Maquina]],Tiempos!$G$1:$G$766,Tiempos!$O$1:$O$766),"") ) -> PLÁSTICO_LIMA | M99: =IF(OR(Ordenes_Mes[[#This Row],[Proceso]]="Plástico_lima",Ordenes_Mes[[#This Row],[Proceso]]="soplado"),24,12) -> 24 | N99: =+VLOOKUP(D99,BD_Spec!$A$1:$K$2336,7,FALSE) -> Línea_045 | O99: =+VLOOKUP(D99,BD_Spec!$A$1:$K$2336,8,FALSE) -> Barril | P99: =+VLOOKUP(C99,OP!$A$1:$P$27848,4,FALSE) -> CERRADO | Q99: =+VLOOKUP(C99,OP!$A$1:$P$27848,10,FALSE) -> 242700 | R99: =+Ordenes_Mes[[#This Row],[Fecha Inicio]] -> 46146
A100: =+MONTH(Ordenes_Mes[[#This Row],[Fecha_Conta]]) -> 5 | B100: =+VLOOKUP(C100,OP!$A$1:$P$27848,12,FALSE) -> 46146 | C100: 3863 | D100: 2310090442 | E100: Barril Para Plumón 045 - NP Verde | F100: 9 | G100: 46146 | H100: =+VLOOKUP(D100,Tiempos!$A$1:$N$7440,3,FALSE) -> 98742.857 | I100: =+VLOOKUP(D100,Tiempos!$A$1:$N$7440,5,FALSE) -> 24 | J100: =+VLOOKUP(D100,Tiempos!$A$1:$N$7440,7,FALSE) -> INY05 | K100: =IF(VLOOKUP(C100,OP!$A$1:$P$27848,4,FALSE)="Cerrado",VLOOKUP(C100,OP!$A$1:$P$27848,10,FALSE),VLOOKUP(C100,OP!$A$1:$P$27848,9,FALSE)) -> 243100 | L100: =IF( IFERROR(VLOOKUP(D100,BD_Spec!$A$1:$D$2300,4,FALSE),"")="Producto Terminado", "TERMINADO", IFERROR(_xlfn.XLOOKUP(Ordenes_Mes[[#This Row],[Maquina]],Tiempos!$G$1:$G$766,Tiempos!$O$1:$O$766),"") ) -> PLÁSTICO_LIMA | M100: =IF(OR(Ordenes_Mes[[#This Row],[Proceso]]="Plástico_lima",Ordenes_Mes[[#This Row],[Proceso]]="soplado"),24,12) -> 24 | N100: =+VLOOKUP(D100,BD_Spec!$A$1:$K$2336,7,FALSE) -> Línea_045 | O100: =+VLOOKUP(D100,BD_Spec!$A$1:$K$2336,8,FALSE) -> Barril | P100: =+VLOOKUP(C100,OP!$A$1:$P$27848,4,FALSE) -> CERRADO | Q100: =+VLOOKUP(C100,OP!$A$1:$P$27848,10,FALSE) -> 243100 | R100: =+Ordenes_Mes[[#This Row],[Fecha Inicio]] -> 46146
A101: =+MONTH(Ordenes_Mes[[#This Row],[Fecha_Conta]]) -> 5 | B101: =+VLOOKUP(C101,OP!$A$1:$P$27848,12,FALSE) -> 46146 | C101: 3871 | D101: 2310090507 | E101: Barril Para Plumón 045 - NP Violeta | F101: 10 | G101: 46156 | H101: =+VLOOKUP(D101,Tiempos!$A$1:$N$7440,3,FALSE) -> 98742.857 | I101: =+VLOOKUP(D101,Tiempos!$A$1:$N$7440,5,FALSE) -> 24 | J101: =+VLOOKUP(D101,Tiempos!$A$1:$N$7440,7,FALSE) -> INY05 | K101: =IF(VLOOKUP(C101,OP!$A$1:$P$27848,4,FALSE)="Cerrado",VLOOKUP(C101,OP!$A$1:$P$27848,10,FALSE),VLOOKUP(C101,OP!$A$1:$P$27848,9,FALSE)) -> 342450 | L101: =IF( IFERROR(VLOOKUP(D101,BD_Spec!$A$1:$D$2300,4,FALSE),"")="Producto Terminado", "TERMINADO", IFERROR(_xlfn.XLOOKUP(Ordenes_Mes[[#This Row],[Maquina]],Tiempos!$G$1:$G$766,Tiempos!$O$1:$O$766),"") ) -> PLÁSTICO_LIMA | M101: =IF(OR(Ordenes_Mes[[#This Row],[Proceso]]="Plástico_lima",Ordenes_Mes[[#This Row],[Proceso]]="soplado"),24,12) -> 24 | N101: =+VLOOKUP(D101,BD_Spec!$A$1:$K$2336,7,FALSE) -> Línea_045 | O101: =+VLOOKUP(D101,BD_Spec!$A$1:$K$2336,8,FALSE) -> Barril | P101: =+VLOOKUP(C101,OP!$A$1:$P$27848,4,FALSE) -> CERRADO | Q101: =+VLOOKUP(C101,OP!$A$1:$P$27848,10,FALSE) -> 342450 | R101: =+Ordenes_Mes[[#This Row],[Fecha Inicio]] -> 46156
...

Sheet BD_Spec
A1: Código_Material | B1: Descripción_Material | C1: Línea_PT | D1: Tipo_Material | E1: Familia_PT | F1: Proceso_Interno | G1: Líneas | H1: Subcomponente | I1: Sublìnea | J1: CONTAR.SI | K1: CV | L1: Secuencia | M1: Color | N1: Peso | P1: A | Q1: A | R1: A | S1: A
A2: 2310320328 | B2: Carga Para Bolígrafo 036 PFTR Azul N | C2: Ensamble - Máquina | D2: Semiterminado | E2: N/A | F2: Carga | G2: Línea_036 | H2: Colores | I2: Carga | J2: 1 | K2: 1 | L2: 1 | M2: N/A | P2: 2310090469 | Q2: Barril Para Marcador 042 - NP Piel P.S. | R2: Piel | S2: =+VLOOKUP(R2,$V$2:$W$13,2,FALSE) -> 1 | V2: Piel | W2: 1
A3: 2310320330 | B3: Carga Para Bolígrafo 036 PFTR Negro N | C3: Ensamble - Máquina | D3: Semiterminado | E3: N/A | F3: Carga | G3: Línea_036 | H3: Colores | I3: Carga | J3: 1 | K3: 1 | L3: 1 | M3: N/A | P3: 2310090461 | Q3: Barril Para Marcador 042 - NP Amarillo P.S. | R3: Amarillo | S3: =+VLOOKUP(R3,$V$2:$W$13,2,FALSE) -> 2 | V3: Amarillo | W3: 2
A4: 2310320329 | B4: Carga Para Bolígrafo 036 PFTR Rojo N | C4: Ensamble - Máquina | D4: Semiterminado | E4: N/A | F4: Carga | G4: Línea_036 | H4: Colores | I4: Carga | J4: 1 | K4: 1 | L4: 1 | M4: N/A | P4: 2310090466 | Q4: Barril Para Marcador 042 - NP Anaranjado P.S. | R4: Anaranjado | S4: =+VLOOKUP(R4,$V$2:$W$13,2,FALSE) -> 3 | V4: Anaranjado | W4: 3
A5: 2310320348 | B5: Carga Para Bolígrafo 036 PFTR Verde N | C5: Ensamble - Máquina | D5: Semiterminado | E5: N/A | F5: Carga | G5: Línea_036 | H5: Colores | I5: Carga | J5: 1 | K5: 1 | L5: 1 | M5: N/A | P5: 2310090464 | Q5: Barril Para Marcador 042 - NP Rosado P.S. | R5: Rosado | S5: =+VLOOKUP(R5,$V$2:$W$13,2,FALSE) -> 4 | V5: Rosado | W5: 4
A6: 2110030056 | B6: Témpera Layconsa Puppy x 250 cc Blanca c/Dispensador | C6: Ensamble - Máquina | D6: Producto Terminado | E6: Témpera 250 | F6: Dosificado | G6: Línea_250cc | H6: =+BD_Spec[[#This Row],[Familia_PT]] -> Témpera 250 | I6: N/A | J6: 1 | K6: 1 | L6: 1 | M6: N/A | P6: 2310090459 | Q6: Barril Para Marcador 042 - NP Rojo P.S. | R6: Rojo | S6: =+VLOOKUP(R6,$V$2:$W$13,2,FALSE) -> 5 | V6: Rojo | W6: 5
A7: 2110030057 | B7: Témpera Layconsa Puppy x 250 cc Azul c/Dispensador | C7: Ensamble - Máquina | D7: Producto Terminado | E7: Témpera 250 | F7: Dosificado | G7: Línea_250cc | H7: =+BD_Spec[[#This Row],[Familia_PT]] -> Témpera 250 | I7: N/A | J7: 1 | K7: 1 | L7: 1 | M7: N/A | P7: 2310090465 | Q7: Barril Para Marcador 042 - NP Morado P.S. | R7: Morado | S7: =+VLOOKUP(R7,$V$2:$W$13,2,FALSE) -> 10 | V7: Morado | W7: 10
A8: 2110030058 | B8: Témpera Layconsa Puppy x 250 cc Roja c/Dispensador | C8: Ensamble - Máquina | D8: Producto Terminado | E8: Témpera 250 | F8: Dosificado | G8: Línea_250cc | H8: =+BD_Spec[[#This Row],[Familia_PT]] -> Témpera 250 | I8: N/A | J8: 1 | K8: 1 | L8: 1 | M8: N/A | P8: 2310090463 | Q8: Barril Para Marcador 042 - NP Celeste P.S. | R8: Celeste | S8: =+VLOOKUP(R8,$V$2:$W$13,2,FALSE) -> 6 | V8: Celeste | W8: 6
A9: 2110030117 | B9: Témpera Layconsa Puppy x 250 cc Morado c/Dispensador | C9: Ensamble - Máquina | D9: Producto Terminado | E9: Témpera 250 | F9: Dosificado | G9: Línea_250cc | H9: =+BD_Spec[[#This Row],[Familia_PT]] -> Témpera 250 | I9: N/A | J9: 1 | K9: 1 | L9: 1 | M9: N/A | P9: 2310090457 | Q9: Barril Para Marcador 042 - NP Azul P.S. | R9: Azul | S9: =+VLOOKUP(R9,$V$2:$W$13,2,FALSE) -> 7 | V9: Azul | W9: 7
A10: 2110030055 | B10: Témpera Layconsa Puppy x 250 cc Verde c/Dispensador | C10: Ensamble - Máquina | D10: Producto Terminado | E10: Témpera 250 | F10: Dosificado | G10: Línea_250cc | H10: =+BD_Spec[[#This Row],[Familia_PT]] -> Témpera 250 | I10: N/A | J10: 1 | K10: 1 | L10: 1 | M10: N/A | P10: 2310090468 | Q10: Barril Para Marcador 042 - NP Verde Claro P.S. | R10: Verde Claro | S10: =+VLOOKUP(R10,$V$2:$W$13,2,FALSE) -> 8 | V10: Verde Claro | W10: 8
A11: 2110030059 | B11: Témpera Layconsa Puppy x 250 cc Amarilla c/Dispensador | C11: Ensamble - Máquina | D11: Producto Terminado | E11: Témpera 250 | F11: Dosificado | G11: Línea_250cc | H11: =+BD_Spec[[#This Row],[Familia_PT]] -> Témpera 250 | I11: N/A | J11: 1 | K11: 1 | L11: 1 | M11: N/A | P11: 2310090460 | Q11: Barril Para Marcador 042 - NP Verde P.S. | R11: Verde | S11: =+VLOOKUP(R11,$V$2:$W$13,2,FALSE) -> 9 | V11: Verde | W11: 9
A12: 2110030060 | B12: Témpera Layconsa Puppy x 250 cc Piel c/Dispensador | C12: Ensamble - Máquina | D12: Producto Terminado | E12: Témpera 250 | F12: Dosificado | G12: Línea_250cc | H12: =+BD_Spec[[#This Row],[Familia_PT]] -> Témpera 250 | I12: N/A | J12: 1 | K12: 1 | L12: 1 | M12: N/A | P12: 2310090462 | Q12: Barril Para Marcador 042 - NP Marrón P.S. | R12: Marrón | S12: =+VLOOKUP(R12,$V$2:$W$13,2,FALSE) -> 11 | V12: Marrón | W12: 11
A13: 2110030078 | B13: Témpera Layconsa Puppy x 250 cc Marrón c/Dispensador | C13: Ensamble - Máquina | D13: Producto Terminado | E13: Témpera 250 | F13: Dosificado | G13: Línea_250cc | H13: =+BD_Spec[[#This Row],[Familia_PT]] -> Témpera 250 | I13: N/A | J13: 1 | K13: 1 | L13: 1 | M13: N/A | P13: 2310090458 | Q13: Barril Para Marcador 042 - NP Negro P.S. | R13: Negro | S13: =+VLOOKUP(R13,$V$2:$W$13,2,FALSE) -> 12 | V13: Negro | W13: 12
A14: 2110030081 | B14: Témpera Layconsa Puppy x 250 cc Celeste c/Dispensador | C14: Ensamble - Máquina | D14: Producto Terminado | E14: Témpera 250 | F14: Dosificado | G14: Línea_250cc | H14: =+BD_Spec[[#This Row],[Familia_PT]] -> Témpera 250 | I14: N/A | J14: 1 | K14: 1 | L14: 1 | M14: N/A | P14: 2310160355 | Q14: Tapa Para Marcador 042 - N Piel P.S. | R14: Piel | S14: =+VLOOKUP(R14,$V$2:$W$13,2,FALSE) -> 1
A15: 2110030082 | B15: Témpera Layconsa Puppy x 250 cc Anaranjado c/Dispensador | C15: Ensamble - Máquina | D15: Producto Terminado | E15: Témpera 250 | F15: Dosificado | G15: Línea_250cc | H15: =+BD_Spec[[#This Row],[Familia_PT]] -> Témpera 250 | I15: N/A | J15: 1 | K15: 1 | L15: 1 | M15: N/A | P15: 2310160242 | Q15: Tapa Para Marcador 042 - N Amarillo P.S. | R15: Amarillo | S15: =+VLOOKUP(R15,$V$2:$W$13,2,FALSE) -> 2 | V15: Blanco | W15: 9
A16: 2110030119 | B16: Témpera Layconsa Puppy x 250 cc Verde Limón c/Dispensador | C16: Ensamble - Máquina | D16: Producto Terminado | E16: Témpera 250 | F16: Dosificado | G16: Línea_250cc | H16: =+BD_Spec[[#This Row],[Familia_PT]] -> Témpera 250 | I16: N/A | J16: 1 | K16: 1 | L16: 1 | M16: N/A | P16: 2310160247 | Q16: Tapa Para Marcador 042 - N Anaranjado P.S. | R16: Anaranjado | S16: =+VLOOKUP(R16,$V$2:$W$13,2,FALSE) -> 3 | V16: Amarillo | W16: 1
A17: 2110030079 | B17: Témpera Layconsa Puppy x 250 cc Negro c/Dispensador | C17: Ensamble - Máquina | D17: Producto Terminado | E17: Témpera 250 | F17: Dosificado | G17: Línea_250cc | H17: =+BD_Spec[[#This Row],[Familia_PT]] -> Témpera 250 | I17: N/A | J17: 1 | K17: 1 | L17: 1 | M17: N/A | P17: 2310160245 | Q17: Tapa Para Marcador 042 - N Rosado P.S. | R17: Rosado | S17: =+VLOOKUP(R17,$V$2:$W$13,2,FALSE) -> 4 | V17: Anaranjado | W17: 2
A18: 2110030080 | B18: Témpera Layconsa Puppy x 250 cc Rosado c/Dispensador | C18: Ensamble - Máquina | D18: Producto Terminado | E18: Témpera 250 | F18: Dosificado | G18: Línea_250cc | H18: =+BD_Spec[[#This Row],[Familia_PT]] -> Témpera 250 | I18: N/A | J18: 1 | K18: 1 | L18: 1 | M18: N/A | P18: 2310160240 | Q18: Tapa Para Marcador 042 - N Rojo P.S. | R18: Rojo | S18: =+VLOOKUP(R18,$V$2:$W$13,2,FALSE) -> 5 | V18: Rosado | W18: 3
A19: 2110030120 | B19: Témpera Layconsa Puppy x 250 cc Neón Amarillo c/Dispensador | C19: Ensamble - Máquina | D19: Producto Terminado | E19: Témpera 250 | F19: Dosificado | G19: Línea_250cc | H19: =+BD_Spec[[#This Row],[Familia_PT]] -> Témpera 250 | I19: N/A | J19: 1 | K19: 1 | L19: 1 | M19: N/A | P19: 2310160246 | Q19: Tapa Para Marcador 042 - N Morado P.S. | R19: Morado | S19: =+VLOOKUP(R19,$V$2:$W$13,2,FALSE) -> 10 | V19: Rojo | W19: 4
A20: 2110030121 | B20: Témpera Layconsa Puppy x 250 cc Neón Violeta c/Dispensador | C20: Ensamble - Máquina | D20: Producto Terminado | E20: Témpera 250 | F20: Dosificado | G20: Línea_250cc | H20: =+BD_Spec[[#This Row],[Familia_PT]] -> Témpera 250 | I20: N/A | J20: 1 | K20: 1 | L20: 1 | M20: N/A | P20: 2310160244 | Q20: Tapa Para Marcador 042 - N Celeste P.S. | R20: Celeste | S20: =+VLOOKUP(R20,$V$2:$W$13,2,FALSE) -> 6 | V20: Morado | W20: 10
A21: 2110030123 | B21: Témpera Layconsa Puppy x 250 cc Neón Rosado c/Dispensador | C21: Ensamble - Máquina | D21: Producto Terminado | E21: Témpera 250 | F21: Dosificado | G21: Línea_250cc | H21: =+BD_Spec[[#This Row],[Familia_PT]] -> Témpera 250 | I21: N/A | J21: 1 | K21: 1 | L21: 1 | M21: N/A | P21: 2310160238 | Q21: Tapa Para Marcador 042 - N Azul P.S. | R21: Azul | S21: =+VLOOKUP(R21,$V$2:$W$13,2,FALSE) -> 7 | V21: Celeste | W21: 8
A22: 2110030124 | B22: Témpera Layconsa Puppy x 250 cc Neón Verde c/Dispensador | C22: Ensamble - Máquina | D22: Producto Terminado | E22: Témpera 250 | F22: Dosificado | G22: Línea_250cc | H22: =+BD_Spec[[#This Row],[Familia_PT]] -> Témpera 250 | I22: N/A | J22: 1 | K22: 1 | L22: 1 | M22: N/A | P22: 2310160356 | Q22: Tapa Para Marcador 042 - N Verde Claro P.S. | R22: Verde Claro | S22: =+VLOOKUP(R22,$V$2:$W$13,2,FALSE) -> 8 | V22: Azul | W22: 7
A23: 2110030118 | B23: Témpera Layconsa Puppy x 250 cc Fucsia c/Dispensador | C23: Ensamble - Máquina | D23: Producto Terminado | E23: Témpera 250 | F23: Dosificado | G23: Línea_250cc | H23: =+BD_Spec[[#This Row],[Familia_PT]] -> Témpera 250 | I23: N/A | J23: 1 | K23: 1 | L23: 1 | M23: N/A | P23: 2310160241 | Q23: Tapa Para Marcador 042 - N Verde P.S. | R23: Verde | S23: =+VLOOKUP(R23,$V$2:$W$13,2,FALSE) -> 9 | V23: Verde Claro | W23: 5
A24: 2110030122 | B24: Témpera Layconsa Puppy x 250 cc Neón Naranja c/Dispensador | C24: Ensamble - Máquina | D24: Producto Terminado | E24: Témpera 250 | F24: Dosificado | G24: Línea_250cc | H24: =+BD_Spec[[#This Row],[Familia_PT]] -> Témpera 250 | I24: N/A | J24: 1 | K24: 1 | L24: 1 | M24: N/A | P24: 2310160243 | Q24: Tapa Para Marcador 042 - N Marrón P.S. | R24: Marrón | S24: =+VLOOKUP(R24,$V$2:$W$13,2,FALSE) -> 11 | V24: Verde | W24: 6
A25: 2110030190 | B25: Témpera Layconsa Puppy x 250 cc Turquesa c/Dispensador | C25: Ensamble - Máquina | D25: Producto Terminado | E25: Témpera 250 | F25: Dosificado | G25: Línea_250cc | H25: =+BD_Spec[[#This Row],[Familia_PT]] -> Témpera 250 | I25: N/A | J25: 1 | K25: 1 | L25: 1 | M25: N/A | P25: 2310160239 | Q25: Tapa Para Marcador 042 - N Negro P.S. | R25: Negro | S25: =+VLOOKUP(R25,$V$2:$W$13,2,FALSE) -> 12 | V25: Marrón | W25: 11
A26: 2110030191 | B26: Témpera Layconsa Puppy x 250 cc Neón Rojo c/Dispensador | C26: Ensamble - Máquina | D26: Producto Terminado | E26: Témpera 250 | F26: Dosificado | G26: Línea_250cc | H26: =+BD_Spec[[#This Row],[Familia_PT]] -> Témpera 250 | I26: N/A | J26: 1 | K26: 1 | L26: 1 | M26: N/A | P26: 2310160353 | Q26: Tapita Para Marcador 042 - N Piel | R26: Piel | S26: =+VLOOKUP(R26,$V$2:$W$13,2,FALSE) -> 1 | V26: Negro | W26: 12
A27: 2110030195 | B27: Témpera Rojo Arti x 250 ML | C27: Ensamble - Máquina | D27: Producto Terminado | E27: Cola | F27: Dosificado | G27: Línea_cola | H27: N/A | I27: N/A | J27: 1 | K27: 1 | L27: 1 | M27: N/A | P27: 2310160252 | Q27: Tapita Para Marcador 042 - N Amarillo | R27: Amarillo | S27: =+VLOOKUP(R27,$V$2:$W$13,2,FALSE) -> 2
A28: 2110030236 | B28: Témpera Violeta Arti x 250 ML | C28: Ensamble - Máquina | D28: Producto Terminado | E28: Cola | F28: Dosificado | G28: Línea_cola | H28: N/A | I28: N/A | J28: 1 | K28: 1 | L28: 1 | M28: N/A | P28: 2310160257 | Q28: Tapita Para Marcador 042 - N Anaranjado | R28: Anaranjado | S28: =+VLOOKUP(R28,$V$2:$W$13,2,FALSE) -> 3
A29: 2110030237 | B29: Témpera Marrón Arti x 250 ML | C29: Ensamble - Máquina | D29: Producto Terminado | E29: Cola | F29: Dosificado | G29: Línea_cola | H29: N/A | I29: N/A | J29: 1 | K29: 1 | L29: 1 | M29: N/A | P29: 2310160255 | Q29: Tapita Para Marcador 042 - N Rosado | R29: Rosado | S29: =+VLOOKUP(R29,$V$2:$W$13,2,FALSE) -> 4
A30: 2110030239 | B30: Témpera Azul Celeste Arti x 250 ML | C30: Ensamble - Máquina | D30: Producto Terminado | E30: Cola | F30: Dosificado | G30: Línea_cola | H30: N/A | I30: N/A | J30: 1 | K30: 1 | L30: 1 | M30: N/A | P30: 2310160250 | Q30: Tapita Para Marcador 042 - N Rojo | R30: Rojo | S30: =+VLOOKUP(R30,$V$2:$W$13,2,FALSE) -> 5
A31: 2110030200 | B31: Témpera Blanca Arti x 250 ML | C31: Ensamble - Máquina | D31: Producto Terminado | E31: Cola | F31: Dosificado | G31: Línea_cola | H31: N/A | I31: N/A | J31: 1 | K31: 1 | L31: 1 | M31: N/A | P31: 2310160256 | Q31: Tapita Para Marcador 042 - N Morado | R31: Morado | S31: =+VLOOKUP(R31,$V$2:$W$13,2,FALSE) -> 10
A32: 2110030238 | B32: Témpera Color Carne Arti x 250 ML | C32: Ensamble - Máquina | D32: Producto Terminado | E32: Cola | F32: Dosificado | G32: Línea_cola | H32: N/A | I32: N/A | J32: 1 | K32: 1 | L32: 1 | M32: N/A | P32: 2310160254 | Q32: Tapita Para Marcador 042 - N Celeste | R32: Celeste | S32: =+VLOOKUP(R32,$V$2:$W$13,2,FALSE) -> 6
A33: 2110110001 | B33: Cola Escolar Layconsa x 125 gr. | C33: Ensamble - Máquina | D33: Producto Terminado | E33: Cola | F33: Dosificado | G33: Línea_Cola | H33: Cola | J33: 1 | K33: 1 | L33: 1 | M33: N/A | P33: 2310160248 | Q33: Tapita Para Marcador 042 - N Azul | R33: Azul | S33: =+VLOOKUP(R33,$V$2:$W$13,2,FALSE) -> 7
A34: 2110110002 | B34: Cola Escolar Layconsa de 250Gr con Dispensador | C34: Ensamble - Máquina | D34: Producto Terminado | E34: Cola | F34: Dosificado | G34: Línea_Cola | H34: Cola | J34: 1 | K34: 1 | L34: 1 | M34: N/A | P34: 2310160354 | Q34: Tapita Para Marcador 042 - N Verde Claro | R34: Verde Claro | S34: =+VLOOKUP(R34,$V$2:$W$13,2,FALSE) -> 8
A35: 2110110025 | B35: Cola sintética Layconsa x 60 g. c/ dispensador | C35: Ensamble - Máquina | D35: Producto Terminado | E35: Cola | F35: Dosificado | G35: Línea_Cola | H35: Cola | J35: 1 | K35: 1 | L35: 1 | M35: N/A | P35: 2310160251 | Q35: Tapita Para Marcador 042 - N Verde | R35: Verde | S35: =+VLOOKUP(R35,$V$2:$W$13,2,FALSE) -> 9
A36: 2110110004 | B36: Cola Sintética Layconsa x 250Gr | C36: Ensamble - Máquina | D36: Producto Terminado | E36: Cola | F36: Dosificado | G36: Línea_Cola | H36: Cola | J36: 1 | K36: 1 | L36: 1 | M36: N/A | P36: 2310160253 | Q36: Tapita Para Marcador 042 - N Marrón | R36: Marrón | S36: =+VLOOKUP(R36,$V$2:$W$13,2,FALSE) -> 11
A37: 2110110033 | B37: Goma Líquida Transparente Layconsa x 240 ml | C37: Ensamble - Máquina | D37: Producto Terminado | E37: Cola | F37: Dosificado | G37: Línea_Cola | H37: Cola | J37: 1 | K37: 1 | L37: 1 | M37: N/A | P37: 2310160249 | Q37: Tapita Para Marcador 042 - N Negro | R37: Negro | S37: =+VLOOKUP(R37,$V$2:$W$13,2,FALSE) -> 12
A38: 2110100138 | B38: Tinta Para Marcador de Pizarra Layconsa L-126 Rojo | C38: Ensamble - Máquina | D38: Producto Terminado | E38: Tinteros | F38: Dosificado | G38: Línea_126 | H38: Tinteros | I38: N/A | J38: 1 | K38: 1 | L38: 1 | M38: N/A | P38: 2310090502 | Q38: Barril Para Marcador LYC Serigrafiado 047 - MK Piel Imp. Blanco | R38: Piel | S38: =+VLOOKUP(R38,$V$2:$W$13,2,FALSE) -> 1
A39: 2110100139 | B39: Tinta Para Marcador de Pizarra Layconsa L-126 Verde | C39: Ensamble - Máquina | D39: Producto Terminado | E39: Tinteros | F39: Dosificado | G39: Línea_126 | H39: Tinteros | I39: N/A | J39: 1 | K39: 1 | L39: 1 | M39: N/A | P39: 2310090495 | Q39: Barril Para Marcador LYC Serigrafiado 047 - MK Amarillo Imp. Blanco | R39: Amarillo | S39: =+VLOOKUP(R39,$V$2:$W$13,2,FALSE) -> 2
A40: 2110100136 | B40: Tinta Para Marcador de Pizarra Layconsa L-126 Azul | C40: Ensamble - Máquina | D40: Producto Terminado | E40: Tinteros | F40: Dosificado | G40: Línea_126 | H40: Tinteros | I40: N/A | J40: 1 | K40: 1 | L40: 1 | M40: N/A | P40: 2310090500 | Q40: Barril Para Marcador LYC Serigrafiado 047 - MK Anaranjado Imp. Blanco | R40: Anaranjado | S40: =+VLOOKUP(R40,$V$2:$W$13,2,FALSE) -> 3
A41: 2110100137 | B41: Tinta Para Marcador de Pizarra Layconsa L-126 Negro | C41: Ensamble - Máquina | D41: Producto Terminado | E41: Tinteros | F41: Dosificado | G41: Línea_126 | H41: Tinteros | I41: N/A | J41: 1 | K41: 1 | L41: 1 | M41: N/A | P41: 2310090498 | Q41: Barril Para Marcador LYC Serigrafiado 047 - MK Rosado Imp. Blanco | R41: rosado | S41: =+VLOOKUP(R41,$V$2:$W$13,2,FALSE) -> 4
A42: 2110080228 | B42: Bolígrafo Layconsa crystal L-036 Negro | C42: Ensamble - Máquina | D42: Producto Terminado | E42: Bolígrafo | F42: Encajado | G42: Línea_036 | H42: N/A | I42: N/A | J42: 1 | K42: 1 | L42: 1 | M42: N/A | P42: 2310090493 | Q42: Barril Para Marcador LYC Serigrafiado 047 - MK Rojo Imp. Blanco | R42: rojo | S42: =+VLOOKUP(R42,$V$2:$W$13,2,FALSE) -> 5
A43: 2110080229 | B43: Bolígrafo Layconsa crystal L-036 Rojo | C43: Ensamble - Máquina | D43: Producto Terminado | E43: Bolígrafo | F43: Encajado | G43: Línea_036 | H43: N/A | I43: N/A | J43: 1 | K43: 1 | L43: 1 | M43: N/A | P43: 2310090499 | Q43: Barril Para Marcador LYC Serigrafiado 047 - MK Morado Imp. Blanco | R43: morado | S43: =+VLOOKUP(R43,$V$2:$W$13,2,FALSE) -> 10
A44: 2110080227 | B44: Bolígrafo Layconsa crystal L-036 Azul | C44: Ensamble - Máquina | D44: Producto Terminado | E44: Bolígrafo | F44: Encajado | G44: Línea_036 | H44: N/A | I44: N/A | J44: 1 | K44: 1 | L44: 1 | M44: N/A | P44: 2310090497 | Q44: Barril Para Marcador LYC Serigrafiado 047 - MK Celeste Imp. Blanco | R44: celeste | S44: =+VLOOKUP(R44,$V$2:$W$13,2,FALSE) -> 6
A45: 2110080231 | B45: Bolígrafo Layconsa crystal L-036 Verde | C45: Ensamble - Máquina | D45: Producto Terminado | E45: Bolígrafo | F45: Encajado | G45: Línea_036 | H45: N/A | I45: N/A | J45: 1 | K45: 1 | L45: 1 | M45: N/A | P45: 2310090491 | Q45: Barril Para Marcador LYC Serigrafiado 047 - MK Azul Imp. Blanco | R45: azul | S45: =+VLOOKUP(R45,$V$2:$W$13,2,FALSE) -> 7
A46: 2110020288 | B46: Marcador Para Pizarra Recargable Layconsa L-123R Negro | C46: Ensamble - Máquina | D46: Producto Terminado | E46: Marc. Pizarra | F46: Encajado | G46: Línea_130 | H46: N/A | I46: N/A | J46: 1 | K46: 1 | L46: 1 | M46: N/A | P46: 2310090501 | Q46: Barril Para Marcador LYC Serigrafiado 047 - MK Verde Claro Imp. Blanco | R46: Verde Claro | S46: =+VLOOKUP(R46,$V$2:$W$13,2,FALSE) -> 8
A47: 2110020289 | B47: Marcador Para Pizarra Recargable Layconsa L-123R Rojo | C47: Ensamble - Máquina | D47: Producto Terminado | E47: Marc. Pizarra | F47: Encajado | G47: Línea_130 | H47: N/A | I47: N/A | J47: 1 | K47: 1 | L47: 1 | M47: N/A | P47: 2310090494 | Q47: Barril Para Marcador LYC Serigrafiado 047 - MK Verde Imp. Blanco | R47: verde | S47: =+VLOOKUP(R47,$V$2:$W$13,2,FALSE) -> 9
A48: 2110020287 | B48: Marcador Para Pizarra Recargable Layconsa L-123R Azul | C48: Ensamble - Máquina | D48: Producto Terminado | E48: Marc. Pizarra | F48: Encajado | G48: Línea_130 | H48: N/A | I48: N/A | J48: 1 | K48: 1 | L48: 1 | M48: N/A | P48: 2310090496 | Q48: Barril Para Marcador LYC Serigrafiado 047 - MK Marrrón Imp. Blanco | R48: marrón | S48: =+VLOOKUP(R48,$V$2:$W$13,2,FALSE) -> 11
A49: 2110020095 | B49: Plumones Layconsa School 45 Estuche x 12 | C49: Ensamble - Máquina | D49: Producto Terminado | E49: Plumones | F49: Encajado | G49: Línea_045 | H49: Plumones | I49: N/A | J49: 1 | K49: 12 | L49: 1 | M49: N/A | P49: 2310090492 | Q49: Barril Para Marcador LYC Serigrafiado 047 - MK Negro Imp. Blanco | R49: negro | S49: =+VLOOKUP(R49,$V$2:$W$13,2,FALSE) -> 12
... A131: 2140110705 | B131: Cuad.Grap. T. Renglón 70 H Arcoíris Femenino | C131: Cuaderno | D131: Producto Terminado | E131: Cuaderno Arcoiris Femenino | F131: Encuadernado | G131: Cuad Arcoíris | H131: N/A | I131: N/A | J131: 1 | K131: 1 | L131: 1 | M131: N/A | P131: 2310210138 | Q131: Plumones LYC School 45 Granel Piel NP P.S. | R131: Piel | S131: =+VLOOKUP(R131,$V$2:$W$13,2,FALSE) -> 1
A132: 2140110706 | B132: Cuad.Grap. 1x1 Cuadrimax. 70 H Arcoíris Femenino | C132: Cuaderno | D132: Producto Terminado | E132: Cuaderno Arcoiris Femenino | F132: Encuadernado | G132: Cuad Arcoíris | H132: N/A | I132: N/A | J132: 1 | K132: 1 | L132: 1 | M132: N/A | P132: 2310040558 | Q132: Formado Crayón Jumbo LYC Marrón | R132: Marrón | S132: =+VLOOKUP(R132,$V$15:$W$26,2,FALSE) -> 11
A133: 2140110707 | B133: Cuad.Grap. Cuad. 70 H Arcoíris Masculino | C133: Cuaderno | D133: Producto Terminado | E133: Cuaderno Arcoiris Masculino | F133: Encuadernado | G133: Cuad Arcoíris | H133: N/A | I133: N/A | J133: 1 | K133: 1 | L133: 1 | M133: N/A | P133: 2310040552 | Q133: Formado Crayón Jumbo LYC Verde Oscuro | R133: Verde | S133: =+VLOOKUP(R133,$V$15:$W$26,2,FALSE) -> 6
A134: 2140110708 | B134: Cuad.Grap. Ray. 70 H Arcoíris Masculino | C134: Cuaderno | D134: Producto Terminado | E134: Cuaderno Arcoiris Masculino | F134: Encuadernado | G134: Cuad Arcoíris | H134: N/A | I134: N/A | J134: 1 | K134: 1 | L134: 1 | M134: N/A | P134: 2310040555 | Q134: Formado Crayón Jumbo LYC Violeta | R134: Morado | S134: =+VLOOKUP(R134,$V$15:$W$26,2,FALSE) -> 10
A135: 2140110709 | B135: Cuad.Grap. T. Renglón 70 H Arcoíris Masculino | C135: Cuaderno | D135: Producto Terminado | E135: Cuaderno Arcoiris Masculino | F135: Encuadernado | G135: Cuad Arcoíris | H135: N/A | I135: N/A | J135: 1 | K135: 1 | L135: 1 | M135: N/A | P135: 2310040571 | Q135: Formado Crayón Triangular Jumbo LYC Blanco | R135: Blanco | S135: =+VLOOKUP(R135,$V$15:$W$26,2,FALSE) -> 9
A136: 2140110710 | B136: Cuad.Grap. 1x1 Cuadrimax. 70 H Arcoíris Masculino | C136: Cuaderno | D136: Producto Terminado | E136: Cuaderno Arcoiris Masculino | F136: Encuadernado | G136: Cuad Arcoíris | H136: N/A | I136: N/A | J136: 1 | K136: 1 | L136: 1 | M136: N/A | P136: 2310040362 | Q136: Formado Crayón Triangular Jumbo LYC Amarillo | R136: Amarillo | S136: =+VLOOKUP(R136,$V$15:$W$26,2,FALSE) -> 1
A137: 2140110711 | B137: Cuad. Grap. 1X1 Lucas Markin 100 Hj | C137: Cuaderno | D137: Producto Terminado | E137: Cuaderno Markin 100 | F137: Encuadernado | G137: Cuad Markin | H137: N/A | I137: N/A | J137: 1 | K137: 1 | L137: 1 | M137: N/A | P137: 2310040364 | Q137: Formado Crayón Triangular Jumbo LYC Anaranjado | R137: Anaranjado | S137: =+VLOOKUP(R137,$V$15:$W$26,2,FALSE) -> 2
A138: 2140110712 | B138: Cuad. Grap. 2X2 Lucas Markin 100 Hj | C138: Cuaderno | D138: Producto Terminado | E138: Cuaderno Markin 100 | F138: Encuadernado | G138: Cuad Markin | H138: N/A | I138: N/A | J138: 1 | K138: 1 | L138: 1 | M138: N/A | P138: 2310040368 | Q138: Formado Crayón Triangular Jumbo LYC Azul | R138: Azul | S138: =+VLOOKUP(R138,$V$15:$W$26,2,FALSE) -> 7
A139: 2140110699 | B139: Cuad.Grap. Cuad. 70 H Arcoíris | C139: Cuaderno | D139: Producto Terminado | E139: Cuaderno Arcoiris Color | F139: Encuadernado | G139: Cuad Arcoíris | H139: N/A | I139: N/A | J139: 1 | K139: 1 | L139: 1 | M139: N/A | P139: 2310040372 | Q139: Formado Crayón Triangular Jumbo LYC Marrón | R139: Marrón | S139: =+VLOOKUP(R139,$V$15:$W$26,2,FALSE) -> 11
A140: 2140110694 | B140: Cuad. Grap.Triple Reng. sin sombra 80H Layconsa Estudiante | C140: Cuaderno | D140: Producto Terminado | E140: Cuaderno Estudiante | F140: Encuadernado | G140: Cuad Layconsa | H140: N/A | I140: N/A | J140: 1 | K140: 1 | L140: 1 | M140: N/A | P140: 2310040370 | Q140: Formado Crayón Triangular Jumbo LYC Negro | R140: Negro | S140: =+VLOOKUP(R140,$V$15:$W$26,2,FALSE) -> 12
A141: 2140110677 | B141: Cuad. Grap. Cuadric. c/rojo 80H Layconsa Estudiante | C141: Cuaderno | D141: Producto Terminado | E141: Cuaderno Estudiante | F141: Encuadernado | G141: Cuad Layconsa | H141: N/A | I141: N/A | J141: 1 | K141: 1 | L141: 1 | M141: N/A | P141: 2310040361 | Q141: Formado Crayón Triangular Jumbo LYC Rojo | R141: Rojo | S141: =+VLOOKUP(R141,$V$15:$W$26,2,FALSE) -> 4
A142: 2140110678 | B142: Cuad. Grap. Cuadric. c/amarillo 80H Layconsa Estudiante | C142: Cuaderno | D142: Producto Terminado | E142: Cuaderno Estudiante | F142: Encuadernado | G142: Cuad Layconsa | H142: N/A | I142: N/A | J142: 1 | K142: 1 | L142: 1 | M142: N/A | P142: 2310040371 | Q142: Formado Crayón Triangular Jumbo LYC Rosado | R142: Rosado | S142: =+VLOOKUP(R142,$V$15:$W$26,2,FALSE) -> 3
A143: 2140110679 | B143: Cuad. Grap. Cuadric. c/azul 80H Layconsa Estudiante | C143: Cuaderno | D143: Producto Terminado | E143: Cuaderno Estudiante | F143: Encuadernado | G143: Cuad Layconsa | H143: N/A | I143: N/A | J143: 1 | K143: 1 | L143: 1 | M143: N/A | P143: 2310040365 | Q143: Formado Crayón Triangular Jumbo LYC Verde Claro | R143: Verde Claro | S143: =+VLOOKUP(R143,$V$15:$W$26,2,FALSE) -> 5
... A155: 2140110729 | B155: Cuad. Grap. Cuadric. marrón 80H Layconsa Estudiante | C155: Cuaderno | D155: Producto Terminado | E155: Cuaderno Estudiante | F155: Encuadernado | G155: Cuad Layconsa | H155: N/A | I155: N/A | J155: 1 | K155: 1 | L155: 1 | M155: N/A | P155: 2310040547 | Q155: Formado Crayón Jumbo LYC Rojo | R155: Rojo | S155: =+VLOOKUP(R155,$V$15:$W$26,2,FALSE) -> 4
A156: 2140110730 | B156: Cuad. Grap. Triple renglon calig. amarillo 80H Layconsa Estudiante | C156: Cuaderno | D156: Producto Terminado | E156: Cuaderno Estudiante | F156: Encuadernado | G156: Cuad Layconsa | H156: N/A | I156: N/A | J156: 1 | K156: 1 | L156: 1 | M156: N/A
A157: 2140110720 | B157: Cuad.Grap. 1x1 80H Lucas Markin masc c/sticker | C157: Cuaderno | D157: Producto Terminado | E157: Cuaderno Markin Masculino | F157: Encuadernado | G157: Cuad Markin | H157: N/A | I157: N/A | J157: 1 | K157: 1 | L157: 1 | M157: N/A
A158: 2140110731 | B158: Cuad. Grap. A-4 Cuadr. 88 H Layconsa Lite | C158: Cuaderno | D158: Producto Terminado | E158: Cuaderno Lite 88 | F158: Encuadernado | G158: Cuad Layconsa | H158: N/A | I158: N/A | J158: 1 | K158: 1 | L158: 1 | M158: N/A
A159: 2140110732 | B159: Cuad. Grap. A-4 Ray. 88 H Layconsa Lite | C159: Cuaderno | D159: Producto Terminado | E159: Cuaderno Lite 88 | F159: Encuadernado | G159: Cuad Layconsa | H159: N/A | I159: N/A | J159: 1 | K159: 1 | L159: 1 | M159: N/A
A160: 2140110733 | B160: Cuad. Grap. T.R. Caligráfico 88 H. Layconsa Lite | C160: Cuaderno | D160: Producto Terminado | E160: Cuaderno Lite 88 | F160: Encuadernado | G160: Cuad Layconsa | H160: N/A | I160: N/A | J160: 1 | K160: 1 | L160: 1 | M160: N/A
A161: 2140110734 | B161: Cuad. Grap. Cuadr. Gamer Layconsa 80 H | C161: Cuaderno | D161: Producto Terminado | E161: Cuaderno Layconsa Diseño | F161: Encuadernado | G161: Cuad Layconsa | H161: N/A | I161: N/A | J161: 1 | K161: 1 | L161: 1 | M161: N/A
A162: 2140110735 | B162: Cuad. Grap. Ray. Gamer Layconsa 80 H | C162: Cuaderno | D162: Producto Terminado | E162: Cuaderno Layconsa Diseño | F162: Encuadernado | G162: Cuad Layconsa | H162: N/A | I162: N/A | J162: 1 | K162: 1 | L162: 1 | M162: N/A
A163: 2140110736 | B163: Cuad. Grap. T.R. Caligráfico Gamer Layconsa 80 H | C163: Cuaderno | D163: Producto Terminado | E163: Cuaderno Layconsa Diseño | F163: Encuadernado | G163: Cuad Layconsa | H163: N/A | I163: N/A | J163: 1 | K163: 1 | L163: 1 | M163: N/A
A164: 2140110737 | B164: Cuad. Grap. Cuadr. K-POP Layconsa 80 H | C164: Cuaderno | D164: Producto Terminado | E164: Cuaderno Layconsa Diseño | F164: Encuadernado | G164: Cuad Layconsa | H164: N/A | I164: N/A | J164: 1 | K164: 1 | L164: 1 | M164: N/A
A165: 2140110738 | B165: Cuad. Grap. Ray. K-POP Layconsa 80 H | C165: Cuaderno | D165: Producto Terminado | E165: Cuaderno Layconsa Diseño | F165: Encuadernado | G165: Cuad Layconsa | H165: N/A | I165: N/A | J165: 1 | K165: 1 | L165: 1 | M165: N/A
A166: 2140110739 | B166: Cuad. Grap. T.R. Caligráfico K-POP Layconsa 80 H | C166: Cuaderno | D166: Producto Terminado | E166: Cuaderno Layconsa Diseño | F166: Encuadernado | G166: Cuad Layconsa | H166: N/A | I166: N/A | J166: 1 | K166: 1 | L166: 1 | M166: N/A
A167: 2140110743 | B167: Cuad. Grap. Triple Reng. caligráfico c/mco rojo 80 H. Layconsa Puppy | C167: Cuaderno | D167: Producto Terminado | E167: Cuaderno Puppy | F167: Encuadernado | G167: Cuad Layconsa | H167: N/A | I167: N/A | J167: 1 | K167: 1 | L167: 1 | M167: N/A
... A227: 2310210201 | B227: Plumones LYC School 45 Granel Chocolate P.S. | C227: Ensamble - Máquina | D227: Semiterminado | E227: N/A | F227: Ensamble | G227: Línea_045 | H227: Ensamble_36 | I227: Ensamble_L45 | J227: 1 | K227: 1 | L227: 1 | M227: N/A
A228: 2310160166 | B228: Tapa Dosificador Ensamblada Azul | C228: Ensamble - Máquina | D228: Semiterminado | E228: N/A | F228: Ensamble | G228: Línea_Cola | H228: Dosificador | J228: 1 | K228: 1 | L228: 1 | M228: N/A
A229: 2310160552 | B229: Tapa Dosificador Ensamblada Rojo Paleta | C229: Ensamble - Máquina | D229: Semiterminado | E229: N/A | F229: Ensamble | G229: Línea_Cola | H229: Dosificador | J229: 1 | K229: 1 | L229: 1 | M229: N/A
A230: 2310160282 | B230: Tapa Dosificador Ensamblada Rojo | C230: Ensamble - Máquina | D230: Semiterminado | E230: N/A | F230: Ensamble | G230: Línea_250cc | H230: Dosificador | I230: Ensamble - Tem | J230: 1 | K230: 1 | L230: 1 | M230: N/A
A231: 2310090514 | B231: Barril 42 C/Etiqueta Marcador Magico P.S. | C231: Ensamble - Máquina | D231: Semiterminado | E231: N/A | F231: Etiquetado | G231: Línea_042 | H231: Marc. Mágico | J231: 1 | K231: 1 | L231: 1 | M231: N/A
A232: 2310230105 | B232: Frasco de tempera etiquetado 30 cc ARTI P.S. | C232: Ensamble - Máquina | D232: Semiterminado | E232: N/A | F232: Etiquetado | G232: Línea_30cc | H232: Frasco | I232: N/A | J232: 1 | K232: 1 | L232: 1 | M232: N/A
A233: 2310040525 | B233: Formado Crayón Delgado c/Etiqueta LYC Rosado | C233: Ensamble - Máquina | D233: Semiterminado | E233: N/A | F233: Etiquetado | G233: Línea_Crayón | H233: Crayón_Delgadp | I233: Etiquetado | J233: 1 | K233: 1 | L233: 1 | M233: N/A
A234: 2310040528 | B234: Formado Crayón Delgado c/Etiqueta LYC Verde Oscuro | C234: Ensamble - Máquina | D234: Semiterminado | E234: N/A | F234: Etiquetado | G234: Línea_Crayón | H234: Crayón_Delgadp | I234: Etiquetado | J234: 1 | K234: 1 | L234: 1 | M234: N/A
A235: 2310040532 | B235: Formado Crayón Delgado c/Etiqueta LYC Negro | C235: Ensamble - Máquina | D235: Semiterminado | E235: N/A | F235: Etiquetado | G235: Línea_Crayón | H235: Crayón_Delgadp | I235: Etiquetado | J235: 1 | K235: 1 | L235: 1 | M235: N/A
A236: 2310040524 | B236: Formado Crayón Delgado c/Etiqueta LYC Amarillo | C236: Ensamble - Máquina | D236: Semiterminado | E236: N/A | F236: Etiquetado | G236: Línea_Crayón | H236: Crayón_Delgadp | I236: Etiquetado | J236: 1 | K236: 1 | L236: 1 | M236: N/A
A237: 2310040527 | B237: Formado Crayón Delgado c/Etiqueta LYC Verde Claro | C237: Ensamble - Máquina | D237: Semiterminado | E237: N/A | F237: Etiquetado | G237: Línea_Crayón | H237: Crayón_Delgadp | I237: Etiquetado | J237: 1 | K237: 1 | L237: 1 | M237: N/A
A238: 2310040523 | B238: Formado Crayón Delgado c/Etiqueta LYC Rojo | C238: Ensamble - Máquina | D238: Semiterminado | E238: N/A | F238: Etiquetado | G238: Línea_Crayón | H238: Crayón_Delgadp | I238: Etiquetado | J238: 1 | K238: 1 | L238: 1 | M238: N/A
A239: 2310040526 | B239: Formado Crayón Delgado c/Etiqueta LYC Anaranjado | C239: Ensamble - Máquina | D239: Semiterminado | E239: N/A | F239: Etiquetado | G239: Línea_Crayón | H239: Crayón_Delgadp | I239: Etiquetado | J239: 1 | K239: 1 | L239: 1 | M239: N/A
A240: 2310040531 | B240: Formado Crayón Delgado c/Etiqueta LYC Violeta | C240: Ensamble - Máquina | D240: Semiterminado | E240: N/A | F240: Etiquetado | G240: Línea_Crayón | H240: Crayón_Delgadp | I240: Etiquetado | J240: 1 | K240: 1 | L240: 1 | M240: N/A
A241: 2310040534 | B241: Formado Crayón Delgado c/Etiqueta LYC Marrón | C241: Ensamble - Máquina | D241: Semiterminado | E241: N/A | F241: Etiquetado | G241: Línea_Crayón | H241: Crayón_Delgadp | I241: Etiquetado | J241: 1 | K241: 1 | L241: 1 | M241: N/A
A242: 2310040529 | B242: Formado Crayón Delgado c/Etiqueta LYC Celeste | C242: Ensamble - Máquina | D242: Semiterminado | E242: N/A | F242: Etiquetado | G242: Línea_Crayón | H242: Crayón_Delgadp | I242: Etiquetado | J242: 1 | K242: 1 | L242: 1 | M242: N/A
A243: 2310040530 | B243: Formado Crayón Delgado c/Etiqueta LYC Azul | C243: Ensamble - Máquina | D243: Semiterminado | E243: N/A | F243: Etiquetado | G243: Línea_Crayón | H243: Crayón_Delgadp | I243: Etiquetado | J243: 1 | K243: 1 | L243: 1 | M243: N/A
... A268: 2310040626 | B268: Formado Crayón c/Etiqueta Jumbo Rosado Mongol P.S. | C268: Ensamble - Máquina | D268: Semiterminado | E268: N/A | F268: Etiquetado | G268: Línea_Crayón | H268: Crayón_Colores | I268: Etiquetado | J268: 1 | K268: 1 | L268: 1 | M268: N/A
A269: 2310040560 | B269: Formado Crayón c/Etiqueta Jumbo LYC Amarillo | C269: Ensamble - Máquina | D269: Semiterminado | E269: N/A | F269: Etiquetado | G269: Línea_Crayón | H269: Crayón_Jumbo | J269: 1 | K269: 1 | L269: 1 | M269: N/A
A270: 2310040562 | B270: Formado Crayón c/Etiqueta Jumbo LYC Anaranjado | C270: Ensamble - Máquina | D270: Semiterminado | E270: N/A | F270: Etiquetado | G270: Línea_Crayón | H270: Crayón_Jumbo | J270: 1 | K270: 1 | L270: 1 | M270: N/A
A271: 2310040566 | B271: Formado Crayón c/Etiqueta Jumbo LYC Azul | C271: Ensamble - Máquina | D271: Semiterminado | E271: N/A | F271: Etiquetado | G271: Línea_Crayón | H271: Crayón_Jumbo | J271: 1 | K271: 1 | L271: 1 | M271: N/A
A272: 2310040561 | B272: Formado Crayón c/Etiqueta Jumbo LYC Blanco | C272: Ensamble - Máquina | D272: Semiterminado | E272: N/A | F272: Etiquetado | G272: Línea_Crayón | H272: Crayón_Jumbo | J272: 1 | K272: 1 | L272: 1 | M272: N/A
A273: 2310040565 | B273: Formado Crayón c/Etiqueta Jumbo LYC Celeste | C273: Ensamble - Máquina | D273: Semiterminado | E273: N/A | F273: Etiquetado | G273: Línea_Crayón | H273: Crayón_Jumbo | J273: 1 | K273: 1 | L273: 1 | M273: N/A
A274: 2310040570 | B274: Formado Crayón c/Etiqueta Jumbo LYC Marrón | C274: Ensamble - Máquina | D274: Semiterminado | E274: N/A | F274: Etiquetado | G274: Línea_Crayón | H274: Crayón_Jumbo | J274: 1 | K274: 1 | L274: 1 | M274: N/A
A275: 2310040568 | B275: Formado Crayón c/Etiqueta Jumbo LYC Negro | C275: Ensamble - Máquina | D275: Semiterminado | E275: N/A | F275: Etiquetado | G275: Línea_Crayón | H275: Crayón_Jumbo | J275: 1 | K275: 1 | L275: 1 | M275: N/A
...

Sheet Tiempos
A1: Código Semi | B1: 0 | C1: Cantidad Base | D1: T.MO | E1: T.Maq | F1: Cant.Opr | G1: Maquina | H1: Tarifa Maquina | I1: Tarifa MO | J1: Proceso | K1: T.ciclo | L1: Cav. Oper | M1: Cav. Tot | N1: Componente | O1: Grupo del recurso
A2: 2110030001 | B2: Témperas Layconsa Puppy Set x 7 | C2: 6000 | D2: 60 | E2: 12 | F2: 5 | G2: DOSI_TEMP01 | H2: 159.8419 | I2: 10.94472 | J2: Dosificado | K2: 0 | L2: 0 | M2: 0 | O2: ENSAMBLE_LIMA
A3: 2110110001 | B3: Cola Escolar Layconsa x 125 gr. | C3: 20000 | D3: 60 | E3: 12 | F3: 5 | G3: MAQ_DOS1 | H3: 233.4585 | I3: 9.46003 | J3: Dosificado | K3: 0 | L3: 0 | M3: 0 | O3: ENSAMBLE_LIMA
A4: 2110110002 | B4: Cola Escolar Layconsa de 250Gr con Dispensador | C4: 20000 | D4: 60 | E4: 12 | F4: 5 | G4: MAQ_DOS1 | H4: 233.4585 | I4: 9.46003 | J4: Dosificado | K4: 0 | L4: 0 | M4: 0 | O4: ENSAMBLE_LIMA
A5: 2110110025 | B5: Cola sintética Layconsa x 60 g. c/ dispensador | C5: 30000 | D5: 60 | E5: 12 | F5: 5 | G5: MAQ_DOS1 | H5: 233.4585 | I5: 9.46003 | J5: Dosificado | K5: 0 | L5: 0 | M5: 0 | O5: ENSAMBLE_LIMA
A6: 2110030055 | B6: Témpera Layconsa Puppy x 250 cc Verde c/Dispensador | C6: 15000 | D6: 48 | E6: 12 | F6: 4 | G6: MAQ_DOS1 | H6: 233.4585 | I6: 9.46003 | J6: Dosificado | K6: 0 | L6: 0 | M6: 0 | O6: ENSAMBLE_LIMA
A7: 2110030056 | B7: Témpera Layconsa Puppy x 250 cc Blanca c/Dispensador | C7: 15000 | D7: 48 | E7: 12 | F7: 4 | G7: MAQ_DOS1 | H7: 233.4585 | I7: 9.46003 | J7: Dosificado | K7: 0 | L7: 0 | M7: 0 | O7: ENSAMBLE_LIMA
A8: 2110030057 | B8: Témpera Layconsa Puppy x 250 cc Azul c/Dispensador | C8: 15000 | D8: 48 | E8: 12 | F8: 4 | G8: MAQ_DOS1 | H8: 233.4585 | I8: 9.46003 | J8: Dosificado | K8: 0 | L8: 0 | M8: 0 | O8: ENSAMBLE_LIMA
A9: 2110030058 | B9: Témpera Layconsa Puppy x 250 cc Roja c/Dispensador | C9: 15000 | D9: 48 | E9: 12 | F9: 4 | G9: MAQ_DOS1 | H9: 233.4585 | I9: 9.46003 | J9: Dosificado | K9: 0 | L9: 0 | M9: 0 | O9: ENSAMBLE_LIMA
A10: 2110030059 | B10: Témpera Layconsa Puppy x 250 cc Amarilla c/Dispensador | C10: 15000 | D10: 48 | E10: 12 | F10: 4 | G10: MAQ_DOS1 | H10: 233.4585 | I10: 9.46003 | J10: Dosificado | K10: 0 | L10: 0 | M10: 0 | O10: ENSAMBLE_LIMA
A11: 2110030060 | B11: Témpera Layconsa Puppy x 250 cc Piel c/Dispensador | C11: 15000 | D11: 48 | E11: 12 | F11: 4 | G11: MAQ_DOS1 | H11: 233.4585 | I11: 9.46003 | J11: Dosificado | K11: 0 | L11: 0 | M11: 0 | O11: ENSAMBLE_LIMA
A12: 2110030078 | B12: Témpera Layconsa Puppy x 250 cc Marrón c/Dispensador | C12: 15000 | D12: 48 | E12: 12 | F12: 4 | G12: MAQ_DOS1 | H12: 233.4585 | I12: 9.46003 | J12: Dosificado | K12: 0 | L12: 0 | M12: 0 | O12: ENSAMBLE_LIMA
A13: 2110030079 | B13: Témpera Layconsa Puppy x 250 cc Negro c/Dispensador | C13: 15000 | D13: 48 | E13: 12 | F13: 4 | G13: MAQ_DOS1 | H13: 233.4585 | I13: 9.46003 | J13: Dosificado | K13: 0 | L13: 0 | M13: 0 | O13: ENSAMBLE_LIMA
... A34: 2110110033 | B34: Goma Líquida Transparente Layconsa x 240 ml | C34: 4000 | D34: 60 | E34: 12 | F34: 5 | G34: MAQ_DOS1 | H34: 233.4585 | I34: 9.46003 | J34: Dosificado | K34: 0 | L34: 0 | M34: 0 | O34: ENSAMBLE_LIMA
A35: 2310320328 | B35: Carga Para Bolígrafo 036 PFTR Azul N | C35: 35000 | D35: 12 | E35: 12 | F35: 1 | G35: CAR02 | H35: 21.0719 | I35: 17.35738 | J35: Dosificado | O35: ENSAMBLE_LIMA
A36: 2310320330 | B36: Carga Para Bolígrafo 036 PFTR Negro N | C36: 35000 | D36: 12 | E36: 12 | F36: 1 | G36: CAR02 | H36: 21.0719 | I36: 17.35738 | J36: Dosificado | O36: ENSAMBLE_LIMA
A37: 2310320329 | B37: Carga Para Bolígrafo 036 PFTR Rojo N | C37: 35000 | D37: 12 | E37: 12 | F37: 1 | G37: CAR02 | H37: 21.0719 | I37: 17.35738 | J37: Dosificado | O37: ENSAMBLE_LIMA
A38: 2310320348 | B38: Carga Para Bolígrafo 036 PFTR Verde N | C38: 35000 | D38: 12 | E38: 12 | F38: 1 | G38: CAR02 | H38: 21.0719 | I38: 17.35738 | J38: Dosificado | O38: ENSAMBLE_LIMA
A39: 2310350114 | B39: Carga para Bolígrafo 036 PT MD Amarillo | C39: 35000 | D39: 12 | E39: 12 | F39: 1 | G39: CAR02 | H39: 21.0719 | I39: 17.35738 | J39: Dosificado | O39: ENSAMBLE_LIMA
A40: 2310350115 | B40: Carga para Bolígrafo 036 PT MD Anaranjado | C40: 35000 | D40: 12 | E40: 12 | F40: 1 | G40: CAR02 | H40: 21.0719 | I40: 17.35738 | J40: Dosificado | O40: ENSAMBLE_LIMA
A41: 2310350020 | B41: Carga para Bolígrafo 036 PT MD Azul | C41: 35000 | D41: 12 | E41: 12 | F41: 1 | G41: CAR02 | H41: 21.0719 | I41: 17.35738 | J41: Dosificado | O41: ENSAMBLE_LIMA
A42: 2310350113 | B42: Carga para Bolígrafo 036 PT MD Marron | C42: 35000 | D42: 12 | E42: 12 | F42: 1 | G42: CAR02 | H42: 21.0719 | I42: 17.35738 | J42: Dosificado | O42: ENSAMBLE_LIMA
A43: 2310350110 | B43: Carga para Bolígrafo 036 PT MD Morado | C43: 35000 | D43: 12 | E43: 12 | F43: 1 | G43: CAR02 | H43: 21.0719 | I43: 17.35738 | J43: Dosificado | O43: ENSAMBLE_LIMA
A44: 2310350021 | B44: Carga para Bolígrafo 036 PT MD Negro | C44: 35000 | D44: 12 | E44: 12 | F44: 1 | G44: CAR02 | H44: 21.0719 | I44: 17.35738 | J44: Dosificado | O44: ENSAMBLE_LIMA
A45: 2310350043 | B45: Carga Para Bolígrafo 036 PT MD Rojo | C45: 35000 | D45: 12 | E45: 12 | F45: 1 | G45: CAR02 | H45: 21.0719 | I45: 17.35738 | J45: Dosificado | O45: ENSAMBLE_LIMA
A46: 2310350109 | B46: Carga para Bolígrafo 036 PT MD Rosado | C46: 35000 | D46: 12 | E46: 12 | F46: 1 | G46: CAR02 | H46: 21.0719 | I46: 17.35738 | J46: Dosificado | O46: ENSAMBLE_LIMA
... A48: 2310350111 | B48: Carga para Bolígrafo 036 PT MD Verde Claro | C48: 35000 | D48: 12 | E48: 12 | F48: 1 | G48: CAR02 | H48: 21.0719 | I48: 17.35738 | J48: Dosificado | O48: ENSAMBLE_LIMA
A49: 211003DTAZ | B49: Témpera Layconsa Puppy x 120 cc Azul c/Dispensador | C49: 20000 | D49: 48 | E49: 12 | F49: 4 | G49: MAQ_DOS1 | H49: 233.4585 | I49: 9.46003 | J49: Dosificado | K49: 0 | L49: 0 | M49: 0 | O49: ENSAMBLE_LIMA
A50: 211003DTPI | B50: Témpera Layconsa Puppy x 120 cc Piel c/Dispensador | C50: 20000 | D50: 48 | E50: 12 | F50: 4 | G50: MAQ_DOS1 | H50: 233.4585 | I50: 9.46003 | J50: Dosificado | K50: 0 | L50: 0 | M50: 0 | O50: ENSAMBLE_LIMA
A51: 211003DTRO | B51: Témpera Layconsa Puppy x 120 cc Rojo c/Dispensador | C51: 20000 | D51: 48 | E51: 12 | F51: 4 | G51: MAQ_DOS1 | H51: 233.4585 | I51: 9.46003 | J51: Dosificado | K51: 0 | L51: 0 | M51: 0 | O51: ENSAMBLE_LIMA
A52: 211003DTNE | B52: Témpera Layconsa Puppy x 120 cc Negro c/Dispensador | C52: 20000 | D52: 48 | E52: 12 | F52: 4 | G52: MAQ_DOS1 | H52: 233.4585 | I52: 9.46003 | J52: Dosificado | K52: 0 | L52: 0 | M52: 0 | O52: ENSAMBLE_LIMA
A53: 211003DTVE | B53: Témpera Layconsa Puppy x 120 cc Verde c/Dispensador | C53: 20000 | D53: 48 | E53: 12 | F53: 4 | G53: MAQ_DOS1 | H53: 233.4585 | I53: 9.46003 | J53: Dosificado | K53: 0 | L53: 0 | M53: 0 | O53: ENSAMBLE_LIMA
A54: 211003DTAM | B54: Témpera Layconsa Puppy x 120 cc Amarillo c/Dispensador | C54: 20000 | D54: 48 | E54: 12 | F54: 4 | G54: MAQ_DOS1 | H54: 233.4585 | I54: 9.46003 | J54: Dosificado | K54: 0 | L54: 0 | M54: 0 | O54: ENSAMBLE_LIMA
A55: 211003DTNA | B55: Témpera Layconsa Puppy x 120 cc Naranja c/Dispensador | C55: 20000 | D55: 48 | E55: 12 | F55: 4 | G55: MAQ_DOS1 | H55: 233.4585 | I55: 9.46003 | J55: Dosificado | K55: 0 | L55: 0 | M55: 0 | O55: ENSAMBLE_LIMA
A56: 211003DTBL | B56: Témpera Layconsa Puppy x 120 cc Blanco c/Dispensador | C56: 20000 | D56: 48 | E56: 12 | F56: 4 | G56: MAQ_DOS1 | H56: 233.4585 | I56: 9.46003 | J56: Dosificado | K56: 0 | L56: 0 | M56: 0 | O56: ENSAMBLE_LIMA
A57: 211003DTCE | B57: Témpera Layconsa Puppy x 120 cc Celeste c/Dispensador | C57: 20000 | D57: 48 | E57: 12 | F57: 4 | G57: MAQ_DOS1 | H57: 233.4585 | I57: 9.46003 | J57: Dosificado | K57: 0 | L57: 0 | M57: 0 | O57: ENSAMBLE_LIMA
A58: 211003DTFU | B58: Témpera Layconsa Puppy x 120 cc Fucsia c/Dispensador | C58: 20000 | D58: 48 | E58: 12 | F58: 4 | G58: MAQ_DOS1 | H58: 233.4585 | I58: 9.46003 | J58: Dosificado | K58: 0 | L58: 0 | M58: 0 | O58: ENSAMBLE_LIMA
A59: 211003DTMA | B59: Témpera Layconsa Puppy x 120 cc Marrón c/Dispensador | C59: 20000 | D59: 48 | E59: 12 | F59: 4 | G59: MAQ_DOS1 | H59: 233.4585 | I59: 9.46003 | J59: Dosificado | K59: 0 | L59: 0 | M59: 0 | O59: ENSAMBLE_LIMA
A60: 211003DTRS | B60: Témpera Layconsa Puppy x 120 cc Rosado c/Dispensador | C60: 20000 | D60: 48 | E60: 12 | F60: 4 | G60: MAQ_DOS1 | H60: 233.4585 | I60: 9.46003 | J60: Dosificado | K60: 0 | L60: 0 | M60: 0 | O60: ENSAMBLE_LIMA
A61: 211003DTVC | B61: Témpera Layconsa Puppy x 120 cc Verde Claro c/Dispensador | C61: 20000 | D61: 48 | E61: 12 | F61: 4 | G61: MAQ_DOS1 | H61: 233.4585 | I61: 9.46003 | J61: Dosificado | K61: 0 | L61: 0 | M61: 0 | O61: ENSAMBLE_LIMA
A62: 2110020095 | B62: Plumones Layconsa School 45 Estuche x 12 | C62: 8000 | D62: 72 | E62: 12 | F62: 6 | G62: ENCJ02 | H62: 259.0706 | I62: 9.02076 | J62: Encajado | K62: 0 | L62: 0 | M62: 0 | O62: ENSAMBLE_LIMA
A63: 2110020322 | B63: Marcador Layconsa Jumbo L-47 x 12 Colores NT Estuche | C63: 6000 | D63: 72 | E63: 12 | F63: 6 | G63: ENCJ01 | H63: 172.7865 | I63: 9.18112 | J63: Encajado | K63: 0 | L63: 0 | M63: 0 | O63: ENSAMBLE_LIMA
A64: 2110080227 | B64: Bolígrafo Layconsa crystal L-036 Azul | C64: 35000 | D64: 24 | E64: 12 | F64: 2 | G64: ENS03 | H64: 15.3382 | I64: 12.0544 | J64: Encajado | K64: 0 | L64: 0 | M64: 0 | O64: ENSAMBLE_LIMA
A65: 2110080228 | B65: Bolígrafo Layconsa crystal L-036 Negro | C65: 35000 | D65: 24 | E65: 12 | F65: 2 | G65: ENS03 | H65: 15.3382 | I65: 12.0544 | J65: Encajado | K65: 0 | L65: 0 | M65: 0 | O65: ENSAMBLE_LIMA
A66: 2110080229 | B66: Bolígrafo Layconsa crystal L-036 Rojo | C66: 35000 | D66: 24 | E66: 12 | F66: 2 | G66: ENS03 | H66: 15.3382 | I66: 12.0544 | J66: Encajado | K66: 0 | L66: 0 | M66: 0 | O66: ENSAMBLE_LIMA
A67: 2110080231 | B67: Bolígrafo Layconsa crystal L-036 Verde | C67: 35000 | D67: 24 | E67: 12 | F67: 2 | G67: ENS03 | H67: 15.3382 | I67: 12.0544 | J67: Encajado | K67: 0 | L67: 0 | M67: 0 | O67: ENSAMBLE_LIMA
A68: 2110040016 | B68: Crayón Layconsa Puppy Jumbo x 12 | C68: 7000 | D68: 60 | E68: 12 | F68: 5 | G68: ENCJ03 | H68: 111.5332 | I68: 8.53306 | J68: Encajado | K68: 0 | L68: 0 | M68: 0 | O68: ENSAMBLE_LIMA
A69: 2110040047 | B69: Crayón triangular cj. cartón Layconsa Puppy Jumbo x 12 | C69: 4000 | D69: 96 | E69: 0 | F69: 8 | G69: ENCJ03 | H69: 111.5332 | I69: 8.53306 | J69: Encajado | K69: 0 | L69: 0 | M69: 0 | O69: ENSAMBLE_LIMA
A70: 2110020108 | B70: Marcador Layconsa Jumbo L-47 Estuche x 6 Colores NT | C70: 8000 | D70: 48 | E70: 12 | F70: 4 | G70: ENCJ01 | H70: 172.7865 | I70: 9.18112 | J70: Encajado | K70: 0 | L70: 0 | M70: 0 | O70: ENSAMBLE_LIMA
A71: 2110020109 | B71: Marcador Layconsa Jumbo L-47 Estuche x 10 Colores NT | C71: 7000 | D71: 48 | E71: 12 | F71: 4 | G71: ENCJ01 | H71: 172.7865 | I71: 9.18112 | J71: Encajado | K71: 0 | L71: 0 | M71: 0 | O71: ENSAMBLE_LIMA
A72: 2110020107 | B72: Marcador Layconsa Jumbo L-47 Verde NT | C72: 25000 | D72: 24 | E72: 12 | F72: 2 | G72: ENS01 | H72: 64.1264 | I72: 10.91894 | J72: Encajado | K72: 0 | L72: 0 | M72: 0 | O72: ENSAMBLE_LIMA
A73: 2110020316 | B73: Marcador Layconsa Jumbo L-47 Marrón NT | C73: 25000 | D73: 24 | E73: 12 | F73: 2 | G73: ENS01 | H73: 64.1264 | I73: 10.91894 | J73: Encajado | K73: 0 | L73: 0 | M73: 0 | O73: ENSAMBLE_LIMA
... A93: 2110020346 | B93: Plumones Layconsa School 45 estuche x 36 | C93: 2000 | D93: 108 | E93: 0 | F93: 9 | G93: AMAN02 | H93: 0 | I93: 11.11745 | J93: Encajado | K93: 0 | L93: 0 | M93: 0 | O93: ENSAMBLE_LIMA
A94: 211002ESTU | B94: Marcador Pizarra Layconsa L-123 Est. x 12 colores | C94: 6000 | D94: 72 | E94: 12 | F94: 6 | G94: ENCJ01 | H94: 172.7865 | I94: 9.18112 | J94: Encajado | K94: 0 | L94: 0 | M94: 0 | O94: ENSAMBLE_LIMA
A95: 2140110610 | B95: Cuad. Grap. Cuadr. 80 H. c/marco rojo Layconsa Puppy | C95: 40000 | D95: 456 | E95: 24 | F95: 19 | G95: WIL001 | H95: 279.7313 | I95: 14.99874 | J95: Encuadernado | O95: PAPELERIA_LIMA
A96: 2140110673 | B96: Cuad. Grap. 1x1 c/mco rojo 80 H. Layconsa Puppy | C96: 40000 | D96: 456 | E96: 24 | F96: 19 | G96: WIL001 | H96: 279.7313 | I96: 14.99874 | J96: Encuadernado | O96: PAPELERIA_LIMA
A97: 2140110675 | B97: Cuad. Grap. Decroly c/mco rojo 80 H. Layconsa Puppy | C97: 40000 | D97: 456 | E97: 24 | F97: 19 | G97: WIL001 | H97: 279.7313 | I97: 14.99874 | J97: Encuadernado | O97: PAPELERIA_LIMA
A98: 2140110676 | B98: Cuad. Grap. Triple Max c/mco rojo 80 H. Layconsa Puppy | C98: 40000 | D98: 456 | E98: 24 | F98: 19 | G98: WIL001 | H98: 279.7313 | I98: 14.99874 | J98: Encuadernado | O98: PAPELERIA_LIMA
A99: 2140110674 | B99: Cuad. Grap. 2x2 c/mco rojo 80 H. Layconsa Puppy | C99: 40000 | D99: 456 | E99: 24 | F99: 19 | G99: WIL001 | H99: 279.7313 | I99: 14.99874 | J99: Encuadernado | O99: PAPELERIA_LIMA
A100: 2140110613 | B100: Cuad. Grap. Cuadr. Princess Club Layconsa 80 H | C100: 40000 | D100: 456 | E100: 24 | F100: 19 | G100: WIL001 | H100: 279.7313 | I100: 14.99874 | J100: Encuadernado | O100: PAPELERIA_LIMA
A101: 2140110615 | B101: Cuad. Grap. Cuadr. Unicornios Layconsa 80 H | C101: 40000 | D101: 456 | E101: 24 | F101: 19 | G101: WIL001 | H101: 279.7313 | I101: 14.99874 | J101: Encuadernado | O101: PAPELERIA_LIMA
A102: 2140110620 | B102: Cuad. Grap. Cuadr. Dino Attack Layconsa 80 H | C102: 40000 | D102: 456 | E102: 24 | F102: 19 | G102: WIL001 | H102: 279.7313 | I102: 14.99874 | J102: Encuadernado | O102: PAPELERIA_LIMA
A103: 2140110622 | B103: Cuad. Grap. Cuadr. Potencia Extrema Layconsa 80 H | C103: 40000 | D103: 456 | E103: 24 | F103: 19 | G103: WIL001 | H103: 279.7313 | I103: 14.99874 | J103: Encuadernado | O103: PAPELERIA_LIMA
A104: 2140110644 | B104: Cuad. Grap. Cuadr. Fast Racer Layconsa 80 H | C104: 40000 | D104: 456 | E104: 24 | F104: 19 | G104: WIL001 | H104: 279.7313 | I104: 14.99874 | J104: Encuadernado | O104: PAPELERIA_LIMA
A105: 2140110642 | B105: Cuad. Grap. T.R. Caligráfico Dino Attack Layconsa 80 H. | C105: 40000 | D105: 456 | E105: 24 | F105: 19 | G105: WIL001 | H105: 279.7313 | I105: 14.99874 | J105: Encuadernado | O105: PAPELERIA_LIMA
A106: 2140110614 | B106: Cuad. Grap. T.R. Caligráfico Princess Club Layconsa 80 H | C106: 40000 | D106: 456 | E106: 24 | F106: 19 | G106: WIL001 | H106: 279.7313 | I106: 14.99874 | J106: Encuadernado | O106: PAPELERIA_LIMA
... A177: 2140110632 | B177: Cuad. Grap. Ray. deluxe 92 hj. A4 Layconsa PC | C177: 40000 | D177: 456 | E177: 24 | F177: 19 | G177: WIL001 | H177: 279.7313 | I177: 14.99874 | J177: Encuadernado | O177: PAPELERIA_LIMA
A178: 2310210127 | B178: Plumones LYC School 45 Granel Azul NP P.S. | C178: 50000 | D178: 12 | E178: 12 | F178: 1 | G178: ENS02 | H178: 128.5658 | I178: 11.9658 | J178: Ensamble | K178: 0 | L178: 0 | M178: 0 | O178: ENSAMBLE_LIMA
A179: 2310210128 | B179: Plumones LYC School 45 Granel Negro NP P.S. | C179: 50000 | D179: 12 | E179: 12 | F179: 1 | G179: ENS02 | H179: 128.5658 | I179: 11.9658 | J179: Ensamble | K179: 0 | L179: 0 | M179: 0 | O179: ENSAMBLE_LIMA
A180: 2310210129 | B180: Plumones LYC School 45 Granel Rojo NP P.S. | C180: 50000 | D180: 12 | E180: 12 | F180: 1 | G180: ENS02 | H180: 128.5658 | I180: 11.9658 | J180: Ensamble | K180: 0 | L180: 0 | M180: 0 | O180: ENSAMBLE_LIMA
A181: 2310210130 | B181: Plumones LYC School 45 Granel Verde NP P.S. | C181: 50000 | D181: 12 | E181: 12 | F181: 1 | G181: ENS02 | H181: 128.5658 | I181: 11.9658 | J181: Ensamble | K181: 0 | L181: 0 | M181: 0 | O181: ENSAMBLE_LIMA
A182: 2310210131 | B182: Plumones LYC School 45 Granel Amarillo NP P.S. | C182: 50000 | D182: 12 | E182: 12 | F182: 1 | G182: ENS02 | H182: 128.5658 | I182: 11.9658 | J182: Ensamble | K182: 0 | L182: 0 | M182: 0 | O182: ENSAMBLE_LIMA
A183: 2310210132 | B183: Plumones LYC School 45 Granel Marrón NP P.S. | C183: 50000 | D183: 12 | E183: 12 | F183: 1 | G183: ENS02 | H183: 128.5658 | I183: 11.9658 | J183: Ensamble | K183: 0 | L183: 0 | M183: 0 | O183: ENSAMBLE_LIMA
A184: 2310210133 | B184: Plumones LYC School 45 Granel Anaranjado NP P.S. | C184: 50000 | D184: 12 | E184: 12 | F184: 1 | G184: ENS02 | H184: 128.5658 | I184: 11.9658 | J184: Ensamble | K184: 0 | L184: 0 | M184: 0 | O184: ENSAMBLE_LIMA
A185: 2310210134 | B185: Plumones LYC School 45 Granel Rosado NP P.S. | C185: 50000 | D185: 12 | E185: 12 | F185: 1 | G185: ENS02 | H185: 128.5658 | I185: 11.9658 | J185: Ensamble | K185: 0 | L185: 0 | M185: 0 | O185: ENSAMBLE_LIMA
A186: 2310210135 | B186: Plumones LYC School 45 Granel Violeta NP P.S. | C186: 50000 | D186: 12 | E186: 12 | F186: 1 | G186: ENS02 | H186: 128.5658 | I186: 11.9658 | J186: Ensamble | K186: 0 | L186: 0 | M186: 0 | O186: ENSAMBLE_LIMA
A187: 2310210136 | B187: Plumones LYC School 45 Granel Celeste NP P.S. | C187: 50000 | D187: 12 | E187: 12 | F187: 1 | G187: ENS02 | H187: 128.5658 | I187: 11.9658 | J187: Ensamble | K187: 0 | L187: 0 | M187: 0 | O187: ENSAMBLE_LIMA
A188: 2310210137 | B188: Plumones LYC School 45 Granel Verde Limon NP P.S. | C188: 50000 | D188: 12 | E188: 12 | F188: 1 | G188: ENS02 | H188: 128.5658 | I188: 11.9658 | J188: Ensamble | K188: 0 | L188: 0 | M188: 0 | O188: ENSAMBLE_LIMA
A189: 2310210138 | B189: Plumones LYC School 45 Granel Piel NP P.S. | C189: 50000 | D189: 12 | E189: 12 | F189: 1 | G189: ENS02 | H189: 128.5658 | I189: 11.9658 | J189: Ensamble | K189: 0 | L189: 0 | M189: 0 | O189: ENSAMBLE_LIMA
... A222: 2110030194 | B222: Témpera Puppy Layconsa Fucsia 30cc | C222: 30000 | D222: 48 | E222: 12 | F222: 4 | G222: DOSI_TEMP01 | H222: 159.8419 | I222: 10.94472 | J222: Ensamble | K222: 0 | L222: 0 | M222: 0 | O222: ENSAMBLE_LIMA
A223: 2310190093 | B223: Bolígrafo Layconsa L-033 Medio Amarillo Granel P.S. | C223: 35000 | D223: 24 | E223: 12 | F223: 2 | G223: ENS03 | H223: 15.3382 | I223: 12.0544 | J223: Ensamble | O223: ENSAMBLE_LIMA
A224: 2310190098 | B224: Bolígrafo Layconsa L-033 Medio Anaranjado Granel P.S. | C224: 35000 | D224: 24 | E224: 12 | F224: 2 | G224: ENS03 | H224: 15.3382 | I224: 12.0544 | J224: Ensamble | O224: ENSAMBLE_LIMA
A225: 2310190090 | B225: Bolígrafo Layconsa L-033 Medio Azul Granel P.S. | C225: 35000 | D225: 24 | E225: 12 | F225: 2 | G225: ENS03 | H225: 15.3382 | I225: 12.0544 | J225: Ensamble | O225: ENSAMBLE_LIMA
A226: 2310190094 | B226: Bolígrafo Layconsa L-033 Medio Marron Granel P.S. | C226: 35000 | D226: 24 | E226: 12 | F226: 2 | G226: ENS03 | H226: 15.3382 | I226: 12.0544 | J226: Ensamble | O226: ENSAMBLE_LIMA
A227: 2310190096 | B227: Bolígrafo Layconsa L-033 Medio Morado Granel P.S. | C227: 35000 | D227: 24 | E227: 12 | F227: 2 | G227: ENS03 | H227: 15.3382 | I227: 12.0544 | J227: Ensamble | O227: ENSAMBLE_LIMA
A228: 2310190091 | B228: Bolígrafo Layconsa L-033 Medio Negro Granel P.S. | C228: 35000 | D228: 24 | E228: 12 | F228: 2 | G228: ENS03 | H228: 15.3382 | I228: 12.0544 | J228: Ensamble | O228: ENSAMBLE_LIMA
A229: 2310190089 | B229: Bolígrafo Layconsa L-033 Medio Rojo Granel P.S. | C229: 35000 | D229: 24 | E229: 12 | F229: 2 | G229: ENS03 | H229: 15.3382 | I229: 12.0544 | J229: Ensamble | O229: ENSAMBLE_LIMA
A230: 2310190095 | B230: Bolígrafo Layconsa L-033 Medio Rosado Granel P.S. | C230: 35000 | D230: 24 | E230: 12 | F230: 2 | G230: ENS03 | H230: 15.3382 | I230: 12.0544 | J230: Ensamble | O230: ENSAMBLE_LIMA
A231: 2310190097 | B231: Bolígrafo Layconsa L-033 Medio Turquesa Granel P.S. | C231: 35000 | D231: 24 | E231: 12 | F231: 2 | G231: ENS03 | H231: 15.3382 | I231: 12.0544 | J231: Ensamble | O231: ENSAMBLE_LIMA
A232: 2310190092 | B232: Bolígrafo Layconsa L-033 Medio Verde Granel P.S. | C232: 35000 | D232: 24 | E232: 12 | F232: 2 | G232: ENS03 | H232: 15.3382 | I232: 12.0544 | J232: Ensamble | O232: ENSAMBLE_LIMA
A233: 2310210166 | B233: Marcador Mágico Azul a amarillo Granel P.S. | C233: 25000 | D233: 24 | E233: 12 | F233: 2 | G233: ENS01 | H233: 64.1264 | I233: 10.91894 | J233: Ensamble | K233: 0 | L233: 0 | M233: 0 | O233: ENSAMBLE_LIMA
A234: 2310210164 | B234: Marcador Mágico Azul a Turquesa Granel P.S. | C234: 25000 | D234: 24 | E234: 12 | F234: 2 | G234: ENS01 | H234: 64.1264 | I234: 10.91894 | J234: Ensamble | K234: 0 | L234: 0 | M234: 0 | O234: ENSAMBLE_LIMA
A235: 2310210168 | B235: Marcador Mágico Marrón a Verde Granel P.S. | C235: 25000 | D235: 24 | E235: 12 | F235: 2 | G235: ENS01 | H235: 64.1264 | I235: 10.91894 | J235: Ensamble | K235: 0 | L235: 0 | M235: 0 | O235: ENSAMBLE_LIMA
A236: 2310210162 | B236: Marcador Mágico Naranja a Rosado Granel P.S. | C236: 25000 | D236: 24 | E236: 12 | F236: 2 | G236: ENS01 | H236: 64.1264 | I236: 10.91894 | J236: Ensamble | K236: 0 | L236: 0 | M236: 0 | O236: ENSAMBLE_LIMA
A237: 2310210169 | B237: Marcador Mágico Negro a Rosado Granel P.S. | C237: 25000 | D237: 24 | E237: 12 | F237: 2 | G237: ENS01 | H237: 64.1264 | I237: 10.91894 | J237: Ensamble | K237: 0 | L237: 0 | M237: 0 | O237: ENSAMBLE_LIMA
A238: 2310210165 | B238: Marcador Mágico Verde a Naranja Granel P.S. | C238: 25000 | D238: 24 | E238: 12 | F238: 2 | G238: ENS01 | H238: 64.1264 | I238: 10.91894 | J238: Ensamble | K238: 0 | L238: 0 | M238: 0 | O238: ENSAMBLE_LIMA
A239: 2310210161 | B239: Marcador Mágico Amarillo a Rojo Granel P.S. | C239: 25000 | D239: 24 | E239: 12 | F239: 2 | G239: ENS01 | H239: 64.1264 | I239: 10.91894 | J239: Ensamble | K239: 0 | L239: 0 | M239: 0 | O239: ENSAMBLE_LIMA
A240: 2310210170 | B240: Marcador Mágico Revelador Granel P.S. | C240: 25000 | D240: 24 | E240: 12 | F240: 2 | G240: ENS01 | H240: 64.1264 | I240: 10.91894 | J240: Ensamble | K240: 0 | L240: 0 | M240: 0 | O240: ENSAMBLE_LIMA
A241: 2310210163 | B241: Marcador Mágico Rojo a Amarillo Granel P.S. | C241: 25000 | D241: 24 | E241: 12 | F241: 2 | G241: ENS01 | H241: 64.1264 | I241: 10.91894 | J241: Ensamble | K241: 0 | L241: 0 | M241: 0 | O241: ENSAMBLE_LIMA
A242: 2310210167 | B242: Marcador Mágico Violeta a Rosado Granel P.S. | C242: 25000 | D242: 24 | E242: 12 | F242: 2 | G242: ENS01 | H242: 64.1264 | I242: 10.91894 | J242: Ensamble | K242: 0 | L242: 0 | M242: 0 | O242: ENSAMBLE_LIMA
...

Sheet OP
A1: BELNR_ID | B1: ItemCode | C1: Descripción del artículo | D1: Estado | E1: TYP | F1: WhsCode | G1: NombreAlmacen | H1: Responsable | I1: CantidadOrden | J1: Entregado | K1: Cliente | L1: FechaDocumento | M1: Columna1 | N1: Buscar | O1: Mes Año
A2: 3 | B2: 2310230097 | C2: Frasco Para Témperas 30 cc NP P.S. | D2: CERRADO | E2: ÚTILES_LIMA | F2: ALMA070 | G2: Almacén Producción Inyección | H2: ANGEL | I2: 402000 | J2: 402000 | K2: Frascos Para Témperas 30 cc NP P.S. | L2: 45845 | N2: =IFERROR(VLOOKUP(A2,Ordenes!$C$1:$C$215,1,FALSE),"N/A") -> N/A | O2: =_xlfn.CONCAT(YEAR(OP[[#This Row],[FechaDocumento]]),"-",MONTH(OP[[#This Row],[FechaDocumento]])) -> 2025-7
A3: 4 | B3: 2310090459 | C3: Barril Para Marcador 042 - NP Rojo P.S. | D3: CERRADO | E3: ÚTILES_LIMA | F3: ALMA070 | G3: Almacén Producción Inyección | H3: ANGEL | I3: 128083 | J3: 126900 | K3: Barril Para Marcador 042 - NP Rojo P.S. | L3: 45845 | N3: =IFERROR(VLOOKUP(A3,Ordenes!$C$1:$C$215,1,FALSE),"N/A") -> N/A | O3: =_xlfn.CONCAT(YEAR(OP[[#This Row],[FechaDocumento]]),"-",MONTH(OP[[#This Row],[FechaDocumento]])) -> 2025-7
A4: 5 | B4: 2310090457 | C4: Barril Para Marcador 042 - NP Azul P.S. | D4: CERRADO | E4: ÚTILES_LIMA | F4: ALMA070 | G4: Almacén Producción Inyección | H4: ANGEL | I4: 179861 | J4: 179861 | K4: Barril Para Marcador 042 - NP Azul P.S. | L4: 45845 | N4: =IFERROR(VLOOKUP(A4,Ordenes!$C$1:$C$215,1,FALSE),"N/A") -> N/A | O4: =_xlfn.CONCAT(YEAR(OP[[#This Row],[FechaDocumento]]),"-",MONTH(OP[[#This Row],[FechaDocumento]])) -> 2025-7
A5: 6 | B5: 2310090460 | C5: Barril Para Marcador 042 - NP Verde P.S. | D5: CERRADO | E5: ÚTILES_LIMA | F5: ALMA070 | G5: Almacén Producción Inyección | H5: ANGEL | I5: 193487 | J5: 193220 | K5: Barril Para Marcador 042 - NP Verde P.S. | L5: 45845 | N5: =IFERROR(VLOOKUP(A5,Ordenes!$C$1:$C$215,1,FALSE),"N/A") -> N/A | O5: =_xlfn.CONCAT(YEAR(OP[[#This Row],[FechaDocumento]]),"-",MONTH(OP[[#This Row],[FechaDocumento]])) -> 2025-7
A6: 7 | B6: 2310090448 | C6: Barril Para Plumón 045 - NP Celeste | D6: CERRADO | E6: ÚTILES_LIMA | F6: ALMA070 | G6: Almacén Producción Inyección | H6: ANGEL | I6: 196272 | J6: 196272 | K6: Barril Para Plumón 045 - NP Celeste | L6: 45845 | N6: =IFERROR(VLOOKUP(A6,Ordenes!$C$1:$C$215,1,FALSE),"N/A") -> N/A | O6: =_xlfn.CONCAT(YEAR(OP[[#This Row],[FechaDocumento]]),"-",MONTH(OP[[#This Row],[FechaDocumento]])) -> 2025-7
A7: 8 | B7: 2310090445 | C7: Barril Para Plumón 045 - NP Verde Claro | D7: CERRADO | E7: ÚTILES_LIMA | F7: ALMA070 | G7: Almacén Producción Inyección | H7: ANGEL | I7: 196272 | J7: 194800 | K7: Barril Para Plumón 045 - NP Verde Claro | L7: 45845 | N7: =IFERROR(VLOOKUP(A7,Ordenes!$C$1:$C$215,1,FALSE),"N/A") -> N/A | O7: =_xlfn.CONCAT(YEAR(OP[[#This Row],[FechaDocumento]]),"-",MONTH(OP[[#This Row],[FechaDocumento]])) -> 2025-7
A8: 9 | B8: 2310090442 | C8: Barril Para Plumón 045 - NP Verde | D8: CERRADO | E8: ÚTILES_LIMA | F8: ALMA070 | G8: Almacén Producción Inyección | H8: ANGEL | I8: 196272 | J8: 196800 | K8: Barril Para Plumón 045 - NP Verde | L8: 45845 | N8: =IFERROR(VLOOKUP(A8,Ordenes!$C$1:$C$215,1,FALSE),"N/A") -> N/A | O8: =_xlfn.CONCAT(YEAR(OP[[#This Row],[FechaDocumento]]),"-",MONTH(OP[[#This Row],[FechaDocumento]])) -> 2025-7
A9: 10 | B9: 2310230002 | C9: Frasco Para Témperas 30 cc P.S. | D9: CERRADO | E9: ÚTILES_LIMA | F9: ALMA070 | G9: Almacén Producción Inyección | H9: ANGEL | I9: 600606 | J9: 594000 | K9: Frascos Para Témperas P.S. | L9: 45845 | N9: =IFERROR(VLOOKUP(A9,Ordenes!$C$1:$C$215,1,FALSE),"N/A") -> N/A | O9: =_xlfn.CONCAT(YEAR(OP[[#This Row],[FechaDocumento]]),"-",MONTH(OP[[#This Row],[FechaDocumento]])) -> 2025-7
A10: 11 | B10: 2310160476 | C10: Tapa Para Plumón 045 - NP Anaranjado | D10: CERRADO | E10: ÚTILES_LIMA | F10: ALMA070 | G10: Almacén Producción Inyección | H10: ANGEL | I10: 212548 | J10: 212550 | K10: Tapa Para Plumón 045 - NP Anaranjado | L10: 45845 | N10: =IFERROR(VLOOKUP(A10,Ordenes!$C$1:$C$215,1,FALSE),"N/A") -> N/A | O10: =_xlfn.CONCAT(YEAR(OP[[#This Row],[FechaDocumento]]),"-",MONTH(OP[[#This Row],[FechaDocumento]])) -> 2025-7
A11: 12 | B11: 2310160469 | C11: Tapa Para Plumón 045 - NP Rojo | D11: CERRADO | E11: ÚTILES_LIMA | F11: ALMA070 | G11: Almacén Producción Inyección | H11: ANGEL | I11: 173736 | J11: 173736 | K11: Tapa Para Plumón 045 - NP Rojo | L11: 45845 | N11: =IFERROR(VLOOKUP(A11,Ordenes!$C$1:$C$215,1,FALSE),"N/A") -> N/A | O11: =_xlfn.CONCAT(YEAR(OP[[#This Row],[FechaDocumento]]),"-",MONTH(OP[[#This Row],[FechaDocumento]])) -> 2025-7
A12: 13 | B12: 2310160471 | C12: Tapa Para Plumón 045 - NP Verde | D12: CERRADO | E12: ÚTILES_LIMA | F12: ALMA070 | G12: Almacén Producción Inyección | H12: ANGEL | I12: 222000 | J12: 224000 | K12: Tapa Para Plumón 045 - NP Verde | L12: 45845 | N12: =IFERROR(VLOOKUP(A12,Ordenes!$C$1:$C$215,1,FALSE),"N/A") -> N/A | O12: =_xlfn.CONCAT(YEAR(OP[[#This Row],[FechaDocumento]]),"-",MONTH(OP[[#This Row],[FechaDocumento]])) -> 2025-7
A13: 14 | B13: 2310160539 | C13: Tapa Base Dosificador P/Cola Rojo paleta P.S. | D13: CERRADO | E13: ÚTILES_LIMA | F13: ALMA070 | G13: Almacén Producción Inyección | H13: ANGEL | I13: 225684 | J13: 0 | K13: Tapa Base Dosificador Rojo paleta P.S. | L13: 45845 | N13: =IFERROR(VLOOKUP(A13,Ordenes!$C$1:$C$215,1,FALSE),"N/A") -> N/A | O13: =_xlfn.CONCAT(YEAR(OP[[#This Row],[FechaDocumento]]),"-",MONTH(OP[[#This Row],[FechaDocumento]])) -> 2025-7
... A321: 462 | B321: 2140110657 | C321: Cuad. Grap. Ray. Sweet Layconsa 80 H | D321: CERRADO | E321: CUADERNOS_LIMA | F321: ALMA073 | G321: Almacén Producción Cuadernos | H321: BERNARDO | I321: 1500 | J321: 0 | K321: disponible | L321: 45870 | N321: =IFERROR(VLOOKUP(A321,Ordenes!$C$1:$C$215,1,FALSE),"N/A") -> N/A | O321: =_xlfn.CONCAT(YEAR(OP[[#This Row],[FechaDocumento]]),"-",MONTH(OP[[#This Row],[FechaDocumento]])) -> 2025-8
A322: 466 | D322: CERRADO | E322: CUADERNOS_LIMA | H322: SIN RESPONSABLE | I322: 0 | J322: 0 | K322: Cuad. Grap. Ray. Kawaii Layconsa 80 H. | L322: 45870 | N322: =IFERROR(VLOOKUP(A322,Ordenes!$C$1:$C$215,1,FALSE),"N/A") -> N/A | O322: =_xlfn.CONCAT(YEAR(OP[[#This Row],[FechaDocumento]]),"-",MONTH(OP[[#This Row],[FechaDocumento]])) -> 2025-8
A323: 467 | B323: 2140110658 | C323: Cuad. Grap. Ray. Mandalas Layconsa 80 H | D323: CERRADO | E323: CUADERNOS_LIMA | F323: ALMA073 | G323: Almacén Producción Cuadernos | H323: BERNARDO | I323: 4500 | J323: 4525 | K323: Cuad. Grap. Ray. Mandalas Layconsa 80 H | L323: 45870 | N323: =IFERROR(VLOOKUP(A323,Ordenes!$C$1:$C$215,1,FALSE),"N/A") -> N/A | O323: =_xlfn.CONCAT(YEAR(OP[[#This Row],[FechaDocumento]]),"-",MONTH(OP[[#This Row],[FechaDocumento]])) -> 2025-8
A324: 468 | B324: 2140110661 | C324: Cuad. Grap. Ray. Fast Racer Layconsa 80 H | D324: CERRADO | E324: CUADERNOS_LIMA | F324: ALMA073 | G324: Almacén Producción Cuadernos | H324: BERNARDO | I324: 10000 | J324: 10026 | K324: Cuad. Grap. Ray. Fast Racer Layconsa 80 H | L324: 45870 | N324: =IFERROR(VLOOKUP(A324,Ordenes!$C$1:$C$215,1,FALSE),"N/A") -> N/A | O324: =_xlfn.CONCAT(YEAR(OP[[#This Row],[FechaDocumento]]),"-",MONTH(OP[[#This Row],[FechaDocumento]])) -> 2025-8
A325: 470 | B325: 2140110613 | C325: Cuad. Grap. Cuadr. Princess Club Layconsa 80 H | D325: CERRADO | E325: CUADERNOS_LIMA | F325: ALMA073 | G325: Almacén Producción Cuadernos | H325: BERNARDO | I325: 59000 | J325: 59175 | K325: Cuad. Grap. Cuadr. Princess Club Layconsa 80 H | L325: 45870 | N325: =IFERROR(VLOOKUP(A325,Ordenes!$C$1:$C$215,1,FALSE),"N/A") -> N/A | O325: =_xlfn.CONCAT(YEAR(OP[[#This Row],[FechaDocumento]]),"-",MONTH(OP[[#This Row],[FechaDocumento]])) -> 2025-8
A326: 471 | B326: 2140110615 | C326: Cuad. Grap. Cuadr. Unicornios Layconsa 80 H | D326: CERRADO | E326: CUADERNOS_LIMA | F326: ALMA073 | G326: Almacén Producción Cuadernos | H326: BERNARDO | I326: 24500 | J326: 24525 | K326: Cuad. Grap. Cuadr. Unicornios Layconsa 80 H | L326: 45870 | N326: =IFERROR(VLOOKUP(A326,Ordenes!$C$1:$C$215,1,FALSE),"N/A") -> N/A | O326: =_xlfn.CONCAT(YEAR(OP[[#This Row],[FechaDocumento]]),"-",MONTH(OP[[#This Row],[FechaDocumento]])) -> 2025-8
A327: 472 | B327: 2310040547 | C327: Formado Crayón Jumbo LYC Rojo | D327: CERRADO | E327: ÚTILES_LIMA | F327: ALMA072 | G327: Almacén Producción Masas y Tintas | H327: MATIAS | I327: 25000 | J327: 18254 | K327: Formado Crayón Jumbo LYC Rojo | L327: 45873 | N327: =IFERROR(VLOOKUP(A327,Ordenes!$C$1:$C$215,1,FALSE),"N/A") -> N/A | O327: =_xlfn.CONCAT(YEAR(OP[[#This Row],[FechaDocumento]]),"-",MONTH(OP[[#This Row],[FechaDocumento]])) -> 2025-8
A328: 473 | B328: 2310040548 | C328: Formado Crayón Jumbo LYC Amarillo | D328: CERRADO | E328: ÚTILES_LIMA | F328: ALMA072 | G328: Almacén Producción Masas y Tintas | H328: MATIAS | I328: 25000 | J328: 29970 | K328: Formado Crayón Jumbo LYC Amarillo | L328: 45873 | N328: =IFERROR(VLOOKUP(A328,Ordenes!$C$1:$C$215,1,FALSE),"N/A") -> N/A | O328: =_xlfn.CONCAT(YEAR(OP[[#This Row],[FechaDocumento]]),"-",MONTH(OP[[#This Row],[FechaDocumento]])) -> 2025-8
A329: 474 | B329: 2310040549 | C329: Formado Crayón Jumbo LYC Blanco | D329: CERRADO | E329: ÚTILES_LIMA | F329: ALMA072 | G329: Almacén Producción Masas y Tintas | H329: MATIAS | I329: 25000 | J329: 26253 | K329: Formado Crayón Jumbo LYC Blanco | L329: 45873 | N329: =IFERROR(VLOOKUP(A329,Ordenes!$C$1:$C$215,1,FALSE),"N/A") -> N/A | O329: =_xlfn.CONCAT(YEAR(OP[[#This Row],[FechaDocumento]]),"-",MONTH(OP[[#This Row],[FechaDocumento]])) -> 2025-8
A330: 475 | B330: 2310040550 | C330: Formado Crayón Jumbo LYC Anaranjado | D330: CERRADO | E330: ÚTILES_LIMA | F330: ALMA072 | G330: Almacén Producción Masas y Tintas | H330: MATIAS | I330: 25000 | J330: 27114 | K330: Formado Crayón Jumbo LYC Anaranjado | L330: 45873 | N330: =IFERROR(VLOOKUP(A330,Ordenes!$C$1:$C$215,1,FALSE),"N/A") -> N/A | O330: =_xlfn.CONCAT(YEAR(OP[[#This Row],[FechaDocumento]]),"-",MONTH(OP[[#This Row],[FechaDocumento]])) -> 2025-8
A331: 476 | B331: 2310040551 | C331: Formado Crayón Jumbo LYC Verde Claro | D331: CERRADO | E331: ÚTILES_LIMA | F331: ALMA072 | G331: Almacén Producción Masas y Tintas | H331: MATIAS | I331: 25000 | J331: 27573 | K331: Formado Crayón Jumbo LYC Verde Claro | L331: 45873 | N331: =IFERROR(VLOOKUP(A331,Ordenes!$C$1:$C$215,1,FALSE),"N/A") -> N/A | O331: =_xlfn.CONCAT(YEAR(OP[[#This Row],[FechaDocumento]]),"-",MONTH(OP[[#This Row],[FechaDocumento]])) -> 2025-8
A332: 477 | B332: 2310040552 | C332: Formado Crayón Jumbo LYC Verde Oscuro | D332: CERRADO | E332: ÚTILES_LIMA | F332: ALMA072 | G332: Almacén Producción Masas y Tintas | H332: MATIAS | I332: 25000 | J332: 27133 | K332: Formado Crayón Jumbo LYC Verde Oscuro | L332: 45873 | N332: =IFERROR(VLOOKUP(A332,Ordenes!$C$1:$C$215,1,FALSE),"N/A") -> N/A | O332: =_xlfn.CONCAT(YEAR(OP[[#This Row],[FechaDocumento]]),"-",MONTH(OP[[#This Row],[FechaDocumento]])) -> 2025-8
A333: 478 | B333: 2310040553 | C333: Formado Crayón Jumbo LYC Celeste | D333: CERRADO | E333: ÚTILES_LIMA | F333: ALMA072 | G333: Almacén Producción Masas y Tintas | H333: MATIAS | I333: 25000 | J333: 26931 | K333: Formado Crayón Jumbo LYC Celeste | L333: 45873 | N333: =IFERROR(VLOOKUP(A333,Ordenes!$C$1:$C$215,1,FALSE),"N/A") -> N/A | O333: =_xlfn.CONCAT(YEAR(OP[[#This Row],[FechaDocumento]]),"-",MONTH(OP[[#This Row],[FechaDocumento]])) -> 2025-8
A334: 479 | B334: 2310040554 | C334: Formado Crayón Jumbo LYC Azul | D334: CERRADO | E334: ÚTILES_LIMA | F334: ALMA072 | G334: Almacén Producción Masas y Tintas | H334: MATIAS | I334: 25000 | J334: 27052 | K334: Formado Crayón Jumbo LYC Azul | L334: 45873 | N334: =IFERROR(VLOOKUP(A334,Ordenes!$C$1:$C$215,1,FALSE),"N/A") -> N/A | O334: =_xlfn.CONCAT(YEAR(OP[[#This Row],[FechaDocumento]]),"-",MONTH(OP[[#This Row],[FechaDocumento]])) -> 2025-8
... A1308: 1831 | B1308: 2310090491 | C1308: Barril Para Marcador LYC Serigrafiado 047 - MK Azul Imp. Blanco | D1308: CERRADO | E1308: ÚTILES_LIMA | F1308: ALMA071 | G1308: Almacén Producción Ensamble | H1308: ISAIAS | I1308: 20000 | J1308: 21420 | K1308: Barril Para Marcador LYC Serigrafiado 047 - MK Azul Imp. Blanco | L1308: 45957 | N1308: =IFERROR(VLOOKUP(A1308,Ordenes!$C$1:$C$215,1,FALSE),"N/A") -> N/A | O1308: =_xlfn.CONCAT(YEAR(OP[[#This Row],[FechaDocumento]]),"-",MONTH(OP[[#This Row],[FechaDocumento]])) -> 2025-10
A1309: 1832 | D1309: CERRADO | E1309: CUADERNOS_LIMA | H1309: SIN RESPONSABLE | I1309: 0 | J1309: 0 | K1309: Cuad. Grap. 1x1 c/mco rojo 80 H. Layconsa Puppy | L1309: 45957 | N1309: =IFERROR(VLOOKUP(A1309,Ordenes!$C$1:$C$215,1,FALSE),"N/A") -> N/A | O1309: =_xlfn.CONCAT(YEAR(OP[[#This Row],[FechaDocumento]]),"-",MONTH(OP[[#This Row],[FechaDocumento]])) -> 2025-10
A1310: 1833 | B1310: 2110210003 | C1310: Folder Layconsa A4 Cut Pets c/Fastener colores surtidos | D1310: CERRADO | E1310: ÚTILES_LIMA | F1310: ALMA071 | G1310: Almacén Producción Ensamble | H1310: ISAIAS | I1310: 4000 | J1310: 3988 | K1310: Folder Layconsa A4 Cut Pets c/Fastener colores surtidos | L1310: 45957 | N1310: =IFERROR(VLOOKUP(A1310,Ordenes!$C$1:$C$215,1,FALSE),"N/A") -> N/A | O1310: =_xlfn.CONCAT(YEAR(OP[[#This Row],[FechaDocumento]]),"-",MONTH(OP[[#This Row],[FechaDocumento]])) -> 2025-10
A1311: 1834 | B1311: 2110210004 | C1311: Folder Layconsa A4 Kawaii c/Fastener colores surtidos | D1311: CERRADO | E1311: ÚTILES_LIMA | F1311: ALMA071 | G1311: Almacén Producción Ensamble | H1311: ISAIAS | I1311: 2500 | J1311: 2500 | K1311: Folder Layconsa A4 Kawaii c/Fastener colores surtidos | L1311: 45957 | N1311: =IFERROR(VLOOKUP(A1311,Ordenes!$C$1:$C$215,1,FALSE),"N/A") -> N/A | O1311: =_xlfn.CONCAT(YEAR(OP[[#This Row],[FechaDocumento]]),"-",MONTH(OP[[#This Row],[FechaDocumento]])) -> 2025-10
A1312: 1835 | B1312: 2110210006 | C1312: Folder Layconsa A4 Unicorns c/Fastener colores surtidos | D1312: CERRADO | E1312: ÚTILES_LIMA | F1312: ALMA071 | G1312: Almacén Producción Ensamble | H1312: ISAIAS | I1312: 1500 | J1312: 1497 | K1312: Folder Layconsa A4 Unicorns c/Fastener colores surtidos | L1312: 45957 | N1312: =IFERROR(VLOOKUP(A1312,Ordenes!$C$1:$C$215,1,FALSE),"N/A") -> N/A | O1312: =_xlfn.CONCAT(YEAR(OP[[#This Row],[FechaDocumento]]),"-",MONTH(OP[[#This Row],[FechaDocumento]])) -> 2025-10
A1313: 1836 | B1313: 2110210009 | C1313: Folder Layconsa A4 Pre-Escolar Niña c/Fastener colores surtidos | D1313: CERRADO | E1313: ÚTILES_LIMA | F1313: ALMA071 | G1313: Almacén Producción Ensamble | H1313: ISAIAS | I1313: 2000 | J1313: 1996 | K1313: Folder Layconsa A4 Pre-Escolar Niña c/Fastener colores surtidos | L1313: 45957 | N1313: =IFERROR(VLOOKUP(A1313,Ordenes!$C$1:$C$215,1,FALSE),"N/A") -> N/A | O1313: =_xlfn.CONCAT(YEAR(OP[[#This Row],[FechaDocumento]]),"-",MONTH(OP[[#This Row],[FechaDocumento]])) -> 2025-10
A1314: 1837 | B1314: 2110210025 | C1314: Folder Layconsa A4 Femenino c/Fastener colores y diseños surtidos | D1314: CERRADO | E1314: ÚTILES_LIMA | F1314: ALMA071 | G1314: Almacén Producción Ensamble | H1314: ISAIAS | I1314: 4492 | J1314: 4492 | K1314: Folder Layconsa A4 Femenino c/Fastener colores y diseños surtidos | L1314: 45957 | N1314: =IFERROR(VLOOKUP(A1314,Ordenes!$C$1:$C$215,1,FALSE),"N/A") -> N/A | O1314: =_xlfn.CONCAT(YEAR(OP[[#This Row],[FechaDocumento]]),"-",MONTH(OP[[#This Row],[FechaDocumento]])) -> 2025-10
A1315: 1838 | B1315: 2110210010 | C1315: Folder Layconsa Oficio Cut Pets c/Fastener colores surtidos | D1315: CERRADO | E1315: ÚTILES_LIMA | F1315: ALMA071 | G1315: Almacén Producción Ensamble | H1315: ISAIAS | I1315: 2000 | J1315: 1996 | K1315: Folder Layconsa Oficio Cut Pets c/Fastener colores surtidos | L1315: 45957 | N1315: =IFERROR(VLOOKUP(A1315,Ordenes!$C$1:$C$215,1,FALSE),"N/A") -> N/A | O1315: =_xlfn.CONCAT(YEAR(OP[[#This Row],[FechaDocumento]]),"-",MONTH(OP[[#This Row],[FechaDocumento]])) -> 2025-10
A1316: 1839 | B1316: 2110210011 | C1316: Folder Layconsa Oficio Kawaii c/Fastener colores surtidos | D1316: CERRADO | E1316: ÚTILES_LIMA | F1316: ALMA071 | G1316: Almacén Producción Ensamble | H1316: ISAIAS | I1316: 3000 | J1316: 2989 | K1316: Folder Layconsa Oficio Kawaii c/Fastener colores surtidos | L1316: 45957 | N1316: =IFERROR(VLOOKUP(A1316,Ordenes!$C$1:$C$215,1,FALSE),"N/A") -> N/A | O1316: =_xlfn.CONCAT(YEAR(OP[[#This Row],[FechaDocumento]]),"-",MONTH(OP[[#This Row],[FechaDocumento]])) -> 2025-10
A1317: 1840 | B1317: 2110210012 | C1317: Folder Layconsa Oficio Princess c/Fastener colores surtidos | D1317: CERRADO | E1317: ÚTILES_LIMA | F1317: ALMA071 | G1317: Almacén Producción Ensamble | H1317: ISAIAS | I1317: 1000 | J1317: 998 | K1317: Folder Layconsa Oficio Princess c/Fastener colores surtidos | L1317: 45957 | N1317: =IFERROR(VLOOKUP(A1317,Ordenes!$C$1:$C$215,1,FALSE),"N/A") -> N/A | O1317: =_xlfn.CONCAT(YEAR(OP[[#This Row],[FechaDocumento]]),"-",MONTH(OP[[#This Row],[FechaDocumento]])) -> 2025-10
A1318: 1841 | B1318: 2110210013 | C1318: Folder Layconsa Oficio Unicorns c/Fastener colores surtidos | D1318: CERRADO | E1318: ÚTILES_LIMA | F1318: ALMA071 | G1318: Almacén Producción Ensamble | H1318: ISAIAS | I1318: 2000 | J1318: 1995 | K1318: Folder Layconsa Oficio Unicorns c/Fastener colores surtidos | L1318: 45957 | N1318: =IFERROR(VLOOKUP(A1318,Ordenes!$C$1:$C$215,1,FALSE),"N/A") -> N/A | O1318: =_xlfn.CONCAT(YEAR(OP[[#This Row],[FechaDocumento]]),"-",MONTH(OP[[#This Row],[FechaDocumento]])) -> 2025-10
A1319: 1842 | B1319: 2110210014 | C1319: Folder Layconsa Oficio Sweet c/Fastener colores surtidos | D1319: CERRADO | E1319: ÚTILES_LIMA | F1319: ALMA071 | G1319: Almacén Producción Ensamble | H1319: ISAIAS | I1319: 2000 | J1319: 1493 | K1319: Folder Layconsa Oficio Sweet c/Fastener colores surtidos | L1319: 45957 | N1319: =IFERROR(VLOOKUP(A1319,Ordenes!$C$1:$C$215,1,FALSE),"N/A") -> N/A | O1319: =_xlfn.CONCAT(YEAR(OP[[#This Row],[FechaDocumento]]),"-",MONTH(OP[[#This Row],[FechaDocumento]])) -> 2025-10
A1320: 1843 | B1320: 2110210015 | C1320: Folder Layconsa Oficio Madala c/Fastener colores surtidos | D1320: CERRADO | E1320: ÚTILES_LIMA | F1320: ALMA071 | G1320: Almacén Producción Ensamble | H1320: ISAIAS | I1320: 2000 | J1320: 1988 | K1320: Folder Layconsa Oficio Madala c/Fastener colores surtidos | L1320: 45957 | N1320: =IFERROR(VLOOKUP(A1320,Ordenes!$C$1:$C$215,1,FALSE),"N/A") -> N/A | O1320: =_xlfn.CONCAT(YEAR(OP[[#This Row],[FechaDocumento]]),"-",MONTH(OP[[#This Row],[FechaDocumento]])) -> 2025-10
A1321: 1844 | B1321: 2110210016 | C1321: Folder Layconsa Oficio Pre-Escolar Niña c/Fastener colores surtidos | D1321: CERRADO | E1321: ÚTILES_LIMA | F1321: ALMA071 | G1321: Almacén Producción Ensamble | H1321: ISAIAS | I1321: 3000 | J1321: 2991 | K1321: Folder Layconsa Oficio Pre-Escolar Niña c/Fastener colores surtidos | L1321: 45957 | N1321: =IFERROR(VLOOKUP(A1321,Ordenes!$C$1:$C$215,1,FALSE),"N/A") -> N/A | O1321: =_xlfn.CONCAT(YEAR(OP[[#This Row],[FechaDocumento]]),"-",MONTH(OP[[#This Row],[FechaDocumento]])) -> 2025-10
... A3029: 4323 | B3029: 2110040047 | C3029: Crayón triangular cj. cartón Layconsa Puppy Jumbo x 12 | D3029: ABIERTO | E3029: ÚTILES_LIMA | F3029: ALMA071 | G3029: Almacén Producción Ensamble | H3029: ISAIAS | I3029: 10000 | J3029: 0 | K3029: Crayón triangular cj. cartón Layconsa Puppy Jumbo x 12 | L3029: 46163 | N3029: =IFERROR(VLOOKUP(A3029,Ordenes!$C$1:$C$215,1,FALSE),"N/A") -> N/A | O3029: =_xlfn.CONCAT(YEAR(OP[[#This Row],[FechaDocumento]]),"-",MONTH(OP[[#This Row],[FechaDocumento]])) -> 2026-5

Sheet BOM
A1: Código LYC | B1: Posición | C1: Descripción | D1: Und LYC | E1: Qty | F1: Ceco | G1: Componente | H1: Descripción | I1: Und LYC 2 | J1: Qty 2
A2: 2000050591 | B2: 10 | C2: 03 Bolígrafos retráctil Roll click L-64 Layconsa az/ng/rj Blister | D2: BLx1 | E2: 12000 | F2: Blister | G2: 2000050592 | H2: Bolígrafo retráctil Roll click L-64 azul Layconsa | I2: PZ/1 | J2: 1500
A3: 2000050591 | B3: 20 | C3: 03 Bolígrafos retráctil Roll click L-64 Layconsa az/ng/rj Blister | D3: BLx1 | E3: 12000 | F3: Blister | G3: 2000050593 | H3: Bolígrafo retráctil Roll click L-64 negro Layconsa | I3: PZ/1 | J3: 1500
A4: 2000050591 | B4: 30 | C4: 03 Bolígrafos retráctil Roll click L-64 Layconsa az/ng/rj Blister | D4: BLx1 | E4: 12000 | F4: Blister | G4: 2000050594 | H4: Bolígrafo retráctil Roll click L-64 rojo Layconsa | I4: PZ/1 | J4: 1500
A5: 2000050591 | B5: 40 | C5: 03 Bolígrafos retráctil Roll click L-64 Layconsa az/ng/rj Blister | D5: BLx1 | E5: 12000 | F5: Blister | G5: 2320071496 | H5: Respaldo 03 Bolígrafos retráctil Roll click L-64 LYC az/ng/rj Blister | I5: PZ/1 | J5: 1520
A6: 2000050591 | B6: 50 | C6: 03 Bolígrafos retráctil Roll click L-64 Layconsa az/ng/rj Blister | D6: BLx1 | E6: 12000 | F6: Blister | G6: 2500030045 | H6: Cajón C/I 51.5x29.5x22.5 cm (LYC) pote cola sintética x 220 gr | I6: PZ/1 | J6: 13
A7: 2000050591 | B7: 60 | C7: 03 Bolígrafos retráctil Roll click L-64 Layconsa az/ng/rj Blister | D7: BLx1 | E7: 12000 | F7: Blister | G7: 2500150007 | H7: Cinta embalaje transparente 45 mc x 2" x 100 mt | I7: ROLL/1 | J7: 2
A8: 2000050591 | B8: 70 | C8: 03 Bolígrafos retráctil Roll click L-64 Layconsa az/ng/rj Blister | D8: BLx1 | E8: 12000 | F8: Blister | G8: 2500150004 | H8: Cinta Adh Transparente 3/4 x 72 Yds. - Planta | I8: PZ/1 | J8: 1
A9: 2000050591 | B9: 80 | C9: 03 Bolígrafos retráctil Roll click L-64 Layconsa az/ng/rj Blister | D9: BLx1 | E9: 12000 | F9: Blister | G9: 2500090065 | H9: Bolsa Para Blíster de 10x15x1 | I9: PZ/1 | J9: 250
A10: 2000050597 | B10: 10 | C10: 03 Bolígrafos retráctil Gelly click L-61 Layconsa az/ng/rj Blister | D10: BLx1 | E10: 12000 | F10: Blister | G10: 2000050588 | H10: Bolígrafo retráctil gelly click L-61 azul Layconsa | I10: PZ/1 | J10: 1500
A11: 2000050597 | B11: 20 | C11: 03 Bolígrafos retráctil Gelly click L-61 Layconsa az/ng/rj Blister | D11: BLx1 | E11: 12000 | F11: Blister | G11: 2000050589 | H11: Bolígrafo retráctil gelly click L-61 negro Layconsa | I11: PZ/1 | J11: 1500
A12: 2000050597 | B12: 30 | C12: 03 Bolígrafos retráctil Gelly click L-61 Layconsa az/ng/rj Blister | D12: BLx1 | E12: 12000 | F12: Blister | G12: 2000050590 | H12: Bolígrafo retráctil gelly click L-61 rojo Layconsa | I12: PZ/1 | J12: 1500
A13: 2000050597 | B13: 40 | C13: 03 Bolígrafos retráctil Gelly click L-61 Layconsa az/ng/rj Blister | D13: BLx1 | E13: 12000 | F13: Blister | G13: 2320071495 | H13: Respaldo 03 Bolígrafos retráctil Gelly click L-61 LYC az/ng/rj Blister | I13: PZ/1 | J13: 1520
... A728: 2110100139 | B728: 70 | C728: Tinta Para Marcador de Pizarra Layconsa L-126 Verde | D728: PZ/1 | E728: 12000 | F728: Ensamblado - Marcador | G728: 2410110088 | H728: Tinta Pizarra Verde WB 7339.1 | I728: KL/1000 | J728: 336
A729: 2110100225 | B729: 10 | C729: 02 Bol.TRIPLUS (azu/roj)+01 Resaltador neón amarillo+01 Corrector Líquido 9ml | D729: BLx1 | E729: 1000 | G729: 2000050601 | H729: Bolígrafo TRIPLUS L-35F azul Presentacion 50 Layconsa | I729: PZ/1 | J729: 1000
A730: 2110100225 | B730: 20 | C730: 02 Bol.TRIPLUS (azu/roj)+01 Resaltador neón amarillo+01 Corrector Líquido 9ml | D730: BLx1 | E730: 1000 | G730: 2000050603 | H730: Bolígrafo TRIPLUS L-35F rojo Presentacion 50 Layconsa | I730: PZ/1 | J730: 1000
A731: 2110100225 | B731: 30 | C731: 02 Bol.TRIPLUS (azu/roj)+01 Resaltador neón amarillo+01 Corrector Líquido 9ml | D731: BLx1 | E731: 1000 | G731: 2000070139 | H731: Resaltador Layconsa L-48 Amarillo | I731: PZ/1 | J731: 1000
A732: 2110100225 | B732: 40 | C732: 02 Bol.TRIPLUS (azu/roj)+01 Resaltador neón amarillo+01 Corrector Líquido 9ml | D732: BLx1 | E732: 1000 | G732: 2000150041 | H732: Corrector Líquido ergonómico Layconsa 9ml | I732: PZ/1 | J732: 1000
A733: 2110100225 | B733: 50 | C733: 02 Bol.TRIPLUS (azu/roj)+01 Resaltador neón amarillo+01 Corrector Líquido 9ml | D733: BLx1 | E733: 1000 | G733: 2320071524 | H733: Respaldo 02 Bol.TRIPLUS (azu/roj)+01 Resaltador amarillo+01 Corrector 9ml | I733: PZ/1 | J733: 1000
A734: 2110100225 | B734: 60 | C734: 02 Bol.TRIPLUS (azu/roj)+01 Resaltador neón amarillo+01 Corrector Líquido 9ml | D734: BLx1 | E734: 1000 | G734: 2500090065 | H734: Bolsa Para Blíster de 10x15x1 | I734: PZ/1 | J734: 100
A735: 2110100225 | B735: 70 | C735: 02 Bol.TRIPLUS (azu/roj)+01 Resaltador neón amarillo+01 Corrector Líquido 9ml | D735: BLx1 | E735: 1000 | G735: 2500030226 | H735: Cajón Para Plumones LYC School 45x12pz 34x31x36.00cm | I735: PZ/1 | J735: 10
A736: 2110100225 | B736: 80 | C736: 02 Bol.TRIPLUS (azu/roj)+01 Resaltador neón amarillo+01 Corrector Líquido 9ml | D736: BLx1 | E736: 1000 | G736: 2500150004 | H736: Cinta Adh Transparente 3/4 x 72 Yds. - Planta | I736: PZ/1 | J736: 1
A737: 2110100225 | B737: 90 | C737: 02 Bol.TRIPLUS (azu/roj)+01 Resaltador neón amarillo+01 Corrector Líquido 9ml | D737: BLx1 | E737: 1000 | G737: 2500150007 | H737: Cinta embalaje transparente 45 mc x 2" x 100 mt | I737: ROLL/1 | J737: 0.25
A738: 2110100227 | B738: 10 | C738: 01 Tijera escolar + 01 Silicona de 100 ml. | D738: BLx1 | E738: 1650 | F738: Blister | G738: 2000630065 | H738: Tijera Escolar Layconsa 5" Colores surtidos | I738: PZ/1 | J738: 1650
A739: 2110100227 | B739: 20 | C739: 01 Tijera escolar + 01 Silicona de 100 ml. | D739: BLx1 | E739: 1650 | F739: Blister | G739: 2000020080 | H739: Pegamento Silicona Líquida de 100ml | I739: PZ/1 | J739: 1650
A740: 2110100227 | B740: 30 | C740: 01 Tijera escolar + 01 Silicona de 100 ml. | D740: BLx1 | E740: 1650 | F740: Blister | G740: 2500030019 | H740: Cajón 205 C/I 33.0x22.7x17cm (LYC) cola sintetica c/aplicador x 250 gr | I740: PZ/1 | J740: 70
